Workbook

Sheet Summary
A1: Minnesota Specialist Clinics
A2: Every organization registered in the federal NPI Registry (CMS) under these specialties with a Minnesota practice address, its own name and a phone number. Pulled September 24, 2026. TMJ specialists and oral surgeons added October 19, 2026, each one checked on the web.
A4: =COUNTA('All Clinics'!$A:$A)-1 -> 953 | C4: =COUNTIF('All Clinics'!$M:$M,"No") -> 890
A5: clinic locations across Minnesota | C5: of them are not on Xpert Connect yet
A6: ="Plus "&TEXT(COUNTA('Older Entries'!$A:$A)-1,"#,##0")&" older registry entries on the 'Older Entries' sheet: clinics that have not updated their federal registration since before 2022. Call to confirm before using them." -> Plus 2,081 older registry entries on the 'Older Entries' sheet: clinics that have not updated their federal registration since before 2022. Call to confirm before using them.
A8: By specialty group
A9: Group | B9: Clinics | C9: Not on Xpert Connect | D9: Older entries | E9: What it includes
A10: Injury Physicians | B10: =COUNTA('Injury Physicians'!$A:$A)-1 -> 153 | C10: =COUNTIF('Injury Physicians'!$M:$M,"No") -> 96 | D10: =COUNTIF('Older Entries'!$B:$B,"Injury Physicians")+COUNTIF('Older Entries'!$C:$C,"*Injury Physicians*") -> 160 | E10: Orthopedics, spine, sports medicine, neurosurgery, pain, PM&R, neurology
A11: Chiropractic | B11: =COUNTA('Chiropractic'!$A:$A)-1 -> 440 | C11: =COUNTIF('Chiropractic'!$M:$M,"No") -> 439 | D11: =COUNTIF('Older Entries'!$B:$B,"Chiropractic")+COUNTIF('Older Entries'!$C:$C,"*Chiropractic*") -> 1617 | E11: Chiropractic clinics
A12: Physical Therapy | B12: =COUNTA('Physical Therapy'!$A:$A)-1 -> 298 | C12: =COUNTIF('Physical Therapy'!$M:$M,"No") -> 288 | D12: =COUNTIF('Older Entries'!$B:$B,"Physical Therapy")+COUNTIF('Older Entries'!$C:$C,"*Physical Therapy*") -> 298 | E12: Physical therapy clinics
A13: Imaging | B13: =COUNTA(Imaging!$A:$A)-1 -> 16 | C13: =COUNTIF(Imaging!$M:$M,"No") -> 13 | D13: =COUNTIF('Older Entries'!$B:$B,"Imaging")+COUNTIF('Older Entries'!$C:$C,"*Imaging*") -> 43 | E13: Radiology and MRI centers
A14: TMJ Specialists | B14: =COUNTA('TMJ Specialists'!$A:$A)-1 -> 33 | C14: =COUNTIF('TMJ Specialists'!$P:$P,"No") -> 32 | D14: =COUNTIF('Older Entries'!$B:$B,"TMJ Specialists")+COUNTIF('Older Entries'!$C:$C,"*TMJ Specialists*") -> 1 | E14: TMJ and orofacial pain specialists and clinics
A15: Oral Surgery | B15: =COUNTA('Oral Surgery'!$A:$A)-1 -> 67 | C15: =COUNTIF('Oral Surgery'!$Q:$Q,"No") -> 67 | D15: =COUNTIF('Older Entries'!$B:$B,"Oral Surgery")+COUNTIF('Older Entries'!$C:$C,"*Oral Surgery*") -> 10 | E15: Oral and maxillofacial surgeons (TMJ and jaw surgery)
A16: A multi-specialty clinic is listed in each of its groups, so the groups add up to more than the total.
A18: By region (each clinic counted once, under its main specialty group)
A19: Region | B19: Injury Physicians | C19: Chiropractic | D19: Physical Therapy | E19: Imaging | F19: TMJ Specialists | G19: Oral Surgery | H19: Total
A20: Twin Cities Metro | B20: =COUNTIFS('All Clinics'!$I:$I,$A20,'All Clinics'!$B:$B,"Injury Physicians") -> 109 | C20: =COUNTIFS('All Clinics'!$I:$I,$A20,'All Clinics'!$B:$B,"Chiropractic") -> 279 | D20: =COUNTIFS('All Clinics'!$I:$I,$A20,'All Clinics'!$B:$B,"Physical Therapy") -> 166 | E20: =COUNTIFS('All Clinics'!$I:$I,$A20,'All Clinics'!$B:$B,"Imaging") -> 10 | F20: =COUNTIFS('All Clinics'!$I:$I,$A20,'All Clinics'!$B:$B,"TMJ Specialists") -> 27 | G20: =COUNTIFS('All Clinics'!$I:$I,$A20,'All Clinics'!$B:$B,"Oral Surgery") -> 50 | H20: =SUM(B20:G20) -> 641
A21: Central Minnesota | B21: =COUNTIFS('All Clinics'!$I:$I,$A21,'All Clinics'!$B:$B,"Injury Physicians") -> 2 | C21: =COUNTIFS('All Clinics'!$I:$I,$A21,'All Clinics'!$B:$B,"Chiropractic") -> 21 | D21: =COUNTIFS('All Clinics'!$I:$I,$A21,'All Clinics'!$B:$B,"Physical Therapy") -> 11 | E21: =COUNTIFS('All Clinics'!$I:$I,$A21,'All Clinics'!$B:$B,"Imaging") -> 0 | F21: =COUNTIFS('All Clinics'!$I:$I,$A21,'All Clinics'!$B:$B,"TMJ Specialists") -> 1 | G21: =COUNTIFS('All Clinics'!$I:$I,$A21,'All Clinics'!$B:$B,"Oral Surgery") -> 2 | H21: =SUM(B21:G21) -> 37
A22: Northeast Minnesota | B22: =COUNTIFS('All Clinics'!$I:$I,$A22,'All Clinics'!$B:$B,"Injury Physicians") -> 10 | C22: =COUNTIFS('All Clinics'!$I:$I,$A22,'All Clinics'!$B:$B,"Chiropractic") -> 39 | D22: =COUNTIFS('All Clinics'!$I:$I,$A22,'All Clinics'!$B:$B,"Physical Therapy") -> 27 | E22: =COUNTIFS('All Clinics'!$I:$I,$A22,'All Clinics'!$B:$B,"Imaging") -> 0 | F22: =COUNTIFS('All Clinics'!$I:$I,$A22,'All Clinics'!$B:$B,"TMJ Specialists") -> 0 | G22: =COUNTIFS('All Clinics'!$I:$I,$A22,'All Clinics'!$B:$B,"Oral Surgery") -> 6 | H22: =SUM(B22:G22) -> 82
A23: Northwest Minnesota | B23: =COUNTIFS('All Clinics'!$I:$I,$A23,'All Clinics'!$B:$B,"Injury Physicians") -> 2 | C23: =COUNTIFS('All Clinics'!$I:$I,$A23,'All Clinics'!$B:$B,"Chiropractic") -> 7 | D23: =COUNTIFS('All Clinics'!$I:$I,$A23,'All Clinics'!$B:$B,"Physical Therapy") -> 6 | E23: =COUNTIFS('All Clinics'!$I:$I,$A23,'All Clinics'!$B:$B,"Imaging") -> 0 | F23: =COUNTIFS('All Clinics'!$I:$I,$A23,'All Clinics'!$B:$B,"TMJ Specialists") -> 0 | G23: =COUNTIFS('All Clinics'!$I:$I,$A23,'All Clinics'!$B:$B,"Oral Surgery") -> 0 | H23: =SUM(B23:G23) -> 15
A24: West Central Minnesota | B24: =COUNTIFS('All Clinics'!$I:$I,$A24,'All Clinics'!$B:$B,"Injury Physicians") -> 6 | C24: =COUNTIFS('All Clinics'!$I:$I,$A24,'All Clinics'!$B:$B,"Chiropractic") -> 18 | D24: =COUNTIFS('All Clinics'!$I:$I,$A24,'All Clinics'!$B:$B,"Physical Therapy") -> 16 | E24: =COUNTIFS('All Clinics'!$I:$I,$A24,'All Clinics'!$B:$B,"Imaging") -> 1 | F24: =COUNTIFS('All Clinics'!$I:$I,$A24,'All Clinics'!$B:$B,"TMJ Specialists") -> 1 | G24: =COUNTIFS('All Clinics'!$I:$I,$A24,'All Clinics'!$B:$B,"Oral Surgery") -> 3 | H24: =SUM(B24:G24) -> 45
A25: South Central Minnesota | B25: =COUNTIFS('All Clinics'!$I:$I,$A25,'All Clinics'!$B:$B,"Injury Physicians") -> 7 | C25: =COUNTIFS('All Clinics'!$I:$I,$A25,'All Clinics'!$B:$B,"Chiropractic") -> 23 | D25: =COUNTIFS('All Clinics'!$I:$I,$A25,'All Clinics'!$B:$B,"Physical Therapy") -> 6 | E25: =COUNTIFS('All Clinics'!$I:$I,$A25,'All Clinics'!$B:$B,"Imaging") -> 0 | F25: =COUNTIFS('All Clinics'!$I:$I,$A25,'All Clinics'!$B:$B,"TMJ Specialists") -> 1 | G25: =COUNTIFS('All Clinics'!$I:$I,$A25,'All Clinics'!$B:$B,"Oral Surgery") -> 1 | H25: =SUM(B25:G25) -> 38
A26: Southeast Minnesota | B26: =COUNTIFS('All Clinics'!$I:$I,$A26,'All Clinics'!$B:$B,"Injury Physicians") -> 7 | C26: =COUNTIFS('All Clinics'!$I:$I,$A26,'All Clinics'!$B:$B,"Chiropractic") -> 28 | D26: =COUNTIFS('All Clinics'!$I:$I,$A26,'All Clinics'!$B:$B,"Physical Therapy") -> 23 | E26: =COUNTIFS('All Clinics'!$I:$I,$A26,'All Clinics'!$B:$B,"Imaging") -> 0 | F26: =COUNTIFS('All Clinics'!$I:$I,$A26,'All Clinics'!$B:$B,"TMJ Specialists") -> 3 | G26: =COUNTIFS('All Clinics'!$I:$I,$A26,'All Clinics'!$B:$B,"Oral Surgery") -> 2 | H26: =SUM(B26:G26) -> 63
A27: Southwest Minnesota | B27: =COUNTIFS('All Clinics'!$I:$I,$A27,'All Clinics'!$B:$B,"Injury Physicians") -> 8 | C27: =COUNTIFS('All Clinics'!$I:$I,$A27,'All Clinics'!$B:$B,"Chiropractic") -> 16 | D27: =COUNTIFS('All Clinics'!$I:$I,$A27,'All Clinics'!$B:$B,"Physical Therapy") -> 7 | E27: =COUNTIFS('All Clinics'!$I:$I,$A27,'All Clinics'!$B:$B,"Imaging") -> 0 | F27: =COUNTIFS('All Clinics'!$I:$I,$A27,'All Clinics'!$B:$B,"TMJ Specialists") -> 0 | G27: =COUNTIFS('All Clinics'!$I:$I,$A27,'All Clinics'!$B:$B,"Oral Surgery") -> 1 | H27: =SUM(B27:G27) -> 32
A28: Total | B28: =SUM(B20:B27) -> 151 | C28: =SUM(C20:C27) -> 431 | D28: =SUM(D20:D27) -> 262 | E28: =SUM(E20:E27) -> 11 | F28: =SUM(F20:F27) -> 33 | G28: =SUM(G20:G27) -> 65 | H28: =SUM(H20:H27) -> 953
A30: By county (all 87 Minnesota counties)
A31: County | B31: Region | C31: Injury Physicians | D31: Chiropractic | E31: Physical Therapy | F31: Imaging | G31: TMJ Specialists | H31: Oral Surgery | I31: Total | J31: Older entries
A32: Hennepin | B32: Twin Cities Metro | C32: =COUNTIFS('All Clinics'!$H:$H,$A32,'All Clinics'!$B:$B,"Injury Physicians") -> 50 | D32: =COUNTIFS('All Clinics'!$H:$H,$A32,'All Clinics'!$B:$B,"Chiropractic") -> 108 | E32: =COUNTIFS('All Clinics'!$H:$H,$A32,'All Clinics'!$B:$B,"Physical Therapy") -> 68 | F32: =COUNTIFS('All Clinics'!$H:$H,$A32,'All Clinics'!$B:$B,"Imaging") -> 6 | G32: =COUNTIFS('All Clinics'!$H:$H,$A32,'All Clinics'!$B:$B,"TMJ Specialists") -> 11 | H32: =COUNTIFS('All Clinics'!$H:$H,$A32,'All Clinics'!$B:$B,"Oral Surgery") -> 16 | I32: =SUM(C32:H32) -> 259 | J32: =COUNTIF('Older Entries'!$H:$H,$A32) -> 630
A33: Ramsey | B33: Twin Cities Metro | C33: =COUNTIFS('All Clinics'!$H:$H,$A33,'All Clinics'!$B:$B,"Injury Physicians") -> 22 | D33: =COUNTIFS('All Clinics'!$H:$H,$A33,'All Clinics'!$B:$B,"Chiropractic") -> 39 | E33: =COUNTIFS('All Clinics'!$H:$H,$A33,'All Clinics'!$B:$B,"Physical Therapy") -> 23 | F33: =COUNTIFS('All Clinics'!$H:$H,$A33,'All Clinics'!$B:$B,"Imaging") -> 3 | G33: =COUNTIFS('All Clinics'!$H:$H,$A33,'All Clinics'!$B:$B,"TMJ Specialists") -> 4 | H33: =COUNTIFS('All Clinics'!$H:$H,$A33,'All Clinics'!$B:$B,"Oral Surgery") -> 8 | I33: =SUM(C33:H33) -> 99 | J33: =COUNTIF('Older Entries'!$H:$H,$A33) -> 252
A34: Dakota | B34: Twin Cities Metro | C34: =COUNTIFS('All Clinics'!$H:$H,$A34,'All Clinics'!$B:$B,"Injury Physicians") -> 10 | D34: =COUNTIFS('All Clinics'!$H:$H,$A34,'All Clinics'!$B:$B,"Chiropractic") -> 45 | E34: =COUNTIFS('All Clinics'!$H:$H,$A34,'All Clinics'!$B:$B,"Physical Therapy") -> 27 | F34: =COUNTIFS('All Clinics'!$H:$H,$A34,'All Clinics'!$B:$B,"Imaging") -> 0 | G34: =COUNTIFS('All Clinics'!$H:$H,$A34,'All Clinics'!$B:$B,"TMJ Specialists") -> 2 | H34: =COUNTIFS('All Clinics'!$H:$H,$A34,'All Clinics'!$B:$B,"Oral Surgery") -> 7 | I34: =SUM(C34:H34) -> 91 | J34: =COUNTIF('Older Entries'!$H:$H,$A34) -> 159
A35: Washington | B35: Twin Cities Metro | C35: =COUNTIFS('All Clinics'!$H:$H,$A35,'All Clinics'!$B:$B,"Injury Physicians") -> 10 | D35: =COUNTIFS('All Clinics'!$H:$H,$A35,'All Clinics'!$B:$B,"Chiropractic") -> 25 | E35: =COUNTIFS('All Clinics'!$H:$H,$A35,'All Clinics'!$B:$B,"Physical Therapy") -> 15 | F35: =COUNTIFS('All Clinics'!$H:$H,$A35,'All Clinics'!$B:$B,"Imaging") -> 0 | G35: =COUNTIFS('All Clinics'!$H:$H,$A35,'All Clinics'!$B:$B,"TMJ Specialists") -> 5 | H35: =COUNTIFS('All Clinics'!$H:$H,$A35,'All Clinics'!$B:$B,"Oral Surgery") -> 6 | I35: =SUM(C35:H35) -> 61 | J35: =COUNTIF('Older Entries'!$H:$H,$A35) -> 112
A36: Anoka | B36: Twin Cities Metro | C36: =COUNTIFS('All Clinics'!$H:$H,$A36,'All Clinics'!$B:$B,"Injury Physicians") -> 8 | D36: =COUNTIFS('All Clinics'!$H:$H,$A36,'All Clinics'!$B:$B,"Chiropractic") -> 22 | E36: =COUNTIFS('All Clinics'!$H:$H,$A36,'All Clinics'!$B:$B,"Physical Therapy") -> 13 | F36: =COUNTIFS('All Clinics'!$H:$H,$A36,'All Clinics'!$B:$B,"Imaging") -> 0 | G36: =COUNTIFS('All Clinics'!$H:$H,$A36,'All Clinics'!$B:$B,"TMJ Specialists") -> 1 | H36: =COUNTIFS('All Clinics'!$H:$H,$A36,'All Clinics'!$B:$B,"Oral Surgery") -> 6 | I36: =SUM(C36:H36) -> 50 | J36: =COUNTIF('Older Entries'!$H:$H,$A36) -> 88
A37: St. Louis | B37: Northeast Minnesota | C37: =COUNTIFS('All Clinics'!$H:$H,$A37,'All Clinics'!$B:$B,"Injury Physicians") -> 7 | D37: =COUNTIFS('All Clinics'!$H:$H,$A37,'All Clinics'!$B:$B,"Chiropractic") -> 9 | E37: =COUNTIFS('All Clinics'!$H:$H,$A37,'All Clinics'!$B:$B,"Physical Therapy") -> 14 | F37: =COUNTIFS('All Clinics'!$H:$H,$A37,'All Clinics'!$B:$B,"Imaging") -> 0 | G37: =COUNTIFS('All Clinics'!$H:$H,$A37,'All Clinics'!$B:$B,"TMJ Specialists") -> 0 | H37: =COUNTIFS('All Clinics'!$H:$H,$A37,'All Clinics'!$B:$B,"Oral Surgery") -> 4 | I37: =SUM(C37:H37) -> 34 | J37: =COUNTIF('Older Entries'!$H:$H,$A37) -> 54
A38: Olmsted | B38: Southeast Minnesota | C38: =COUNTIFS('All Clinics'!$H:$H,$A38,'All Clinics'!$B:$B,"Injury Physicians") -> 4 | D38: =COUNTIFS('All Clinics'!$H:$H,$A38,'All Clinics'!$B:$B,"Chiropractic") -> 9 | E38: =COUNTIFS('All Clinics'!$H:$H,$A38,'All Clinics'!$B:$B,"Physical Therapy") -> 9 | F38: =COUNTIFS('All Clinics'!$H:$H,$A38,'All Clinics'!$B:$B,"Imaging") -> 0 | G38: =COUNTIFS('All Clinics'!$H:$H,$A38,'All Clinics'!$B:$B,"TMJ Specialists") -> 3 | H38: =COUNTIFS('All Clinics'!$H:$H,$A38,'All Clinics'!$B:$B,"Oral Surgery") -> 2 | I38: =SUM(C38:H38) -> 27 | J38: =COUNTIF('Older Entries'!$H:$H,$A38) -> 35
A39: Wright | B39: Twin Cities Metro | C39: =COUNTIFS('All Clinics'!$H:$H,$A39,'All Clinics'!$B:$B,"Injury Physicians") -> 1 | D39: =COUNTIFS('All Clinics'!$H:$H,$A39,'All Clinics'!$B:$B,"Chiropractic") -> 12 | E39: =COUNTIFS('All Clinics'!$H:$H,$A39,'All Clinics'!$B:$B,"Physical Therapy") -> 8 | F39: =COUNTIFS('All Clinics'!$H:$H,$A39,'All Clinics'!$B:$B,"Imaging") -> 0 | G39: =COUNTIFS('All Clinics'!$H:$H,$A39,'All Clinics'!$B:$B,"TMJ Specialists") -> 2 | H39: =COUNTIFS('All Clinics'!$H:$H,$A39,'All Clinics'!$B:$B,"Oral Surgery") -> 2 | I39: =SUM(C39:H39) -> 25 | J39: =COUNTIF('Older Entries'!$H:$H,$A39) -> 49
A40: Stearns | B40: Central Minnesota | C40: =COUNTIFS('All Clinics'!$H:$H,$A40,'All Clinics'!$B:$B,"Injury Physicians") -> 2 | D40: =COUNTIFS('All Clinics'!$H:$H,$A40,'All Clinics'!$B:$B,"Chiropractic") -> 8 | E40: =COUNTIFS('All Clinics'!$H:$H,$A40,'All Clinics'!$B:$B,"Physical Therapy") -> 8 | F40: =COUNTIFS('All Clinics'!$H:$H,$A40,'All Clinics'!$B:$B,"Imaging") -> 0 | G40: =COUNTIFS('All Clinics'!$H:$H,$A40,'All Clinics'!$B:$B,"TMJ Specialists") -> 1 | H40: =COUNTIFS('All Clinics'!$H:$H,$A40,'All Clinics'!$B:$B,"Oral Surgery") -> 2 | I40: =SUM(C40:H40) -> 21 | J40: =COUNTIF('Older Entries'!$H:$H,$A40) -> 73
A41: Douglas | B41: West Central Minnesota | C41: =COUNTIFS('All Clinics'!$H:$H,$A41,'All Clinics'!$B:$B,"Injury Physicians") -> 5 | D41: =COUNTIFS('All Clinics'!$H:$H,$A41,'All Clinics'!$B:$B,"Chiropractic") -> 6 | E41: =COUNTIFS('All Clinics'!$H:$H,$A41,'All Clinics'!$B:$B,"Physical Therapy") -> 7 | F41: =COUNTIFS('All Clinics'!$H:$H,$A41,'All Clinics'!$B:$B,"Imaging") -> 1 | G41: =COUNTIFS('All Clinics'!$H:$H,$A41,'All Clinics'!$B:$B,"TMJ Specialists") -> 0 | H41: =COUNTIFS('All Clinics'!$H:$H,$A41,'All Clinics'!$B:$B,"Oral Surgery") -> 1 | I41: =SUM(C41:H41) -> 20 | J41: =COUNTIF('Older Entries'!$H:$H,$A41) -> 16
A42: Carver | B42: Twin Cities Metro | C42: =COUNTIFS('All Clinics'!$H:$H,$A42,'All Clinics'!$B:$B,"Injury Physicians") -> 2 | D42: =COUNTIFS('All Clinics'!$H:$H,$A42,'All Clinics'!$B:$B,"Chiropractic") -> 9 | E42: =COUNTIFS('All Clinics'!$H:$H,$A42,'All Clinics'!$B:$B,"Physical Therapy") -> 5 | F42: =COUNTIFS('All Clinics'!$H:$H,$A42,'All Clinics'!$B:$B,"Imaging") -> 1 | G42: =COUNTIFS('All Clinics'!$H:$H,$A42,'All Clinics'!$B:$B,"TMJ Specialists") -> 0 | H42: =COUNTIFS('All Clinics'!$H:$H,$A42,'All Clinics'!$B:$B,"Oral Surgery") -> 1 | I42: =SUM(C42:H42) -> 18 | J42: =COUNTIF('Older Entries'!$H:$H,$A42) -> 38
A43: Scott | B43: Twin Cities Metro | C43: =COUNTIFS('All Clinics'!$H:$H,$A43,'All Clinics'!$B:$B,"Injury Physicians") -> 1 | D43: =COUNTIFS('All Clinics'!$H:$H,$A43,'All Clinics'!$B:$B,"Chiropractic") -> 9 | E43: =COUNTIFS('All Clinics'!$H:$H,$A43,'All Clinics'!$B:$B,"Physical Therapy") -> 3 | F43: =COUNTIFS('All Clinics'!$H:$H,$A43,'All Clinics'!$B:$B,"Imaging") -> 0 | G43: =COUNTIFS('All Clinics'!$H:$H,$A43,'All Clinics'!$B:$B,"TMJ Specialists") -> 2 | H43: =COUNTIFS('All Clinics'!$H:$H,$A43,'All Clinics'!$B:$B,"Oral Surgery") -> 2 | I43: =SUM(C43:H43) -> 17 | J43: =COUNTIF('Older Entries'!$H:$H,$A43) -> 61
... A118: Wilkin | B118: West Central Minnesota | C118: =COUNTIFS('All Clinics'!$H:$H,$A118,'All Clinics'!$B:$B,"Injury Physicians") -> 0 | D118: =COUNTIFS('All Clinics'!$H:$H,$A118,'All Clinics'!$B:$B,"Chiropractic") -> 0 | E118: =COUNTIFS('All Clinics'!$H:$H,$A118,'All Clinics'!$B:$B,"Physical Therapy") -> 0 | F118: =COUNTIFS('All Clinics'!$H:$H,$A118,'All Clinics'!$B:$B,"Imaging") -> 0 | G118: =COUNTIFS('All Clinics'!$H:$H,$A118,'All Clinics'!$B:$B,"TMJ Specialists") -> 0 | H118: =COUNTIFS('All Clinics'!$H:$H,$A118,'All Clinics'!$B:$B,"Oral Surgery") -> 0 | I118: =SUM(C118:H118) -> 0 | J118: =COUNTIF('Older Entries'!$H:$H,$A118) -> 2

Sheet All Clinics
A1: Clinic Name | B1: Specialty Group | C1: Also In | D1: Specialties | E1: Street | F1: Suite | G1: City | H1: County | I1: Region | J1: ZIP | K1: Phone | L1: Providers at Address | M1: On Xpert Connect | N1: Registry Updated | O1: Legal Name | P1: NPI | Q1: Map | R1: NPPES Record
A2: Health and Healing Family Chiropractic | B2: Chiropractic | D2: Chiropractic | E2: 1883 Station Pkwy NW | G2: Andover | H2: Anoka | I2: Twin Cities Metro | J2: 55304 | K2: (763) 323-0061 | L2: 1 | M2: No | N2: 45559 | O2: Health and Healing Family Chiropractic | P2: 1366657280 | Q2: Map | R2: Record
A3: Moore Therapies, PLLC | B3: Physical Therapy | D3: Physical Therapy | E3: 16817 Zion St NW | G3: Andover | H3: Anoka | I3: Twin Cities Metro | J3: 55304 | K3: (651) 955-3327 | L3: 0 | M3: No | N3: 45408 | O3: Moore Therapies, PLLC | P3: 1225884661 | Q3: Map | R3: Record
A4: 7th Avenue Chiropractic | B4: Chiropractic | D4: Chiropractic | E4: 3722 7th Ave | G4: Anoka | H4: Anoka | I4: Twin Cities Metro | J4: 55303 | K4: (763) 312-1257 | L4: 2 | M4: No | N4: 45659 | O4: 7th Avenue Chiropractic | P4: 1053120220 | Q4: Map | R4: Record
A5: HealthPartners Riverway Pain Clinic | B5: Injury Physicians | D5: Pain Management | E5: 2621 Greenhaven Rd | G5: Anoka | H5: Anoka | I5: Twin Cities Metro | J5: 55303 | K5: (763) 587-4488 | L5: 0 | M5: No | N5: 46240 | O5: Group Health, INC. | P5: 1689068462 | Q5: Map | R5: Record
A6: Kuss Chiropractic | B6: Chiropractic | D6: Chiropractic | E6: 440 Bunker Lake Blvd NW | F6: Ste 105 | G6: Anoka | H6: Anoka | I6: Twin Cities Metro | J6: 55303 | K6: (763) 330-0393 | L6: 1 | M6: No | N6: 45778 | O6: Kuss Company LLC | P6: 1821895756 | Q6: Map | R6: Record
A7: Unison Chiropractic Center PLLC | B7: Chiropractic | D7: Chiropractic | E7: 2006 1st Ave | F7: Ste 209 | G7: Anoka | H7: Anoka | I7: Twin Cities Metro | J7: 55303 | K7: (763) 421-0436 | L7: 1 | M7: No | N7: 46001 | O7: Unison Chiropractic Center PLLC | P7: 1538644885 | Q7: Map | R7: Record
A8: Blaine Chiropractic Center PA | B8: Chiropractic | D8: Chiropractic | E8: 11919 Central Ave NE | G8: Blaine | H8: Anoka | I8: Twin Cities Metro | J8: 55434 | K8: (763) 757-1660 | L8: 8 | M8: No | N8: 45384 | O8: Blaine Chiropractic Center PA | P8: 1376759589 | Q8: Map | R8: Record
A9: Club West Chiropractic PA | B9: Chiropractic | C9: Physical Therapy | D9: Chiropractic, Physical Therapy | E9: 10950 Club West Pkwy | F9: Ste 190 | G9: Blaine | H9: Anoka | I9: Twin Cities Metro | J9: 55449 | K9: (763) 400-4940 | L9: 3 | M9: No | N9: 45348 | O9: Club West Chiropractic PA | P9: 1427447432 | Q9: Map | R9: Record
A10: Concentra Medical Center | B10: Physical Therapy | D10: Physical Therapy | E10: 10190 Baltimore St NE | F10: Ste 100 | G10: Blaine | H10: Anoka | I10: Twin Cities Metro | J10: 55449 | K10: (763) 780-8264 | L10: 0 | M10: No | N10: 45827 | O10: Occupational Health Centers of Minnesota PC | P10: 1508347964 | Q10: Map | R10: Record
A11: Metro Dentalcare Blaine 10 | B11: Oral Surgery | D11: Oral & Maxillofacial Surgery | E11: 261 County Road 10 NE | F11: Ste 10 | G11: Blaine | H11: Anoka | I11: Twin Cities Metro | J11: 55434 | K11: (763) 786-9644 | L11: 0 | M11: No | N11: 44642 | O11: Family Oral Surgery Specialists, PLC | P11: 1730838186 | Q11: Map | R11: Record
A12: Novacare Rehabilitation | B12: Physical Therapy | D12: Physical Therapy | E12: 11855 Ulysses St NE | F12: Ste 20 | G12: Blaine | H12: Anoka | I12: Twin Cities Metro | J12: 55434 | K12: (763) 767-3140 | L12: 10 | M12: No | N12: 45589 | O12: Novacare Outpatient Rehabilitation East, INC. | P12: 1235950957 | Q12: Map | R12: Record
A13: OMS Specialists | B13: Oral Surgery | D13: Oral & Maxillofacial Surgery | E13: 11855 Ulysses Street NE | F13: 130 | G13: Blaine | H13: Anoka | I13: Twin Cities Metro | J13: 55434 | K13: (763) 757-2220 | L13: 0 | M13: No | N13: 41849 | O13: Oral & Maxillofacial Surgery Specialists, PA | P13: 1467563510 | Q13: Map | R13: Record
A14: Open Heart Chiropractic PA | B14: Chiropractic | D14: Chiropractic | E14: 12265 Central Ave NE | G14: Blaine | H14: Anoka | I14: Twin Cities Metro | J14: 55434 | K14: (763) 757-8511 | L14: 2 | M14: No | N14: 45153 | O14: Open Heart Chiropractic PA | P14: 1811687015 | Q14: Map | R14: Record
A15: Summit Orthopedics, LTD | B15: Injury Physicians | D15: Orthopedics, Sports Medicine | E15: 10230 Baltimore St NE | F15: Ste 300 | G15: Blaine | H15: Anoka | I15: Twin Cities Metro | J15: 55449 | K15: (651) 968-5200 | L15: 2 | M15: Yes | N15: 45818 | O15: Summit Orthopedics, LTD | P15: 1043566045 | Q15: Map | R15: Record
A16: The Facial Pain Center | B16: TMJ Specialists | D16: TMJ Treatment | E16: 4190 108th Ave NE | F16: Ste 130 | G16: Blaine | H16: Anoka | I16: Twin Cities Metro | J16: 55449 | K16: (651) 636-2016 | L16: 0 | M16: No | N16: 46245 | O16: Facial Pain Center PLLC | P16: 1407325830 | Q16: Map | R16: Record
A17: Allina Health Brain and Spine Institute - Coon Rapids | B17: Injury Physicians | D17: Neurosurgery | E17: 11850 Blackfoot St NW | F17: Ste 490 | G17: Coon Rapids | H17: Anoka | I17: Twin Cities Metro | J17: 55433 | K17: (612) 871-7278 | L17: 5 | M17: Yes | N17: 46036 | O17: Allina Health System | P17: 1275351413 | Q17: Map | R17: Record
A18: Associated Oral & Maxillofacial Surgeons (Associated OMS) | B18: Oral Surgery | D18: Oral & Maxillofacial Surgery | E18: 3833 Coon Rapids Blvd NW | G18: Coon Rapids | H18: Anoka | I18: Twin Cities Metro | J18: 55433 | K18: (763) 421-6271 | L18: 1 | M18: No | N18: 45441 | O18: MN Dental Service Providers LLC | P18: 1649043662 | Q18: Map | R18: Record
A19: Caring Chiropractic Center, PA. | B19: Chiropractic | D19: Chiropractic | E19: 10811 Xavis St NW | G19: Coon Rapids | H19: Anoka | I19: Twin Cities Metro | J19: 55433 | K19: (763) 421-1905 | L19: 2 | M19: No | N19: 46248 | O19: Caring Chiropractic Center, PA. | P19: 1134494818 | Q19: Map | R19: Record
A20: Concentra Medical Center | B20: Physical Therapy | D20: Physical Therapy | E20: 600 Coon Rapids Blvd NW | F20: Ste 2 | G20: Coon Rapids | H20: Anoka | I20: Twin Cities Metro | J20: 55433 | K20: (651) 968-5273 | L20: 1 | M20: No | N20: 46211 | O20: Occupational Health Centers of Minnesota PC | P20: 1326966300 | Q20: Map | R20: Record
A21: Courage Kenny Rehabilitation Associates | B21: Injury Physicians | D21: Physical Medicine & Rehabilitation | E21: 11850 Blackfoot St NW | F21: Ste 405 | G21: Coon Rapids | H21: Anoka | I21: Twin Cities Metro | J21: 55433 | K21: (763) 236-0888 | L21: 3 | M21: Yes | N21: 45713 | O21: Allina Health System | P21: 1770034670 | Q21: Map | R21: Record
A22: Fit Family Chiropractic | B22: Chiropractic | D22: Chiropractic | E22: 1835 Gateway Dr | F22: Ste 104 | G22: Coon Rapids | H22: Anoka | I22: Twin Cities Metro | J22: 55448 | K22: (763) 710-8888 | L22: 1 | M22: No | N22: 44663 | O22: Moe Chiro Tres PLLC | P22: 1063054302 | Q22: Map | R22: Record
A23: Mary T Outpatient | B23: Physical Therapy | D23: Physical Therapy | E23: 11800 Xeon Blvd NW | G23: Coon Rapids | H23: Anoka | I23: Twin Cities Metro | J23: 55448 | K23: (763) 489-3638 | L23: 4 | M23: No | N23: 44736 | O23: Mary T Outpatient | P23: 1396475927 | Q23: Map | R23: Record
A24: Metropolitan Neurosurgery, PA | B24: Injury Physicians | D24: Neurosurgery | E24: 11850 Blackfoot St NW | F24: Ste 490 | G24: Coon Rapids | H24: Anoka | I24: Twin Cities Metro | J24: 55433 | K24: (763) 427-1137 | L24: 5 | M24: No | N24: 45394 | O24: Metropolitan Neurosurgery, PA | P24: 1386690543 | Q24: Map | R24: Record
A25: Minnesota Neurosurgical Trauma Associates, PLLC | B25: Injury Physicians | D25: Neurosurgery | E25: 11850 Blackfoot St NW | F25: Ste 490 | G25: Coon Rapids | H25: Anoka | I25: Twin Cities Metro | J25: 55433 | K25: (763) 427-1137 | L25: 5 | M25: No | N25: 45407 | O25: Minnesota Neurosurgical Trauma Associates, PLLC | P25: 1922241884 | Q25: Map | R25: Record
A26: Northside Minnesota Oral and Maxillofacial Surgeons, PLLC | B26: Oral Surgery | D26: Oral & Maxillofacial Surgery | E26: 11441 Osage St NW | G26: Coon Rapids | H26: Anoka | I26: Twin Cities Metro | J26: 55433 | K26: (763) 862-6442 | L26: 1 | M26: No | N26: 44369 | O26: Northside Minnesota Oral and Maxillofacial Surgeons, PLLC | P26: 1245809458 | Q26: Map | R26: Record
A27: Novacare Rehabilitation | B27: Physical Therapy | D27: Physical Therapy | E27: 2104 Northdale Blvd NW | F27: Ste 100 | G27: Coon Rapids | H27: Anoka | I27: Twin Cities Metro | J27: 55433 | K27: (763) 755-5495 | L27: 18 | M27: No | N27: 45593 | O27: Novacare Outpatient Rehabilitation East, INC. | P27: 1386466886 | Q27: Map | R27: Record
A28: Novacare Rehabilitation | B28: Physical Therapy | D28: Physical Therapy | E28: 10091 Dogwood St NW | G28: Coon Rapids | H28: Anoka | I28: Twin Cities Metro | J28: 55448 | K28: (763) 450-0298 | L28: 4 | M28: No | N28: 45926 | O28: Novacare Outpatient Rehabilitation East, INC. | P28: 1982246013 | Q28: Map | R28: Record
A29: Pdr Coon Rapids, INC | B29: Injury Physicians | C29: Chiropractic, Physical Therapy | D29: Physical Medicine & Rehabilitation, Chiropractic, Physical Therapy | E29: 320 Coon Rapids Blvd NW | F29: #100 | G29: Coon Rapids | H29: Anoka | I29: Twin Cities Metro | J29: 55433 | K29: (952) 908-2580 | L29: 5 | M29: No | N29: 45911 | O29: Pdr Coon Rapids, INC | P29: 1477666428 | Q29: Map | R29: Record
A30: Restoring Wellness Chiropractic | B30: Chiropractic | D30: Chiropractic | E30: 10811 Xavis St NW | G30: Coon Rapids | H30: Anoka | I30: Twin Cities Metro | J30: 55433 | K30: (763) 285-6475 | L30: 2 | M30: No | N30: 45131 | O30: Restoring Wellness Chiropractic, LLC | P30: 1447934385 | Q30: Map | R30: Record
A31: Summit Orthopedics, LTD. | B31: Physical Therapy | D31: Physical Therapy | E31: 600 Coon Rapids Blvd NW | F31: Ste 150 | G31: Coon Rapids | H31: Anoka | I31: Twin Cities Metro | J31: 55433 | K31: (651) 968-5201 | L31: 1 | M31: No | N31: 45391 | O31: Summit Orthopedics, LTD. | P31: 1770207193 | Q31: Map | R31: Record
A32: The Dental Specialists - Coon Rapids / Riverdale | B32: Oral Surgery | D32: Oral & Maxillofacial Surgery | E32: 3360 Northdale Blvd. | G32: Coon Rapids | H32: Anoka | I32: Twin Cities Metro | J32: 55448 | K32: (763) 233-3390 | L32: 0 | M32: No | N32: 44763 | O32: Dental Specialists of Minnesota, PLLC | P32: 1396095048 | Q32: Map | R32: Record
A33: The Dental Specialists - Coon Rapids Riverdale | B33: Oral Surgery | D33: Oral & Maxillofacial Surgery | E33: 3360 Northdale Blvd NW | G33: Coon Rapids | H33: Anoka | I33: Twin Cities Metro | J33: 55448 | K33: (763) 201-6962 | L33: 0 | M33: No | N33: 44132 | O33: Dental Specialists of Minnesota, PLLC | P33: 1518200286 | Q33: Map | R33: Record
A34: Therapy Partners INC | B34: Physical Therapy | D34: Physical Therapy | E34: 11800 Xeon Blvd NW | G34: Coon Rapids | H34: Anoka | I34: Twin Cities Metro | J34: 55448 | K34: (763) 489-3638 | L34: 4 | M34: No | N34: 45370 | O34: Therapy Partners INC | P34: 1306606397 | Q34: Map | R34: Record
A35: Therapy Partners, INC. | B35: Physical Therapy | D35: Physical Therapy | E35: 8770 Springbrook Dr NW | F35: Ste 100 | G35: Coon Rapids | H35: Anoka | I35: Twin Cities Metro | J35: 55433 | K35: (763) 231-1824 | L35: 6 | M35: No | N35: 46275 | O35: Therapy Partners, INC. | P35: 1407809494 | Q35: Map | R35: Record
A36: Rooted In Wellness Chiropractic LLC | B36: Chiropractic | D36: Chiropractic | E36: 20730 Hamlet Ave N | G36: Forest Lake | H36: Anoka | I36: Twin Cities Metro | J36: 55025 | K36: (651) 248-1841 | L36: 0 | M36: No | N36: 45674 | O36: Rooted In Wellness Chiropractic LLC | P36: 1538970660 | Q36: Map | R36: Record
A37: Heim Chiropractic, PA | B37: Chiropractic | D37: Chiropractic | E37: 7101 Highway 65 NE | F37: Ste 4 | G37: Fridley | H37: Anoka | I37: Twin Cities Metro | J37: 55432 | K37: (651) 482-9160 | L37: 1 | M37: No | N37: 46266 | O37: Heim Chiropractic, PA | P37: 1073675047 | Q37: Map | R37: Record
A38: Minnesota Chiroworks, PLLC | B38: Chiropractic | D38: Chiropractic | E38: 7400 University Ave NE | F38: Ste 100 | G38: Fridley | H38: Anoka | I38: Twin Cities Metro | J38: 55432 | K38: (637) 571-0239 | L38: 0 | M38: No | N38: 44981 | O38: Minnesota Chiroworks, PLLC | P38: 1750917068 | Q38: Map | R38: Record
A39: Novacare Rehabilitation | B39: Physical Therapy | D39: Physical Therapy | E39: 480 Osborne Road | F39: Number 280 | G39: Fridley | H39: Anoka | I39: Twin Cities Metro | J39: 55432 | K39: (763) 784-3155 | L39: 0 | M39: No | N39: 45951 | O39: Novacare Outpatient Rehabilitation East INC | P39: 1558610519 | Q39: Map | R39: Record
A40: Novacare Rehabilitation | B40: Physical Therapy | D40: Physical Therapy | E40: 480 Osborne Rd NE | F40: Ste 280 | G40: Fridley | H40: Anoka | I40: Twin Cities Metro | J40: 55432 | K40: (763) 784-3155 | L40: 3 | M40: No | N40: 45589 | O40: Novacare Outpatient Rehabilitation East, INC. | P40: 1356162051 | Q40: Map | R40: Record
A41: Spinecare Fridley, PC | B41: Chiropractic | D41: Chiropractic | E41: 7872 University Ave NE | G41: Fridley | H41: Anoka | I41: Twin Cities Metro | J41: 55432 | K41: (763) 780-4300 | L41: 3 | M41: No | N41: 44763 | O41: A Plus Chiropractic, PC | P41: 1265953061 | Q41: Map | R41: Record
A42: The Minnesota Chiroworks, PC | B42: Chiropractic | D42: Chiropractic | E42: 7872 University Ave NE | G42: Fridley | H42: Anoka | I42: Twin Cities Metro | J42: 55432 | K42: (763) 780-4300 | L42: 3 | M42: No | N42: 46129 | O42: The Minnesota Chiroworks, PC | P42: 1720874860 | Q42: Map | R42: Record
A43: Exceptional Chiropractic P A | B43: Chiropractic | D43: Chiropractic | E43: 16230 Aberdeen St NE | F43: Ste B | G43: Ham Lake | H43: Anoka | I43: Twin Cities Metro | J43: 55304 | K43: (763) 208-5382 | L43: 2 | M43: No | N43: 45352 | O43: Exceptional Chiropractic P A | P43: 1881795961 | Q43: Map | R43: Record
A44: Exceptional Chiropractic P A | B44: Chiropractic | D44: Chiropractic | E44: 2415 149th Ave NE | G44: Ham Lake | H44: Anoka | I44: Twin Cities Metro | J44: 55304 | K44: (612) 418-3587 | L44: 0 | M44: No | N44: 45352 | O44: Exceptional Chiropractic P A | P44: 1881795961 | Q44: Map | R44: Record
A45: Silver View Chiropractic Center, PA. | B45: Chiropractic | D45: Chiropractic | E45: 4137 Woodland Road | G45: Lexington | H45: Anoka | I45: Twin Cities Metro | J45: 55014 | K45: (763) 786-5581 | L45: 3 | M45: No | N45: 45523 | O45: Silver View Chiropractic Center, PA. | P45: 1740453968 | Q45: Map | R45: Record
A46: Sprout Chiropractic & Wellness | B46: Chiropractic | D46: Chiropractic | E46: 7525 Village Dr | F46: Ste 110 | G46: Lino Lakes | H46: Anoka | I46: Twin Cities Metro | J46: 55014 | K46: (651) 247-0941 | L46: 1 | M46: No | N46: 44760 | O46: Roseville Chiropractic Clinic, LLC | P46: 1699054304 | Q46: Map | R46: Record
A47: Nura PLLC | B47: Injury Physicians | D47: Pain Management | E47: 2104 Northdale Boulevard NW | F47: Ste 220 | G47: Minneapolis | H47: Anoka | I47: Twin Cities Metro | J47: 55433 | K47: (763) 537-6000 | L47: 10 | M47: No | N47: 46253 | O47: Nura PLLC | P47: 1750316014 | Q47: Map | R47: Record
A48: Meraki Chiropractic PLLC | B48: Chiropractic | D48: Chiropractic | E48: 19201 Lake George Blvd | F48: Ste C | G48: Oak Grove | H48: Anoka | I48: Twin Cities Metro | J48: 55303 | K48: (763) 200-3370 | L48: 1 | M48: No | N48: 45313 | O48: Meraki Chiropractic PLLC | P48: 1750142360 | Q48: Map | R48: Record
A49: Hands Hooves and Hearts Therapeutic Services LLC | B49: Physical Therapy | D49: Physical Therapy | E49: 9457 Highway 10 NW | G49: Ramsey | H49: Anoka | I49: Twin Cities Metro | J49: 55303 | K49: (612) 230-0308 | L49: 0 | M49: No | N49: 46107 | O49: Hands Hooves and Hearts Therapeutic Services LLC | P49: 1891332599 | Q49: Map | R49: Record
A50: Opp Family Chiropractic PA. | B50: Chiropractic | D50: Chiropractic | E50: 23168 Saint Francis Blvd NW | F50: #600 | G50: St. Francis | H50: Anoka | I50: Twin Cities Metro | J50: 55070 | K50: (763) 213-0615 | L50: 3 | M50: No | N50: 45419 | O50: Opp Family Chiropractic PA. | P50: 1982890810 | Q50: Map | R50: Record
A51: St Lukes Chiropractic | B51: Chiropractic | D51: Chiropractic | E51: 3220 Bridge St NW | F51: Ste 108 | G51: St. Francis | H51: Anoka | I51: Twin Cities Metro | J51: 55070 | K51: (763) 452-0171 | L51: 1 | M51: No | N51: 45260 | O51: St Lukes Chiropractic | P51: 1235715574 | Q51: Map | R51: Record
A52: Backed Chiropractic | B52: Chiropractic | D52: Chiropractic | E52: 1286 Park Rd | F52: # B | G52: Chanhassen | H52: Carver | I52: Twin Cities Metro | J52: 55317 | K52: (952) 451-8571 | L52: 1 | M52: No | N52: 45631 | O52: Backed Chiropractic PLLC | P52: 1720862931 | Q52: Map | R52: Record
A53: Chanhassen Chiropractic | B53: Chiropractic | D53: Chiropractic | E53: 7800 Market Blvd | G53: Chanhassen | H53: Carver | I53: Twin Cities Metro | J53: 55317 | K53: (952) 934-4500 | L53: 2 | M53: No | N53: 45225 | O53: Active Mobility Practitioner PA | P53: 1639528508 | Q53: Map | R53: Record
A54: Kandor Physical Therapy & Pelvic Health LLC | B54: Physical Therapy | D54: Physical Therapy | E54: 8951 Crossroads Blvd | F54: Ste 213 | G54: Chanhassen | H54: Carver | I54: Twin Cities Metro | J54: 55317 | K54: (952) 395-7461 | L54: 0 | M54: No | N54: 46037 | O54: Kandor Physical Therapy & Pelvic Health LLC | P54: 1114885357 | Q54: Map | R54: Record
A55: Therapy Partners, INC. | B55: Physical Therapy | D55: Physical Therapy | E55: 600 Market St | F55: Ste 150 | G55: Chanhassen | H55: Carver | I55: Twin Cities Metro | J55: 55317 | K55: (952) 491-4700 | L55: 8 | M55: No | N55: 46275 | O55: Therapy Partners, INC. | P55: 1407809494 | Q55: Map | R55: Record
A56: Ahc Medical, PC | B56: Injury Physicians | D56: Physical Medicine & Rehabilitation | E56: 1476 White Oak Dr | G56: Chaska | H56: Carver | I56: Twin Cities Metro | J56: 55318 | K56: (952) 448-3900 | L56: 0 | M56: No | N56: 44971 | O56: Ahc Medical, PC | P56: 1336846955 | Q56: Map | R56: Record
A57: Concentra Medical Center | B57: Physical Therapy | D57: Physical Therapy | E57: 1580 White Oak Dr | F57: Ste 100 | G57: Chaska | H57: Carver | I57: Twin Cities Metro | J57: 55318 | K57: (952) 544-8800 | L57: 2 | M57: No | N57: 45827 | O57: Occupational Health Centers of Minnesota PC | P57: 1790266153 | Q57: Map | R57: Record
A58: Discover Chiropractic | B58: Chiropractic | D58: Chiropractic | E58: 1107 Hazeltine Blvd | F58: Ste 100 | G58: Chaska | H58: Carver | I58: Twin Cities Metro | J58: 55318 | K58: (952) 368-4700 | L58: 1 | M58: No | N58: 46246 | O58: Coombs Chiropractic PLLC | P58: 1861317349 | Q58: Map | R58: Record
A59: Inmind Health, LLC | B59: Physical Therapy | D59: Physical Therapy | E59: 1107 Hazeltine Blvd | F59: Ste 496, MD 45 | G59: Chaska | H59: Carver | I59: Twin Cities Metro | J59: 55318 | K59: (952) 240-3344 | L59: 0 | M59: No | N59: 46177 | O59: Inmind Health, LLC | P59: 1912782749 | Q59: Map | R59: Record
A60: Lake Life Chiropractic LLC | B60: Chiropractic | D60: Chiropractic | E60: 3650 N Chestnut St | F60: Ste 101A | G60: Chaska | H60: Carver | I60: Twin Cities Metro | J60: 55318 | K60: (612) 562-8384 | L60: 2 | M60: No | N60: 45820 | O60: Lake Life Chiropractic LLC | P60: 1952826778 | Q60: Map | R60: Record
A61: Peak Chiropractic LLC | B61: Chiropractic | D61: Chiropractic | E61: 1107 Hazeltine Blvd | F61: Ste 420 | G61: Chaska | H61: Carver | I61: Twin Cities Metro | J61: 55318 | K61: (952) 600-5584 | L61: 1 | M61: No | N61: 45475 | O61: Peak Chiropractic LLC | P61: 1215773049 | Q61: Map | R61: Record
A62: Twin Cities Pain Clinic | B62: Injury Physicians | D62: Pain Management, Physical Medicine & Rehabilitation | E62: 584 Bavaria Ln | G62: Chaska | H62: Carver | I62: Twin Cities Metro | J62: 55318 | K62: (952) 841-2345 | L62: 4 | M62: No | N62: 45027 | O62: Andrew J Will MD PA | P62: 1669167920 | Q62: Map | R62: Record
A63: Sports Performance Chiropractic | B63: Chiropractic | D63: Chiropractic | E63: 350 Highway 7 | F63: Ste 200 | G63: Excelsior | H63: Carver | I63: Twin Cities Metro | J63: 55331 | K63: (952) 529-3905 | L63: 0 | M63: No | N63: 46125 | O63: Sports Performance Chiropractic | P63: 1649113804 | Q63: Map | R63: Record
A64: Power of Life Alternative and Holistic Health | B64: Chiropractic | D64: Chiropractic | E64: 1700 Stieger Lake Ln | F64: Ste 103 | G64: Victoria | H64: Carver | I64: Twin Cities Metro | J64: 55386 | K64: (952) 443-9000 | L64: 1 | M64: No | N64: 45721 | O64: Power of Life Chiropractic, PA. | P64: 1316120272 | Q64: Map | R64: Record
A65: Movewell Chiropractc & Wellness | B65: Chiropractic | D65: Chiropractic | E65: 9360 Oak Ave | G65: Waconia | H65: Carver | I65: Twin Cities Metro | J65: 55387 | K65: (952) 466-6533 | L65: 3 | M65: No | N65: 46230 | O65: Movewell Chiropractc & Wellness | P65: 1972142081 | Q65: Map | R65: Record
A66: OMS Specialists | B66: Oral Surgery | D66: Oral & Maxillofacial Surgery | E66: 490 S Maple St | F66: Ste 102 | G66: Waconia | H66: Carver | I66: Twin Cities Metro | J66: 55387 | K66: (952) 442-5448 | L66: 1 | M66: No | N66: 41849 | O66: Oral & Maxillofacial Surgery Specialists, PA | P66: 1770694812 | Q66: Map | R66: Record
A67: Ridgeview Medical Center | B67: Imaging | D67: Radiology | E67: 500 S Maple St | G67: Waconia | H67: Carver | I67: Twin Cities Metro | J67: 55387 | K67: (952) 442-2191 | L67: 3 | M67: Yes | N67: 45268 | O67: Ridgeview Medical Center | P67: 1811174923 | Q67: Map | R67: Record
A68: Sunnydays Therapy INC | B68: Physical Therapy | D68: Physical Therapy | E68: 9346 Oak Ave | G68: Waconia | H68: Carver | I68: Twin Cities Metro | J68: 55387 | K68: (952) 223-2506 | L68: 3 | M68: No | N68: 45379 | O68: Sunnydays Therapy INC | P68: 1891914412 | Q68: Map | R68: Record
A69: Watertown Family Chiropractic | B69: Chiropractic | D69: Chiropractic | E69: 204 Lewis Ave S | F69: Sutie 203 | G69: Watertown | H69: Carver | I69: Twin Cities Metro | J69: 55388 | K69: (515) 320-3841 | L69: 1 | M69: No | N69: 44572 | O69: Ryan Goetz, PA. | P69: 1316185036 | Q69: Map | R69: Record
A70: North Branch Family Chiropractic LLC | B70: Chiropractic | D70: Chiropractic | E70: 6241 Main St | F70: Ste 102 | G70: North Branch | H70: Chisago | I70: Twin Cities Metro | J70: 55056 | K70: (651) 470-5422 | L70: 1 | M70: No | N70: 45751 | O70: North Branch Family Chiropractic LLC | P70: 1437943677 | Q70: Map | R70: Record
A71: Revive Chiropractic | B71: Chiropractic | D71: Chiropractic | E71: 6272 Main St | G71: North Branch | H71: Chisago | I71: Twin Cities Metro | J71: 55056 | K71: (651) 674-2700 | L71: 0 | M71: No | N71: 45090 | O71: Wurdemann Chiropractic PA | P71: 1578850061 | Q71: Map | R71: Record
A72: Sage Spine Pain and Nerve Center | B72: Injury Physicians | D72: Pain Management | E72: 38500 Tanger Dr | F72: Ste 110 | G72: North Branch | H72: Chisago | I72: Twin Cities Metro | J72: 55056 | K72: (651) 337-8201 | L72: 1 | M72: No | N72: 46029 | O72: Sage Spine Pain and Nerve Center | P72: 1588536197 | Q72: Map | R72: Record
A73: Weierke Chiropractic PA | B73: Chiropractic | D73: Chiropractic | E73: 386 Bench St | G73: Taylors Falls | H73: Chisago | I73: Twin Cities Metro | J73: 55084 | K73: (651) 465-3811 | L73: 0 | M73: No | N73: 45464 | O73: Weierke Chiropractic PA | P73: 1568876993 | Q73: Map | R73: Record
A74: Fairview Express Care | B74: Injury Physicians | D74: Pain Management | E74: 5200 Fairview Blvd | F74: Ste F | G74: Wyoming | H74: Chisago | I74: Twin Cities Metro | J74: 55092 | K74: (612) 273-5400 | L74: 0 | M74: Yes | N74: 45701 | O74: Fairview Express Care | P74: 1386193613 | Q74: Map | R74: Record
A75: Fairview Express Care | B75: Injury Physicians | D75: Pain Management | E75: 5130 Fairview Blvd | F75: Ste 101 | G75: Wyoming | H75: Chisago | I75: Twin Cities Metro | J75: 55092 | K75: (912) 273-5400 | L75: 0 | M75: Yes | N75: 45701 | O75: Fairview Express Care | P75: 1386193613 | Q75: Map | R75: Record
A76: Apex Family Chiropractic LLC | B76: Chiropractic | D76: Chiropractic | E76: 15678 Pilot Knob Road | F76: Ste 120 | G76: Apple Valley | H76: Dakota | I76: Twin Cities Metro | J76: 55124 | K76: (651) 456-8744 | L76: 1 | M76: No | N76: 44763 | O76: Apex Family Chiropractic LLC | P76: 1982126926 | Q76: Map | R76: Record
A77: Children's Therapy Center, INC | B77: Physical Therapy | D77: Physical Therapy | E77: 14635 Pennock Ave | F77: Ste 300 | G77: Apple Valley | H77: Dakota | I77: Twin Cities Metro | J77: 55124 | K77: (651) 994-9644 | L77: 8 | M77: No | N77: 46141 | O77: Children's Therapy Center, INC | P77: 1295809366 | Q77: Map | R77: Record
A78: Johnson Spinal Care Associates, PA. | B78: Chiropractic | D78: Chiropractic | E78: 14859 Energy Way | G78: Apple Valley | H78: Dakota | I78: Twin Cities Metro | J78: 55124 | K78: (952) 432-3333 | L78: 7 | M78: No | N78: 45005 | O78: Johnson Spinal Care Associates, PA. | P78: 1285711663 | Q78: Map | R78: Record
A79: Liberty Physical Therapy LLC | B79: Physical Therapy | D79: Physical Therapy | E79: 272 Cimarron Rd | G79: Apple Valley | H79: Dakota | I79: Twin Cities Metro | J79: 55124 | K79: (715) 495-6918 | L79: 0 | M79: No | N79: 44797 | O79: Liberty Physical Therapy LLC | P79: 1497474274 | Q79: Map | R79: Record
A80: Lifeway Chiropractic and Wellness LLC | B80: Chiropractic | D80: Chiropractic | E80: 7300 147th St W | F80: Ste 101 | G80: Apple Valley | H80: Dakota | I80: Twin Cities Metro | J80: 55124 | K80: (612) 508-2454 | L80: 6 | M80: No | N80: 45902 | O80: Lifeway Chiropractic and Wellness LLC | P80: 1962568576 | Q80: Map | R80: Record
A81: Niko Physical Therapy LLC | B81: Physical Therapy | D81: Physical Therapy | E81: 7300 147th St W | F81: Ste 403 | G81: Apple Valley | H81: Dakota | I81: Twin Cities Metro | J81: 55124 | K81: (952) 214-8724 | L81: 1 | M81: No | N81: 46031 | O81: Niko Physical Therapy LLC | P81: 1770440810 | Q81: Map | R81: Record
A82: North Star Balance LLC | B82: Physical Therapy | D82: Physical Therapy | E82: 15083 Flagstaff Ave | F82: Ste A | G82: Apple Valley | H82: Dakota | I82: Twin Cities Metro | J82: 55124 | K82: (612) 246-6900 | L82: 0 | M82: No | N82: 46114 | O82: North Star Balance LLC | P82: 1023959228 | Q82: Map | R82: Record
A83: Novacare Rehabilitation | B83: Physical Therapy | D83: Physical Therapy | E83: 15290 Pennock Ln | F83: Ste 120 | G83: Apple Valley | H83: Dakota | I83: Twin Cities Metro | J83: 55124 | K83: (952) 953-3711 | L83: 2 | M83: No | N83: 45951 | O83: Novacare Outpatient Rehabilitation East INC | P83: 1669668026 | Q83: Map | R83: Record
A84: Spinefocus Physical Therapy LLC | B84: Physical Therapy | D84: Physical Therapy | E84: 7300 147th St W | F84: Ste 403 | G84: Apple Valley | H84: Dakota | I84: Twin Cities Metro | J84: 55124 | K84: (651) 363-1449 | L84: 1 | M84: No | N84: 46119 | O84: Spinefocus Physical Therapy LLC | P84: 1013859305 | Q84: Map | R84: Record
A85: Therapy Partners, INC. | B85: Physical Therapy | D85: Physical Therapy | E85: 15160 Foliage Ave | F85: Ste 170 | G85: Apple Valley | H85: Dakota | I85: Twin Cities Metro | J85: 55124 | K85: (952) 683-1745 | L85: 5 | M85: No | N85: 46275 | O85: Therapy Partners, INC. | P85: 1407809494 | Q85: Map | R85: Record
A86: Therapy Partners, INC. | B86: Physical Therapy | D86: Physical Therapy | E86: 14665 Galaxie Ave | F86: Ste 320 | G86: Apple Valley | H86: Dakota | I86: Twin Cities Metro | J86: 55124 | K86: (952) 892-6777 | L86: 2 | M86: No | N86: 46275 | O86: Therapy Partners, INC. | P86: 1407809494 | Q86: Map | R86: Record
A87: Twin Cities Oral & Maxillofacial Surgery | B87: Oral Surgery | D87: Oral & Maxillofacial Surgery | E87: 14635 Pennock Ave | F87: #250 | G87: Apple Valley | H87: Dakota | I87: Twin Cities Metro | J87: 55124 | K87: (952) 432-1514 | L87: 0 | M87: No | N87: 44065 | O87: Twin Cities Oral & Maxillofacial Surgery PA | P87: 1821299041 | Q87: Map | R87: Record
A88: Bloom Chiropractic Center PA | B88: Chiropractic | D88: Chiropractic | E88: 1606 Cliff Rd E | G88: Burnsville | H88: Dakota | I88: Twin Cities Metro | J88: 55337 | K88: (952) 894-6300 | L88: 1 | M88: No | N88: 44733 | O88: Bloom Chiropractic Center PA | P88: 1417075532 | Q88: Map | R88: Record
A89: Chiroflex PLLC | B89: Chiropractic | D89: Chiropractic | E89: 1103 W Burnsville Pkwy | F89: Ste 120 | G89: Burnsville | H89: Dakota | I89: Twin Cities Metro | J89: 55337 | K89: (320) 699-0695 | L89: 1 | M89: No | N89: 45062 | O89: Chiroflex PLLC | P89: 1114618618 | Q89: Map | R89: Record
A90: Healthpro Chiropractic PC | B90: Chiropractic | D90: Chiropractic | E90: 150 E Travelers Trl | F90: Ste B | G90: Burnsville | H90: Dakota | I90: Twin Cities Metro | J90: 55337 | K90: (651) 463-8222 | L90: 3 | M90: No | N90: 45820 | O90: Healthpro Chiropractic PC | P90: 1730320276 | Q90: Map | R90: Record
A91: Heartlight Chiropractic, PA. | B91: Chiropractic | D91: Chiropractic | E91: 2960 Judicial Rd | F91: Ste 210 | G91: Burnsville | H91: Dakota | I91: Twin Cities Metro | J91: 55337 | K91: (952) 890-5694 | L91: 1 | M91: No | N91: 46022 | O91: Heartlight Chiropractic, PA. | P91: 1912184573 | Q91: Map | R91: Record
A92: Heartlight Chiropractic, PA. | B92: Chiropractic | D92: Chiropractic | E92: 13955 W Preserve Blvd | F92: Ste 200 | G92: Burnsville | H92: Dakota | I92: Twin Cities Metro | J92: 55337 | K92: (952) 890-5694 | L92: 9 | M92: No | N92: 46022 | O92: Heartlight Chiropractic, PA. | P92: 1912184573 | Q92: Map | R92: Record
A93: Inspired Spine Health / Tristate Brain & Spine Institute | B93: Injury Physicians | D93: Orthopedics, Spine | E93: 1601 Highway 13 E | F93: Ste 100 | G93: Burnsville | H93: Dakota | I93: Twin Cities Metro | J93: 55337 | K93: (320) 763-8888 | L93: 2 | M93: Yes | N93: 45176 | O93: Sunny S. Kim, MD PA | P93: 1205481041 | Q93: Map | R93: Record
A94: Institute For Orthopedics & Chiropractic, PLLC | B94: Chiropractic | C94: Physical Therapy | D94: Chiropractic, Physical Therapy | E94: 14300 Buck Hill Rd | F94: Ste E | G94: Burnsville | H94: Dakota | I94: Twin Cities Metro | J94: 55306 | K94: (952) 941-3311 | L94: 4 | M94: No | N94: 46161 | O94: Institute For Orthopedics & Chiropractic, PLLC | P94: 1710216858 | Q94: Map | R94: Record
A95: Integrate Chiropractic PLLC | B95: Chiropractic | D95: Chiropractic | E95: 1103 W Burnsville Pkwy | F95: Ste 120 | G95: Burnsville | H95: Dakota | I95: Twin Cities Metro | J95: 55337 | K95: (952) 300-1461 | L95: 1 | M95: No | N95: 45706 | O95: Integrate Chiropractic PLLC | P95: 1295366888 | Q95: Map | R95: Record
A96: Integrative Orthopedic Clinics, PLLC | B96: Physical Therapy | C96: Chiropractic | D96: Chiropractic, Physical Therapy | E96: 14300 Buck Hill Rd | F96: Ste E | G96: Burnsville | H96: Dakota | I96: Twin Cities Metro | J96: 55306 | K96: (952) 941-3311 | L96: 4 | M96: No | N96: 46148 | O96: Integrative Orthopedic Clinics, PLLC | P96: 1558208033 | Q96: Map | R96: Record
A97: Limitless, PLLC | B97: Chiropractic | D97: Chiropractic | E97: 14612 Burnell Park Dr | G97: Burnsville | H97: Dakota | I97: Twin Cities Metro | J97: 55306 | K97: (952) 314-8449 | L97: 0 | M97: No | N97: 45813 | O97: Limitless, PLLC | P97: 1750871372 | Q97: Map | R97: Record
A98: Metro Dentalcare Specialty Center Burnsville - Oral Surgery | B98: Oral Surgery | D98: Oral & Maxillofacial Surgery | E98: 14344 Burnhaven Dr | G98: Burnsville | H98: Dakota | I98: Twin Cities Metro | J98: 55306 | K98: (612) 638-1238 | L98: 1 | M98: No | N98: 44642 | O98: Family Oral Surgery Specialists, PLC | P98: 1407505829 | Q98: Map | R98: Record
A99: Minnesota Head and Neck Pain Clinic, PA | B99: TMJ Specialists | D99: TMJ Clinic | E99: 675 E Nicollet Blvd | F99: Ste 255 | G99: Burnsville | H99: Dakota | I99: Twin Cities Metro | J99: 55337 | K99: (952) 892-6222 | L99: 4 | M99: No | N99: 45490 | O99: Minnesota Head and Neck Pain Clinic, PA | P99: 1255715181 | Q99: Map | R99: Record
A100: Mprove Physical Therapy, LLC | B100: Physical Therapy | D100: Physical Therapy | E100: 1103 W Burnsville Pkwy | F100: Ste 120 | G100: Burnsville | H100: Dakota | I100: Twin Cities Metro | J100: 55337 | K100: (952) 300-1461 | L100: 1 | M100: No | N100: 45169 | O100: Mprove Physical Therapy, LLC | P100: 1538842711 | Q100: Map | R100: Record
...

Sheet Injury Physicians
A1: Clinic Name | B1: Specialty Group | C1: Also In | D1: Specialties | E1: Street | F1: Suite | G1: City | H1: County | I1: Region | J1: ZIP | K1: Phone | L1: Providers at Address | M1: On Xpert Connect | N1: Registry Updated | O1: Legal Name | P1: NPI | Q1: Map | R1: NPPES Record
A2: HealthPartners Riverway Pain Clinic | B2: Injury Physicians | D2: Pain Management | E2: 2621 Greenhaven Rd | G2: Anoka | H2: Anoka | I2: Twin Cities Metro | J2: 55303 | K2: (763) 587-4488 | L2: 0 | M2: No | N2: 46240 | O2: Group Health, INC. | P2: 1689068462 | Q2: Map | R2: Record
A3: Summit Orthopedics, LTD | B3: Injury Physicians | D3: Orthopedics, Sports Medicine | E3: 10230 Baltimore St NE | F3: Ste 300 | G3: Blaine | H3: Anoka | I3: Twin Cities Metro | J3: 55449 | K3: (651) 968-5200 | L3: 2 | M3: Yes | N3: 45818 | O3: Summit Orthopedics, LTD | P3: 1043566045 | Q3: Map | R3: Record
A4: Allina Health Brain and Spine Institute - Coon Rapids | B4: Injury Physicians | D4: Neurosurgery | E4: 11850 Blackfoot St NW | F4: Ste 490 | G4: Coon Rapids | H4: Anoka | I4: Twin Cities Metro | J4: 55433 | K4: (612) 871-7278 | L4: 5 | M4: Yes | N4: 46036 | O4: Allina Health System | P4: 1275351413 | Q4: Map | R4: Record
A5: Courage Kenny Rehabilitation Associates | B5: Injury Physicians | D5: Physical Medicine & Rehabilitation | E5: 11850 Blackfoot St NW | F5: Ste 405 | G5: Coon Rapids | H5: Anoka | I5: Twin Cities Metro | J5: 55433 | K5: (763) 236-0888 | L5: 3 | M5: Yes | N5: 45713 | O5: Allina Health System | P5: 1770034670 | Q5: Map | R5: Record
A6: Metropolitan Neurosurgery, PA | B6: Injury Physicians | D6: Neurosurgery | E6: 11850 Blackfoot St NW | F6: Ste 490 | G6: Coon Rapids | H6: Anoka | I6: Twin Cities Metro | J6: 55433 | K6: (763) 427-1137 | L6: 5 | M6: No | N6: 45394 | O6: Metropolitan Neurosurgery, PA | P6: 1386690543 | Q6: Map | R6: Record
A7: Minnesota Neurosurgical Trauma Associates, PLLC | B7: Injury Physicians | D7: Neurosurgery | E7: 11850 Blackfoot St NW | F7: Ste 490 | G7: Coon Rapids | H7: Anoka | I7: Twin Cities Metro | J7: 55433 | K7: (763) 427-1137 | L7: 5 | M7: No | N7: 45407 | O7: Minnesota Neurosurgical Trauma Associates, PLLC | P7: 1922241884 | Q7: Map | R7: Record
A8: Pdr Coon Rapids, INC | B8: Injury Physicians | C8: Chiropractic, Physical Therapy | D8: Physical Medicine & Rehabilitation, Chiropractic, Physical Therapy | E8: 320 Coon Rapids Blvd NW | F8: #100 | G8: Coon Rapids | H8: Anoka | I8: Twin Cities Metro | J8: 55433 | K8: (952) 908-2580 | L8: 5 | M8: No | N8: 45911 | O8: Pdr Coon Rapids, INC | P8: 1477666428 | Q8: Map | R8: Record
A9: Nura PLLC | B9: Injury Physicians | D9: Pain Management | E9: 2104 Northdale Boulevard NW | F9: Ste 220 | G9: Minneapolis | H9: Anoka | I9: Twin Cities Metro | J9: 55433 | K9: (763) 537-6000 | L9: 10 | M9: No | N9: 46253 | O9: Nura PLLC | P9: 1750316014 | Q9: Map | R9: Record
A10: Ahc Medical, PC | B10: Injury Physicians | D10: Physical Medicine & Rehabilitation | E10: 1476 White Oak Dr | G10: Chaska | H10: Carver | I10: Twin Cities Metro | J10: 55318 | K10: (952) 448-3900 | L10: 0 | M10: No | N10: 44971 | O10: Ahc Medical, PC | P10: 1336846955 | Q10: Map | R10: Record
A11: Twin Cities Pain Clinic | B11: Injury Physicians | D11: Pain Management, Physical Medicine & Rehabilitation | E11: 584 Bavaria Ln | G11: Chaska | H11: Carver | I11: Twin Cities Metro | J11: 55318 | K11: (952) 841-2345 | L11: 4 | M11: No | N11: 45027 | O11: Andrew J Will MD PA | P11: 1669167920 | Q11: Map | R11: Record
A12: Sage Spine Pain and Nerve Center | B12: Injury Physicians | D12: Pain Management | E12: 38500 Tanger Dr | F12: Ste 110 | G12: North Branch | H12: Chisago | I12: Twin Cities Metro | J12: 55056 | K12: (651) 337-8201 | L12: 1 | M12: No | N12: 46029 | O12: Sage Spine Pain and Nerve Center | P12: 1588536197 | Q12: Map | R12: Record
A13: Fairview Express Care | B13: Injury Physicians | D13: Pain Management | E13: 5200 Fairview Blvd | F13: Ste F | G13: Wyoming | H13: Chisago | I13: Twin Cities Metro | J13: 55092 | K13: (612) 273-5400 | L13: 0 | M13: Yes | N13: 45701 | O13: Fairview Express Care | P13: 1386193613 | Q13: Map | R13: Record
A14: Fairview Express Care | B14: Injury Physicians | D14: Pain Management | E14: 5130 Fairview Blvd | F14: Ste 101 | G14: Wyoming | H14: Chisago | I14: Twin Cities Metro | J14: 55092 | K14: (912) 273-5400 | L14: 0 | M14: Yes | N14: 45701 | O14: Fairview Express Care | P14: 1386193613 | Q14: Map | R14: Record
A15: Inspired Spine Health / Tristate Brain & Spine Institute | B15: Injury Physicians | D15: Orthopedics, Spine | E15: 1601 Highway 13 E | F15: Ste 100 | G15: Burnsville | H15: Dakota | I15: Twin Cities Metro | J15: 55337 | K15: (320) 763-8888 | L15: 2 | M15: Yes | N15: 45176 | O15: Sunny S. Kim, MD PA | P15: 1205481041 | Q15: Map | R15: Record
A16: Pdr Burnsville, INC | B16: Injury Physicians | C16: Chiropractic, Physical Therapy | D16: Physical Medicine & Rehabilitation, Chiropractic, Physical Therapy | E16: 14050 Nicollet Ave | F16: #114 | G16: Burnsville | H16: Dakota | I16: Twin Cities Metro | J16: 55337 | K16: (952) 908-2710 | L16: 1 | M16: No | N16: 45911 | O16: Pdr Burnsville, INC | P16: 1952414971 | Q16: Map | R16: Record
A17: Summit Orthopedics, LTD. | B17: Injury Physicians | D17: Orthopedics | E17: 14101 Fairview Dr | F17: Ste 300 | G17: Burnsville | H17: Dakota | I17: Twin Cities Metro | J17: 55337 | K17: (651) 968-5201 | L17: 2 | M17: Yes | N17: 45978 | O17: Summit Orthopedics, LTD. | P17: 1376403857 | Q17: Map | R17: Record
A18: Sunny S. Kim, MD PA | B18: Injury Physicians | D18: Orthopedics, Spine, Neurosurgery | E18: 1601 Highway 13 E | F18: Ste 100 | G18: Burnsville | H18: Dakota | I18: Twin Cities Metro | J18: 55337 | K18: (320) 763-8888 | L18: 3 | M18: Yes | N18: 46087 | O18: Sunny S. Kim, MD PA | P18: 1659301992 | Q18: Map | R18: Record
A19: Summit Orthopedics, LTD | B19: Injury Physicians | C19: Physical Therapy | D19: Orthopedics, Physical Therapy | E19: 2620 Eagan Woods Dr | G19: Eagan | H19: Dakota | I19: Twin Cities Metro | J19: 55121 | K19: (651) 968-5200 | L19: 23 | M19: Yes | N19: 45867 | O19: Summit Orthopedics, LTD | P19: 1063563518 | Q19: Map | R19: Record
A20: Allina Health Nininger Road Clinic | B20: Injury Physicians | D20: Sports Medicine | E20: 1285 Nininger Rd | G20: Hastings | H20: Dakota | I20: Twin Cities Metro | J20: 55033 | K20: (651) 480-4200 | L20: 0 | M20: No | N20: 46143 | O20: Allina Health System | P20: 1578869293 | Q20: Map | R20: Record
A21: Allina Health Brain and Spine Institute | B21: Injury Physicians | D21: Neurosurgery | E21: 18465 Orchard Trl | G21: Lakeville | H21: Dakota | I21: Twin Cities Metro | J21: 55044 | K21: (800) 827-8313 | L21: 0 | M21: No | N21: 46036 | O21: Allina Health System | P21: 1144264540 | Q21: Map | R21: Record
A22: Allina Health Lakeville Specialty Center | B22: Injury Physicians | D22: Orthopedics | E22: 18465 Orchard Trl | G22: Lakeville | H22: Dakota | I22: Twin Cities Metro | J22: 55044 | K22: (952) 428-0950 | L22: 0 | M22: No | N22: 45671 | O22: Allina Health System | P22: 1003683244 | Q22: Map | R22: Record
A23: Summit Orthopedics, LTD | B23: Injury Physicians | C23: Imaging | D23: Orthopedics, MRI | E23: 17210 Kenyon Ave | G23: Lakeville | H23: Dakota | I23: Twin Cities Metro | J23: 55044 | K23: (651) 968-5201 | L23: 0 | M23: No | N23: 45818 | O23: Summit Orthopedics, LTD | P23: 1629740949 | Q23: Map | R23: Record
A24: Entira Family Clinics-West St. Paul | B24: Injury Physicians | D24: Sports Medicine, Physical Medicine & Rehabilitation | E24: 234 Wentworth Ave E | G24: West St Paul | H24: Dakota | I24: Twin Cities Metro | J24: 55118 | K24: (651) 788-4444 | L24: 0 | M24: No | N24: 45944 | O24: Family Healthservices Minnesota, PA. | P24: 1801076526 | Q24: Map | R24: Record
A25: Infinite Health Collaborative, PA | B25: Injury Physicians | C25: Physical Therapy, Imaging | D25: Orthopedics, Physical Therapy, Radiology | E25: 3500 American Blvd W | F25: Ste 300 | G25: Bloomington | H25: Hennepin | I25: Twin Cities Metro | J25: 55431 | K25: (952) 512-5600 | L25: 0 | M25: Yes | N25: 46177 | O25: Infinite Health Collaborative, PA | P25: 1265675870 | Q25: Map | R25: Record
A26: Ltc Professionals, PLLC | B26: Injury Physicians | D26: Pain Management | E26: 7801 East Bush Lake Rd | F26: Ste 400 | G26: Bloomington | H26: Hennepin | I26: Twin Cities Metro | J26: 55439 | K26: (952) 479-4261 | L26: 0 | M26: No | N26: 45498 | O26: Ltc Professionals, PLLC | P26: 1417251935 | Q26: Map | R26: Record
A27: National Dizzy & Balance Center,ltd. | B27: Injury Physicians | C27: Physical Therapy | D27: Physical Medicine & Rehabilitation, Physical Therapy | E27: 4801 W 81st St | F27: Ste 112 | G27: Bloomington | H27: Hennepin | I27: Twin Cities Metro | J27: 55437 | K27: (952) 345-3000 | L27: 19 | M27: No | N27: 44901 | O27: National Dizzy & Balance Center,ltd. | P27: 1023021938 | Q27: Map | R27: Record
A28: Tria Orthopaedic Center LLC | B28: Injury Physicians | C28: Physical Therapy | D28: Orthopedics, Pain Management, Physical Therapy | E28: 8100 Northland Dr | G28: Bloomington | H28: Hennepin | I28: Twin Cities Metro | J28: 55431 | K28: (952) 831-8742 | L28: 78 | M28: Yes | N28: 46237 | O28: Tria Orthopaedic Center LLC | P28: 1346624384 | Q28: Map | R28: Record
A29: Tria Orthopaedic Clinic | B29: Injury Physicians | C29: Physical Therapy | D29: Orthopedics, Pain Management, Physical Therapy | E29: 8100 Northland Dr | G29: Bloomington | H29: Hennepin | I29: Twin Cities Metro | J29: 55431 | K29: (952) 831-8742 | L29: 78 | M29: Yes | N29: 46237 | O29: Tria Orthopaedic Center LLC | P29: 1518273085 | Q29: Map | R29: Record
A30: Allina Health Orthopedics | B30: Injury Physicians | D30: Orthopedics, Sports Medicine | E30: 6001 96th Ln N | F30: Ste 100 | G30: Brooklyn Park | H30: Hennepin | I30: Twin Cities Metro | J30: 55445 | K30: (952) 946-9777 | L30: 0 | M30: No | N30: 46042 | O30: Allina Health System | P30: 1508099656 | Q30: Map | R30: Record
A31: Team Care Clinic | B31: Chiropractic | C31: Injury Physicians | D31: Sports Medicine, Chiropractic | E31: 12217 Champlin Dr | G31: Champlin | H31: Hennepin | I31: Twin Cities Metro | J31: 55316 | K31: (763) 323-1492 | L31: 5 | M31: No | N31: 44881 | O31: Team Health Care Clinic PC | P31: 1457458689 | Q31: Map | R31: Record
A32: Allina Health Eden Prairie Clinic | B32: Injury Physicians | D32: Orthopedics | E32: 775 Prairie Center Dr | F32: Ste 400 | G32: Eden Prairie | H32: Hennepin | I32: Twin Cities Metro | J32: 55344 | K32: (612) 262-1166 | L32: 1 | M32: Yes | N32: 45716 | O32: Allina Health System | P32: 1699501601 | Q32: Map | R32: Record
A33: Odom Health & Wellness | B33: Injury Physicians | D33: Sports Medicine | E33: 6545 Flying Cloud Dr | F33: Ste 201 | G33: Eden Prairie | H33: Hennepin | I33: Twin Cities Metro | J33: 55344 | K33: (952) 224-1919 | L33: 1 | M33: No | N33: 46141 | O33: Odom Sports Medicine, PA. | P33: 1275557886 | Q33: Map | R33: Record
A34: Summit Orthopedics LTD | B34: Injury Physicians | D34: Orthopedics | E34: 11995 Singletree Ln | F34: Ste 325 | G34: Eden Prairie | H34: Hennepin | I34: Twin Cities Metro | J34: 55344 | K34: (651) 968-5201 | L34: 0 | M34: Yes | N34: 45145 | O34: Summit Orthopedics LTD | P34: 1417639626 | Q34: Map | R34: Record
A35: Allina Health Orthopedics | B35: Injury Physicians | D35: Orthopedics, Sports Medicine | E35: 8100 W 78th St | F35: Ste 230 | G35: Edina | H35: Hennepin | I35: Twin Cities Metro | J35: 55439 | K35: (952) 946-9777 | L35: 43 | M35: Yes | N35: 46042 | O35: Allina Health System | P35: 1508099656 | Q35: Map | R35: Record
A36: Innerwell | B36: Injury Physicians | D36: Pain Management | E36: 5201 Eden Ave | F36: Ste 300 | G36: Edina | H36: Hennepin | I36: Twin Cities Metro | J36: 55436 | K36: (909) 679-3482 | L36: 0 | M36: No | N36: 46128 | O36: Kbs Medical PA | P36: 1295461036 | Q36: Map | R36: Record
A37: Joint Relief Institute | B37: Injury Physicians | D37: Pain Management | E37: 7201 Ohms Ln | F37: Ste 100 | G37: Edina | H37: Hennepin | I37: Twin Cities Metro | J37: 55439 | K37: (708) 726-6694 | L37: 0 | M37: No | N37: 45236 | O37: Karas PLLC | P37: 1811778533 | Q37: Map | R37: Record
A38: Minnesota Neurorehabilitation Institute, PLLC | B38: Injury Physicians | D38: Physical Medicine & Rehabilitation | E38: 7400 Metro Blvd | F38: Ste 400 | G38: Edina | H38: Hennepin | I38: Twin Cities Metro | J38: 55439 | K38: (612) 999-1908 | L38: 1 | M38: No | N38: 45632 | O38: Minnesota Neurorehabilitation Institute, PLLC | P38: 1083253991 | Q38: Map | R38: Record
A39: Minworx Health, LLC | B39: Injury Physicians | D39: Orthopedics | E39: 7505 Metro Blvd | F39: Ste 510 | G39: Edina | H39: Hennepin | I39: Twin Cities Metro | J39: 55439 | K39: (612) 808-9870 | L39: 0 | M39: Yes | N39: 46038 | O39: Minworx Health, LLC | P39: 1225916745 | Q39: Map | R39: Record
A40: Nura PLLC | B40: Injury Physicians | D40: Pain Management | E40: 7400 France Ave S | F40: Ste 100 | G40: Edina | H40: Hennepin | I40: Twin Cities Metro | J40: 55435 | K40: (763) 537-6000 | L40: 8 | M40: No | N40: 46253 | O40: Nura PLLC | P40: 1750316014 | Q40: Map | R40: Record
A41: Orthopaedic Institute Surgery Center | B41: Injury Physicians | D41: Orthopedics | E41: 8100 W 78th St | F41: Ste 220 | G41: Edina | H41: Hennepin | I41: Twin Cities Metro | J41: 55439 | K41: (952) 248-5970 | L41: 33 | M41: No | N41: 46161 | O41: Southwest Surgical Center LLC | P41: 1306829866 | Q41: Map | R41: Record
A42: Pdr Southdale, INC | B42: Injury Physicians | C42: Chiropractic, Physical Therapy | D42: Physical Medicine & Rehabilitation, Chiropractic, Physical Therapy | E42: 3400 W 66th St | F42: Ste 450 | G42: Edina | H42: Hennepin | I42: Twin Cities Metro | J42: 55435 | K42: (952) 908-2700 | L42: 41 | M42: No | N42: 45911 | O42: Pdr Southdale, INC | P42: 1073626008 | Q42: Map | R42: Record
A43: Premier Spine and Pain Clinics, PLLC | B43: Injury Physicians | D43: Pain Management | E43: 7450 S France Ave | F43: Ste 240 | G43: Edina | H43: Hennepin | I43: Twin Cities Metro | J43: 55435 | K43: (612) 353-4238 | L43: 0 | M43: No | N43: 44642 | O43: Premier Spine and Pain Clinics, PLLC | P43: 1598414997 | Q43: Map | R43: Record
A44: Rehabilitation Medicine Associates, LLC | B44: Injury Physicians | D44: Physical Medicine & Rehabilitation | E44: 464 2nd St | F44: Ste 204 | G44: Excelsior | H44: Hennepin | I44: Twin Cities Metro | J44: 55331 | K44: (312) 262-6434 | L44: 0 | M44: No | N44: 45995 | O44: Rehabilitation Medicine Associates, LLC | P44: 1093103145 | Q44: Map | R44: Record
A45: Sipple Medical Innovations LLC | B45: Injury Physicians | D45: Pain Management, Physical Medicine & Rehabilitation | E45: 10285 Yellow Circle Dr | G45: Hopkins | H45: Hennepin | I45: Twin Cities Metro | J45: 55343 | K45: (612) 470-3128 | L45: 0 | M45: No | N45: 45015 | O45: Sipple Medical Innovations LLC | P45: 1861866816 | Q45: Map | R45: Record
A46: Advanced Hand and Upper Extremity Center PC | B46: Injury Physicians | D46: Orthopedics | E46: 9325 Upland Ln N | F46: # 255 | G46: Maple Grove | H46: Hennepin | I46: Twin Cities Metro | J46: 55369 | K46: (701) 388-2196 | L46: 2 | M46: No | N46: 44794 | O46: Advanced Hand and Upper Extremity Center PC | P46: 1689343600 | Q46: Map | R46: Record
A47: Interventional Spine and Pain Physicians, PA | B47: Injury Physicians | C47: Physical Therapy | D47: Pain Management, Physical Medicine & Rehabilitation, Physical Therapy | E47: 9645 Grove Cir N | F47: Ste 200 | G47: Maple Grove | H47: Hennepin | I47: Twin Cities Metro | J47: 55369 | K47: (763) 201-8191 | L47: 7 | M47: No | N47: 46287 | O47: Interventional Spine and Pain Physicians, PA | P47: 1326398561 | Q47: Map | R47: Record
A48: Metropolitan Surgical Center, LLC | B48: Injury Physicians | D48: Pain Management | E48: 9645 Grove Cir N | F48: Ste 250 | G48: Maple Grove | H48: Hennepin | I48: Twin Cities Metro | J48: 55369 | K48: (763) 201-8191 | L48: 5 | M48: No | N48: 46287 | O48: Metropolitan Surgical Center, LLC | P48: 1144745951 | Q48: Map | R48: Record
A49: Summit Orthopedics, LTD | B49: Injury Physicians | D49: Orthopedics | E49: 9825 Hospital Dr | F49: Ste 10 | G49: Maple Grove | H49: Hennepin | I49: Twin Cities Metro | J49: 55369 | K49: (651) 968-5201 | L49: 0 | M49: Yes | N49: 45195 | O49: Summit Orthopedics, LTD | P49: 1295402774 | Q49: Map | R49: Record
A50: Twin Cities Pain Clinic | B50: Injury Physicians | D50: Physical Medicine & Rehabilitation | E50: 12000 Elm Creek Blvd N | F50: Ste 300 | G50: Maple Grove | H50: Hennepin | I50: Twin Cities Metro | J50: 55369 | K50: (952) 841-2345 | L50: 2 | M50: No | N50: 44984 | O50: Andrew J Will MD PA | P50: 1750797072 | Q50: Map | R50: Record
A51: Advanced Spine and Pain Clinics of Minnesota LLC | B51: Injury Physicians | D51: Pain Management, Physical Medicine & Rehabilitation | E51: 2801 Wayzata Blvd | G51: Minneapolis | H51: Hennepin | I51: Twin Cities Metro | J51: 55405 | K51: (612) 207-7463 | L51: 0 | M51: No | N51: 44599 | O51: Advanced Spine and Pain Clinics of Minnesota LLC | P51: 1891055851 | Q51: Map | R51: Record
A52: Allina Health Brain and Spine Institute | B52: Injury Physicians | D52: Neurosurgery | E52: 913 E 26th St | F52: Ste 304 | G52: Minneapolis | H52: Hennepin | I52: Twin Cities Metro | J52: 55404 | K52: (612) 863-3200 | L52: 8 | M52: Yes | N52: 46036 | O52: Allina Health System | P52: 1144264540 | Q52: Map | R52: Record
A53: Allina Health Orthopedics | B53: Injury Physicians | D53: Orthopedics, Sports Medicine | E53: 2800 Chicago Ave | F53: Ste 400 | G53: Minneapolis | H53: Hennepin | I53: Twin Cities Metro | J53: 55407 | K53: (952) 946-9777 | L53: 2 | M53: Yes | N53: 46042 | O53: Allina Health System | P53: 1508099656 | Q53: Map | R53: Record
A54: Allina Health System | B54: Injury Physicians | D54: Physical Medicine & Rehabilitation | E54: 2833 Chicago Ave | G54: Minneapolis | H54: Hennepin | I54: Twin Cities Metro | J54: 55407 | K54: (612) 863-3333 | L54: 0 | M54: Yes | N54: 45712 | O54: Allina Health System | P54: 1528259132 | Q54: Map | R54: Record
A55: Chronic Pain Management | B55: Injury Physicians | D55: Pain Management | E55: 800 E 28th St | G55: Minneapolis | H55: Hennepin | I55: Twin Cities Metro | J55: 55407 | K55: (612) 863-4495 | L55: 4 | M55: Yes | N55: 45679 | O55: Allina Health System | P55: 1316980386 | Q55: Map | R55: Record
A56: Courage Kenny Rehab Associates | B56: Injury Physicians | D56: Physical Medicine & Rehabilitation | E56: 800 E 28th St | F56: Ste 1750 | G56: Minneapolis | H56: Hennepin | I56: Twin Cities Metro | J56: 55407 | K56: (612) 863-4495 | L56: 23 | M56: Yes | N56: 45673 | O56: Allina Health System | P56: 1275577215 | Q56: Map | R56: Record
A57: M Health Fairview Pain Clinic - Minneapolis | B57: Injury Physicians | D57: Pain Management | E57: 606 24th Ave S | F57: Ste 600 | G57: Minneapolis | H57: Hennepin | I57: Twin Cities Metro | J57: 55454 | K57: (612) 273-5400 | L57: 1 | M57: No | N57: 45701 | O57: Fairview Express Care | P57: 1457397150 | Q57: Map | R57: Record
A58: Minnesota Pain Prevention Clinic, PA. | B58: Injury Physicians | D58: Pain Management | E58: 3475 Plymouth Blvd | F58: Ste 200 | G58: Minneapolis | H58: Hennepin | I58: Twin Cities Metro | J58: 55447 | K58: (612) 619-1678 | L58: 1 | M58: No | N58: 44754 | O58: Minnesota Pain Prevention Clinic, PA. | P58: 1285368514 | Q58: Map | R58: Record
A59: Neura Health | B59: Injury Physicians | D59: Neurology | E59: 333 Washington Ave N | F59: FL 3 | G59: Minneapolis | H59: Hennepin | I59: Twin Cities Metro | J59: 55401 | K59: (313) 887-0960 | L59: 0 | M59: No | N59: 46267 | O59: On Demand Neurology PA | P59: 1265016174 | Q59: Map | R59: Record
A60: Neurosurgical Associates | B60: Injury Physicians | D60: Neurosurgery | E60: 913 E 26th St | F60: Ste 305 | G60: Minneapolis | H60: Hennepin | I60: Twin Cities Metro | J60: 55404 | K60: (612) 871-7278 | L60: 8 | M60: Yes | N60: 45713 | O60: Allina Health System | P60: 1730532631 | Q60: Map | R60: Record
A61: Nura PLLC | B61: Injury Physicians | D61: Pain Management | E61: 7390 France Ave S | G61: Minneapolis | H61: Hennepin | I61: Twin Cities Metro | J61: 55435 | K61: (763) 537-6000 | L61: 6 | M61: No | N61: 46253 | O61: Nura PLLC | P61: 1750316014 | Q61: Map | R61: Record
A62: Pain & Injury Center PLLC | B62: Injury Physicians | D62: Pain Management, Physical Medicine & Rehabilitation | E62: 825 Nicollet Mall | F62: Ste #1453 | G62: Minneapolis | H62: Hennepin | I62: Twin Cities Metro | J62: 55402 | K62: (612) 886-1562 | L62: 1 | M62: No | N62: 44763 | O62: Pain & Injury Center PLLC | P62: 1063842243 | Q62: Map | R62: Record
A63: Pointcare Family and Behavioral Health INC. | B63: Injury Physicians | D63: Pain Management | E63: 825 Nicollet Mall | F63: Ste 401 | G63: Minneapolis | H63: Hennepin | I63: Twin Cities Metro | J63: 55402 | K63: (612) 286-8674 | L63: 0 | M63: No | N63: 46158 | O63: Pointcare Family and Behavioral Health INC. | P63: 1740035153 | Q63: Map | R63: Record
A64: University Anesthesia Providers, LLC | B64: Injury Physicians | D64: Pain Management | E64: 2450 Riverside Ave | G64: Minneapolis | H64: Hennepin | I64: Twin Cities Metro | J64: 55454 | K64: (612) 273-3000 | L64: 5 | M64: No | N64: 45400 | O64: University Anesthesia Providers, LLC | P64: 1699711143 | Q64: Map | R64: Record
A65: Downtown Orthopedics, PA. | B65: Injury Physicians | D65: Orthopedics | E65: 13911 Ridgedale Dr | F65: Ste 402 | G65: Minnetonka | H65: Hennepin | I65: Twin Cities Metro | J65: 55305 | K65: (763) 545-9130 | L65: 1 | M65: Yes | N65: 46021 | O65: Downtown Orthopedics, PA. | P65: 1295841625 | Q65: Map | R65: Record
A66: Moderni Spine PLLC | B66: Injury Physicians | D66: Pain Management | E66: 3454 County Road 101 | G66: Minnetonka | H66: Hennepin | I66: Twin Cities Metro | J66: 55345 | K66: (651) 323-0850 | L66: 0 | M66: No | N66: 45815 | O66: Moderni Spine PLLC | P66: 1275231698 | Q66: Map | R66: Record
A67: Summit Orthopedics, LTD | B67: Injury Physicians | C67: Physical Therapy | D67: Orthopedics, Physical Therapy | E67: 15450 Highway 7 | F67: Ste 125 | G67: Minnetonka | H67: Hennepin | I67: Twin Cities Metro | J67: 55345 | K67: (651) 968-5201 | L67: 3 | M67: Yes | N67: 45818 | O67: Summit Orthopedics, LTD | P67: 1457028946 | Q67: Map | R67: Record
A68: Allina Health Brain and Spine Institute | B68: Injury Physicians | D68: Neurosurgery | E68: 2855 Campus Dr | F68: Ste 610 | G68: Plymouth | H68: Hennepin | I68: Twin Cities Metro | J68: 55441 | K68: (612) 871-7278 | L68: 1 | M68: Yes | N68: 46036 | O68: Allina Health System | P68: 1144264540 | Q68: Map | R68: Record
A69: Allina Health Medical Spine | B69: Injury Physicians | D69: Orthopedics, Spine | E69: 2855 Campus Dr | F69: Ste 300 | G69: Plymouth | H69: Hennepin | I69: Twin Cities Metro | J69: 55441 | K69: (800) 827-8313 | L69: 1 | M69: Yes | N69: 45671 | O69: Allina Health System | P69: 1063279677 | Q69: Map | R69: Record
A70: Allina Health Neuroscience, Spine, and Pain | B70: Injury Physicians | D70: Orthopedics, Neurosurgery | E70: 2855 Campus Dr | F70: Ste 300 | G70: Plymouth | H70: Hennepin | I70: Twin Cities Metro | J70: 55441 | K70: (612) 262-1166 | L70: 2 | M70: Yes | N70: 45272 | O70: Allina Health System | P70: 1518735331 | Q70: Map | R70: Record
A71: Allina Health Orthopedics | B71: Injury Physicians | D71: Orthopedics, Sports Medicine | E71: 2805 Campus Dr | F71: Ste 465 | G71: Plymouth | H71: Hennepin | I71: Twin Cities Metro | J71: 55441 | K71: (763) 577-7425 | L71: 2 | M71: Yes | N71: 46042 | O71: Allina Health System | P71: 1508099656 | Q71: Map | R71: Record
A72: Dpc Medical | B72: Injury Physicians | D72: Pain Management | E72: 28 Nathan Ln N | G72: Plymouth | H72: Hennepin | I72: Twin Cities Metro | J72: 55441 | K72: (763) 588-7099 | L72: 0 | M72: No | N72: 45337 | O72: Dodson Pain Consultants PA Corp | P72: 1275881971 | Q72: Map | R72: Record
A73: Infusion Associates | B73: Injury Physicians | D73: Neurology | E73: 15655 37th Ave N | F73: Ste 250 | G73: Plymouth | H73: Hennepin | I73: Twin Cities Metro | J73: 55446 | K73: (763) 316-0750 | L73: 2 | M73: No | N73: 46044 | O73: Midwest Immunology Clinics, PLLC | P73: 1457417933 | Q73: Map | R73: Record
A74: Ascend Rehab, LLC | B74: Physical Therapy | C74: Injury Physicians | D74: Physical Medicine & Rehabilitation, Physical Therapy | E74: 1660 Highway 100 S | F74: Ste 103 | G74: St. Louis Park | H74: Hennepin | I74: Twin Cities Metro | J74: 55416 | K74: (952) 292-5801 | L74: 2 | M74: No | N74: 45475 | O74: Ascend Rehab, LLC | P74: 1437403110 | Q74: Map | R74: Record
A75: Guidestar Eldercare - MN | B75: Injury Physicians | D75: Neurology | E75: 1650 W End Blvd | F75: Ste 100 | G75: St. Louis Park | H75: Hennepin | I75: Twin Cities Metro | J75: 55416 | K75: (574) 546-1900 | L75: 0 | M75: No | N75: 46241 | O75: Guidestar Eldercare - MN | P75: 1710809769 | Q75: Map | R75: Record
A76: Ropan Surgical Services LLC | B76: Injury Physicians | D76: Orthopedics | E76: 1382 Hunter Dr | G76: Wayzata | H76: Hennepin | I76: Twin Cities Metro | J76: 55391 | K76: (612) 961-2672 | L76: 0 | M76: No | N76: 46282 | O76: Ropan Surgical Services LLC | P76: 1609787530 | Q76: Map | R76: Record
A77: Volker Sports & Physical Medicine PLLC | B77: Injury Physicians | D77: Physical Medicine & Rehabilitation | E77: 236 2nd Ave SW | G77: Cambridge | H77: Isanti | I77: Twin Cities Metro | J77: 55008 | K77: (763) 689-2462 | L77: 1 | M77: No | N77: 45980 | O77: Volker Sports & Physical Medicine PLLC | P77: 1942161054 | Q77: Map | R77: Record
A78: Fairview Express Care | B78: Injury Physicians | D78: Neurology | E78: 1650 Beam Ave | F78: Ste 200 | G78: Maplewood | H78: Ramsey | I78: Twin Cities Metro | J78: 55109 | K78: (651) 221-9051 | L78: 11 | M78: No | N78: 45701 | O78: Fairview Express Care | P78: 1902311210 | Q78: Map | R78: Record
A79: Pdr Maplewood, INC | B79: Injury Physicians | C79: Chiropractic, Physical Therapy | D79: Physical Medicine & Rehabilitation, Chiropractic, Physical Therapy | E79: 2520 White Bear Ave N | F79: Ste A | G79: Maplewood | H79: Ramsey | I79: Twin Cities Metro | J79: 55109 | K79: (651) 777-6507 | L79: 0 | M79: No | N79: 45911 | O79: Pdr Maplewood, INC | P79: 1356454391 | Q79: Map | R79: Record
A80: Twin Cities Pain Clinic | B80: Injury Physicians | D80: Pain Management, Physical Medicine & Rehabilitation | E80: 1725 Legacy Pkwy E | F80: Ste 100 | G80: Maplewood | H80: Ramsey | I80: Twin Cities Metro | J80: 55109 | K80: (952) 841-2345 | L80: 5 | M80: No | N80: 45020 | O80: Andrew J Will MD PA | P80: 1467157826 | Q80: Map | R80: Record
A81: Entira Family Clinics-North St. Paul | B81: Injury Physicians | D81: Sports Medicine, Physical Medicine & Rehabilitation | E81: 2601 Centennial Dr | F81: Ste 100 | G81: North St Paul | H81: Ramsey | I81: Twin Cities Metro | J81: 55109 | K81: (651) 788-4444 | L81: 0 | M81: No | N81: 45944 | O81: Family Healthservices Minnesota, PA. | P81: 1083894711 | Q81: Map | R81: Record
A82: Minnesota Epilepsy Group PA | B82: Injury Physicians | D82: Neurology | E82: 2720 Fairview Ave N | F82: Ste 100 | G82: Roseville | H82: Ramsey | I82: Twin Cities Metro | J82: 55113 | K82: (651) 241-5290 | L82: 15 | M82: No | N82: 46118 | O82: Minnesota Epilepsy Group PA | P82: 1932118056 | Q82: Map | R82: Record
A83: Minnesota Institute For Pain Management, LLC | B83: Injury Physicians | D83: Pain Management, Physical Medicine & Rehabilitation | E83: 2780 Snelling Ave N | F83: Ste 304 | G83: Roseville | H83: Ramsey | I83: Twin Cities Metro | J83: 55113 | K83: (651) 789-3141 | L83: 1 | M83: No | N83: 45447 | O83: Minnesota Institute For Pain Management, LLC | P83: 1366751562 | Q83: Map | R83: Record
A84: Entira Family Clinics-Shoreview | B84: Injury Physicians | D84: Sports Medicine, Physical Medicine & Rehabilitation | E84: 404 Highway 96 W | G84: Shoreview | H84: Ramsey | I84: Twin Cities Metro | J84: 55126 | K84: (651) 788-4444 | L84: 0 | M84: No | N84: 45944 | O84: Family Healthservices Minnesota, PA. | P84: 1619157344 | Q84: Map | R84: Record
A85: Allina Health Orthopedics | B85: Injury Physicians | D85: Orthopedics, Sports Medicine | E85: 225 Smith Ave N | F85: Ste 200 | G85: St. Paul | H85: Ramsey | I85: Twin Cities Metro | J85: 55102 | K85: (651) 241-8920 | L85: 1 | M85: Yes | N85: 46042 | O85: Allina Health System | P85: 1508099656 | Q85: Map | R85: Record
A86: Allina Health Orthopedics | B86: Injury Physicians | D86: Orthopedics, Sports Medicine | E86: 255 Smith Ave N | F86: Ste 210 | G86: St. Paul | H86: Ramsey | I86: Twin Cities Metro | J86: 55102 | K86: (952) 946-9777 | L86: 0 | M86: Yes | N86: 46042 | O86: Allina Health System | P86: 1508099656 | Q86: Map | R86: Record
A87: Allina Health Orthopedics | B87: Injury Physicians | D87: Orthopedics, Sports Medicine | E87: 310 Smith Ave N | F87: Ste 300 | G87: St. Paul | H87: Ramsey | I87: Twin Cities Metro | J87: 55102 | K87: (952) 946-9888 | L87: 2 | M87: Yes | N87: 46042 | O87: Allina Health System | P87: 1508099656 | Q87: Map | R87: Record
A88: Courage Kenny Rehab Associates | B88: Injury Physicians | D88: Physical Medicine & Rehabilitation | E88: 280 Smith Ave N | F88: Ste 220 | G88: St. Paul | H88: Ramsey | I88: Twin Cities Metro | J88: 55102 | K88: (651) 241-8295 | L88: 8 | M88: Yes | N88: 45714 | O88: Allina Health System | P88: 1962659094 | Q88: Map | R88: Record
A89: Entira Family Clinics-Como/roseville | B89: Injury Physicians | D89: Sports Medicine, Physical Medicine & Rehabilitation | E89: 1050 Larpenteur Ave W | G89: St. Paul | H89: Ramsey | I89: Twin Cities Metro | J89: 55113 | K89: (651) 788-4444 | L89: 0 | M89: No | N89: 45944 | O89: Family Healthservices Minnesota, PA. | P89: 1629258355 | Q89: Map | R89: Record
A90: Entira Family Clinics-East Side | B90: Injury Physicians | D90: Sports Medicine, Physical Medicine & Rehabilitation | E90: 1385 Phalen Blvd | G90: St. Paul | H90: Ramsey | I90: Twin Cities Metro | J90: 55106 | K90: (651) 788-4444 | L90: 0 | M90: No | N90: 45944 | O90: Family Healthservices Minnesota, PA. | P90: 1174703805 | Q90: Map | R90: Record
A91: Entira Family Clinics-Highland | B91: Injury Physicians | D91: Sports Medicine, Physical Medicine & Rehabilitation | E91: 280 Snelling Ave N | G91: St. Paul | H91: Ramsey | I91: Twin Cities Metro | J91: 55104 | K91: (651) 699-8333 | L91: 0 | M91: No | N91: 45944 | O91: Family Healthservices Minnesota, PA. | P91: 1629258348 | Q91: Map | R91: Record
A92: Family Healthservices Minnesota, PA. | B92: Injury Physicians | D92: Sports Medicine, Physical Medicine & Rehabilitation | E92: 2025 Sloan Pl | F92: Ste 35 | G92: St. Paul | H92: Ramsey | I92: Twin Cities Metro | J92: 55117 | K92: (651) 772-1572 | L92: 0 | M92: No | N92: 45944 | O92: Family Healthservices Minnesota, PA. | P92: 1124206677 | Q92: Map | R92: Record
A93: Impact Physical Medicine | B93: Injury Physicians | C93: Physical Therapy | D93: Physical Medicine & Rehabilitation, Physical Therapy | E93: 1600 University Ave W | F93: Ste 10 | G93: St. Paul | H93: Ramsey | I93: Twin Cities Metro | J93: 55104 | K93: (651) 592-9402 | L93: 9 | M93: No | N93: 44925 | O93: Impact Physical Medicine of St. Paul | P93: 1487294401 | Q93: Map | R93: Record
A94: John Nasseff Neuroscience Specialty Clinic | B94: Injury Physicians | D94: Neurosurgery | E94: 310 Smith Ave N | F94: Ste 440 | G94: St. Paul | H94: Ramsey | I94: Twin Cities Metro | J94: 55102 | K94: (651) 241-6555 | L94: 2 | M94: Yes | N94: 45713 | O94: Allina Health System | P94: 1619914207 | Q94: Map | R94: Record
A95: United Hospital - Midwest Spine & Brain Institute | B95: Injury Physicians | D95: Orthopedics, Spine, Neurosurgery, Physical Medicine & Rehabilitation | E95: 280 Smith Ave N | F95: Ste 600 | G95: St. Paul | H95: Ramsey | I95: Twin Cities Metro | J95: 55102 | K95: (651) 430-3827 | L95: 11 | M95: Yes | N95: 45712 | O95: Allina Health System | P95: 1366221491 | Q95: Map | R95: Record
A96: United Pain Center | B96: Injury Physicians | D96: Pain Management | E96: 255 Smith Ave N | F96: Ste 100 | G96: St. Paul | H96: Ramsey | I96: Twin Cities Metro | J96: 55102 | K96: (651) 241-7246 | L96: 3 | M96: Yes | N96: 46055 | O96: Allina Health System | P96: 1962447995 | Q96: Map | R96: Record
A97: Entira Family Clinics-Vadnais Heights | B97: Injury Physicians | D97: Sports Medicine, Physical Medicine & Rehabilitation | E97: 3550 Labore Rd | F97: Ste 7 | G97: Vadnais Heights | H97: Ramsey | I97: Twin Cities Metro | J97: 55110 | K97: (651) 788-4444 | L97: 0 | M97: No | N97: 45944 | O97: Family Healthservices Minnesota, PA. | P97: 1528248259 | Q97: Map | R97: Record
A98: Summit Orthopedics, LTD | B98: Injury Physicians | C98: Physical Therapy | D98: Orthopedics, Physical Therapy | E98: 3580 Arcade St | G98: Vadnais Heights | H98: Ramsey | I98: Twin Cities Metro | J98: 55127 | K98: (651) 968-5201 | L98: 45 | M98: Yes | N98: 45867 | O98: Summit Orthopedics, LTD | P98: 1215358346 | Q98: Map | R98: Record
A99: Fyzical Therapy and Balance Centers | B99: Injury Physicians | D99: Physical Medicine & Rehabilitation | E99: 2680 County Road E E | G99: White Bear Lake | H99: Ramsey | I99: Twin Cities Metro | J99: 55110 | K99: (651) 504-2212 | L99: 0 | M99: No | N99: 45909 | O99: Soleck Ventures INC | P99: 1821979642 | Q99: Map | R99: Record
A100: Summit Orthopedics, LTD | B100: Injury Physicians | D100: Orthopedics | E100: 4360 12th Ave E | G100: Shakopee | H100: Scott | I100: Twin Cities Metro | J100: 55379 | K100: (651) 968-5200 | L100: 0 | M100: No | N100: 45818 | O100: Summit Orthopedics, LTD | P100: 1053955385 | Q100: Map | R100: Record
...

Sheet Chiropractic
A1: Clinic Name | B1: Specialty Group | C1: Also In | D1: Specialties | E1: Street | F1: Suite | G1: City | H1: County | I1: Region | J1: ZIP | K1: Phone | L1: Providers at Address | M1: On Xpert Connect | N1: Registry Updated | O1: Legal Name | P1: NPI | Q1: Map | R1: NPPES Record
A2: Health and Healing Family Chiropractic | B2: Chiropractic | D2: Chiropractic | E2: 1883 Station Pkwy NW | G2: Andover | H2: Anoka | I2: Twin Cities Metro | J2: 55304 | K2: (763) 323-0061 | L2: 1 | M2: No | N2: 45559 | O2: Health and Healing Family Chiropractic | P2: 1366657280 | Q2: Map | R2: Record
A3: 7th Avenue Chiropractic | B3: Chiropractic | D3: Chiropractic | E3: 3722 7th Ave | G3: Anoka | H3: Anoka | I3: Twin Cities Metro | J3: 55303 | K3: (763) 312-1257 | L3: 2 | M3: No | N3: 45659 | O3: 7th Avenue Chiropractic | P3: 1053120220 | Q3: Map | R3: Record
A4: Kuss Chiropractic | B4: Chiropractic | D4: Chiropractic | E4: 440 Bunker Lake Blvd NW | F4: Ste 105 | G4: Anoka | H4: Anoka | I4: Twin Cities Metro | J4: 55303 | K4: (763) 330-0393 | L4: 1 | M4: No | N4: 45778 | O4: Kuss Company LLC | P4: 1821895756 | Q4: Map | R4: Record
A5: Unison Chiropractic Center PLLC | B5: Chiropractic | D5: Chiropractic | E5: 2006 1st Ave | F5: Ste 209 | G5: Anoka | H5: Anoka | I5: Twin Cities Metro | J5: 55303 | K5: (763) 421-0436 | L5: 1 | M5: No | N5: 46001 | O5: Unison Chiropractic Center PLLC | P5: 1538644885 | Q5: Map | R5: Record
A6: Blaine Chiropractic Center PA | B6: Chiropractic | D6: Chiropractic | E6: 11919 Central Ave NE | G6: Blaine | H6: Anoka | I6: Twin Cities Metro | J6: 55434 | K6: (763) 757-1660 | L6: 8 | M6: No | N6: 45384 | O6: Blaine Chiropractic Center PA | P6: 1376759589 | Q6: Map | R6: Record
A7: Club West Chiropractic PA | B7: Chiropractic | C7: Physical Therapy | D7: Chiropractic, Physical Therapy | E7: 10950 Club West Pkwy | F7: Ste 190 | G7: Blaine | H7: Anoka | I7: Twin Cities Metro | J7: 55449 | K7: (763) 400-4940 | L7: 3 | M7: No | N7: 45348 | O7: Club West Chiropractic PA | P7: 1427447432 | Q7: Map | R7: Record
A8: Open Heart Chiropractic PA | B8: Chiropractic | D8: Chiropractic | E8: 12265 Central Ave NE | G8: Blaine | H8: Anoka | I8: Twin Cities Metro | J8: 55434 | K8: (763) 757-8511 | L8: 2 | M8: No | N8: 45153 | O8: Open Heart Chiropractic PA | P8: 1811687015 | Q8: Map | R8: Record
A9: Caring Chiropractic Center, PA. | B9: Chiropractic | D9: Chiropractic | E9: 10811 Xavis St NW | G9: Coon Rapids | H9: Anoka | I9: Twin Cities Metro | J9: 55433 | K9: (763) 421-1905 | L9: 2 | M9: No | N9: 46248 | O9: Caring Chiropractic Center, PA. | P9: 1134494818 | Q9: Map | R9: Record
A10: Fit Family Chiropractic | B10: Chiropractic | D10: Chiropractic | E10: 1835 Gateway Dr | F10: Ste 104 | G10: Coon Rapids | H10: Anoka | I10: Twin Cities Metro | J10: 55448 | K10: (763) 710-8888 | L10: 1 | M10: No | N10: 44663 | O10: Moe Chiro Tres PLLC | P10: 1063054302 | Q10: Map | R10: Record
A11: Pdr Coon Rapids, INC | B11: Injury Physicians | C11: Chiropractic, Physical Therapy | D11: Physical Medicine & Rehabilitation, Chiropractic, Physical Therapy | E11: 320 Coon Rapids Blvd NW | F11: #100 | G11: Coon Rapids | H11: Anoka | I11: Twin Cities Metro | J11: 55433 | K11: (952) 908-2580 | L11: 5 | M11: No | N11: 45911 | O11: Pdr Coon Rapids, INC | P11: 1477666428 | Q11: Map | R11: Record
A12: Restoring Wellness Chiropractic | B12: Chiropractic | D12: Chiropractic | E12: 10811 Xavis St NW | G12: Coon Rapids | H12: Anoka | I12: Twin Cities Metro | J12: 55433 | K12: (763) 285-6475 | L12: 2 | M12: No | N12: 45131 | O12: Restoring Wellness Chiropractic, LLC | P12: 1447934385 | Q12: Map | R12: Record
A13: Rooted In Wellness Chiropractic LLC | B13: Chiropractic | D13: Chiropractic | E13: 20730 Hamlet Ave N | G13: Forest Lake | H13: Anoka | I13: Twin Cities Metro | J13: 55025 | K13: (651) 248-1841 | L13: 0 | M13: No | N13: 45674 | O13: Rooted In Wellness Chiropractic LLC | P13: 1538970660 | Q13: Map | R13: Record
A14: Heim Chiropractic, PA | B14: Chiropractic | D14: Chiropractic | E14: 7101 Highway 65 NE | F14: Ste 4 | G14: Fridley | H14: Anoka | I14: Twin Cities Metro | J14: 55432 | K14: (651) 482-9160 | L14: 1 | M14: No | N14: 46266 | O14: Heim Chiropractic, PA | P14: 1073675047 | Q14: Map | R14: Record
A15: Minnesota Chiroworks, PLLC | B15: Chiropractic | D15: Chiropractic | E15: 7400 University Ave NE | F15: Ste 100 | G15: Fridley | H15: Anoka | I15: Twin Cities Metro | J15: 55432 | K15: (637) 571-0239 | L15: 0 | M15: No | N15: 44981 | O15: Minnesota Chiroworks, PLLC | P15: 1750917068 | Q15: Map | R15: Record
A16: Spinecare Fridley, PC | B16: Chiropractic | D16: Chiropractic | E16: 7872 University Ave NE | G16: Fridley | H16: Anoka | I16: Twin Cities Metro | J16: 55432 | K16: (763) 780-4300 | L16: 3 | M16: No | N16: 44763 | O16: A Plus Chiropractic, PC | P16: 1265953061 | Q16: Map | R16: Record
A17: The Minnesota Chiroworks, PC | B17: Chiropractic | D17: Chiropractic | E17: 7872 University Ave NE | G17: Fridley | H17: Anoka | I17: Twin Cities Metro | J17: 55432 | K17: (763) 780-4300 | L17: 3 | M17: No | N17: 46129 | O17: The Minnesota Chiroworks, PC | P17: 1720874860 | Q17: Map | R17: Record
A18: Exceptional Chiropractic P A | B18: Chiropractic | D18: Chiropractic | E18: 16230 Aberdeen St NE | F18: Ste B | G18: Ham Lake | H18: Anoka | I18: Twin Cities Metro | J18: 55304 | K18: (763) 208-5382 | L18: 2 | M18: No | N18: 45352 | O18: Exceptional Chiropractic P A | P18: 1881795961 | Q18: Map | R18: Record
A19: Exceptional Chiropractic P A | B19: Chiropractic | D19: Chiropractic | E19: 2415 149th Ave NE | G19: Ham Lake | H19: Anoka | I19: Twin Cities Metro | J19: 55304 | K19: (612) 418-3587 | L19: 0 | M19: No | N19: 45352 | O19: Exceptional Chiropractic P A | P19: 1881795961 | Q19: Map | R19: Record
A20: Silver View Chiropractic Center, PA. | B20: Chiropractic | D20: Chiropractic | E20: 4137 Woodland Road | G20: Lexington | H20: Anoka | I20: Twin Cities Metro | J20: 55014 | K20: (763) 786-5581 | L20: 3 | M20: No | N20: 45523 | O20: Silver View Chiropractic Center, PA. | P20: 1740453968 | Q20: Map | R20: Record
A21: Sprout Chiropractic & Wellness | B21: Chiropractic | D21: Chiropractic | E21: 7525 Village Dr | F21: Ste 110 | G21: Lino Lakes | H21: Anoka | I21: Twin Cities Metro | J21: 55014 | K21: (651) 247-0941 | L21: 1 | M21: No | N21: 44760 | O21: Roseville Chiropractic Clinic, LLC | P21: 1699054304 | Q21: Map | R21: Record
A22: Meraki Chiropractic PLLC | B22: Chiropractic | D22: Chiropractic | E22: 19201 Lake George Blvd | F22: Ste C | G22: Oak Grove | H22: Anoka | I22: Twin Cities Metro | J22: 55303 | K22: (763) 200-3370 | L22: 1 | M22: No | N22: 45313 | O22: Meraki Chiropractic PLLC | P22: 1750142360 | Q22: Map | R22: Record
A23: Opp Family Chiropractic PA. | B23: Chiropractic | D23: Chiropractic | E23: 23168 Saint Francis Blvd NW | F23: #600 | G23: St. Francis | H23: Anoka | I23: Twin Cities Metro | J23: 55070 | K23: (763) 213-0615 | L23: 3 | M23: No | N23: 45419 | O23: Opp Family Chiropractic PA. | P23: 1982890810 | Q23: Map | R23: Record
A24: St Lukes Chiropractic | B24: Chiropractic | D24: Chiropractic | E24: 3220 Bridge St NW | F24: Ste 108 | G24: St. Francis | H24: Anoka | I24: Twin Cities Metro | J24: 55070 | K24: (763) 452-0171 | L24: 1 | M24: No | N24: 45260 | O24: St Lukes Chiropractic | P24: 1235715574 | Q24: Map | R24: Record
A25: Backed Chiropractic | B25: Chiropractic | D25: Chiropractic | E25: 1286 Park Rd | F25: # B | G25: Chanhassen | H25: Carver | I25: Twin Cities Metro | J25: 55317 | K25: (952) 451-8571 | L25: 1 | M25: No | N25: 45631 | O25: Backed Chiropractic PLLC | P25: 1720862931 | Q25: Map | R25: Record
A26: Chanhassen Chiropractic | B26: Chiropractic | D26: Chiropractic | E26: 7800 Market Blvd | G26: Chanhassen | H26: Carver | I26: Twin Cities Metro | J26: 55317 | K26: (952) 934-4500 | L26: 2 | M26: No | N26: 45225 | O26: Active Mobility Practitioner PA | P26: 1639528508 | Q26: Map | R26: Record
A27: Discover Chiropractic | B27: Chiropractic | D27: Chiropractic | E27: 1107 Hazeltine Blvd | F27: Ste 100 | G27: Chaska | H27: Carver | I27: Twin Cities Metro | J27: 55318 | K27: (952) 368-4700 | L27: 1 | M27: No | N27: 46246 | O27: Coombs Chiropractic PLLC | P27: 1861317349 | Q27: Map | R27: Record
A28: Lake Life Chiropractic LLC | B28: Chiropractic | D28: Chiropractic | E28: 3650 N Chestnut St | F28: Ste 101A | G28: Chaska | H28: Carver | I28: Twin Cities Metro | J28: 55318 | K28: (612) 562-8384 | L28: 2 | M28: No | N28: 45820 | O28: Lake Life Chiropractic LLC | P28: 1952826778 | Q28: Map | R28: Record
A29: Peak Chiropractic LLC | B29: Chiropractic | D29: Chiropractic | E29: 1107 Hazeltine Blvd | F29: Ste 420 | G29: Chaska | H29: Carver | I29: Twin Cities Metro | J29: 55318 | K29: (952) 600-5584 | L29: 1 | M29: No | N29: 45475 | O29: Peak Chiropractic LLC | P29: 1215773049 | Q29: Map | R29: Record
A30: Sports Performance Chiropractic | B30: Chiropractic | D30: Chiropractic | E30: 350 Highway 7 | F30: Ste 200 | G30: Excelsior | H30: Carver | I30: Twin Cities Metro | J30: 55331 | K30: (952) 529-3905 | L30: 0 | M30: No | N30: 46125 | O30: Sports Performance Chiropractic | P30: 1649113804 | Q30: Map | R30: Record
A31: Power of Life Alternative and Holistic Health | B31: Chiropractic | D31: Chiropractic | E31: 1700 Stieger Lake Ln | F31: Ste 103 | G31: Victoria | H31: Carver | I31: Twin Cities Metro | J31: 55386 | K31: (952) 443-9000 | L31: 1 | M31: No | N31: 45721 | O31: Power of Life Chiropractic, PA. | P31: 1316120272 | Q31: Map | R31: Record
A32: Movewell Chiropractc & Wellness | B32: Chiropractic | D32: Chiropractic | E32: 9360 Oak Ave | G32: Waconia | H32: Carver | I32: Twin Cities Metro | J32: 55387 | K32: (952) 466-6533 | L32: 3 | M32: No | N32: 46230 | O32: Movewell Chiropractc & Wellness | P32: 1972142081 | Q32: Map | R32: Record
A33: Watertown Family Chiropractic | B33: Chiropractic | D33: Chiropractic | E33: 204 Lewis Ave S | F33: Sutie 203 | G33: Watertown | H33: Carver | I33: Twin Cities Metro | J33: 55388 | K33: (515) 320-3841 | L33: 1 | M33: No | N33: 44572 | O33: Ryan Goetz, PA. | P33: 1316185036 | Q33: Map | R33: Record
A34: North Branch Family Chiropractic LLC | B34: Chiropractic | D34: Chiropractic | E34: 6241 Main St | F34: Ste 102 | G34: North Branch | H34: Chisago | I34: Twin Cities Metro | J34: 55056 | K34: (651) 470-5422 | L34: 1 | M34: No | N34: 45751 | O34: North Branch Family Chiropractic LLC | P34: 1437943677 | Q34: Map | R34: Record
A35: Revive Chiropractic | B35: Chiropractic | D35: Chiropractic | E35: 6272 Main St | G35: North Branch | H35: Chisago | I35: Twin Cities Metro | J35: 55056 | K35: (651) 674-2700 | L35: 0 | M35: No | N35: 45090 | O35: Wurdemann Chiropractic PA | P35: 1578850061 | Q35: Map | R35: Record
A36: Weierke Chiropractic PA | B36: Chiropractic | D36: Chiropractic | E36: 386 Bench St | G36: Taylors Falls | H36: Chisago | I36: Twin Cities Metro | J36: 55084 | K36: (651) 465-3811 | L36: 0 | M36: No | N36: 45464 | O36: Weierke Chiropractic PA | P36: 1568876993 | Q36: Map | R36: Record
A37: Apex Family Chiropractic LLC | B37: Chiropractic | D37: Chiropractic | E37: 15678 Pilot Knob Road | F37: Ste 120 | G37: Apple Valley | H37: Dakota | I37: Twin Cities Metro | J37: 55124 | K37: (651) 456-8744 | L37: 1 | M37: No | N37: 44763 | O37: Apex Family Chiropractic LLC | P37: 1982126926 | Q37: Map | R37: Record
A38: Johnson Spinal Care Associates, PA. | B38: Chiropractic | D38: Chiropractic | E38: 14859 Energy Way | G38: Apple Valley | H38: Dakota | I38: Twin Cities Metro | J38: 55124 | K38: (952) 432-3333 | L38: 7 | M38: No | N38: 45005 | O38: Johnson Spinal Care Associates, PA. | P38: 1285711663 | Q38: Map | R38: Record
A39: Lifeway Chiropractic and Wellness LLC | B39: Chiropractic | D39: Chiropractic | E39: 7300 147th St W | F39: Ste 101 | G39: Apple Valley | H39: Dakota | I39: Twin Cities Metro | J39: 55124 | K39: (612) 508-2454 | L39: 6 | M39: No | N39: 45902 | O39: Lifeway Chiropractic and Wellness LLC | P39: 1962568576 | Q39: Map | R39: Record
A40: Bloom Chiropractic Center PA | B40: Chiropractic | D40: Chiropractic | E40: 1606 Cliff Rd E | G40: Burnsville | H40: Dakota | I40: Twin Cities Metro | J40: 55337 | K40: (952) 894-6300 | L40: 1 | M40: No | N40: 44733 | O40: Bloom Chiropractic Center PA | P40: 1417075532 | Q40: Map | R40: Record
A41: Chiroflex PLLC | B41: Chiropractic | D41: Chiropractic | E41: 1103 W Burnsville Pkwy | F41: Ste 120 | G41: Burnsville | H41: Dakota | I41: Twin Cities Metro | J41: 55337 | K41: (320) 699-0695 | L41: 1 | M41: No | N41: 45062 | O41: Chiroflex PLLC | P41: 1114618618 | Q41: Map | R41: Record
A42: Healthpro Chiropractic PC | B42: Chiropractic | D42: Chiropractic | E42: 150 E Travelers Trl | F42: Ste B | G42: Burnsville | H42: Dakota | I42: Twin Cities Metro | J42: 55337 | K42: (651) 463-8222 | L42: 3 | M42: No | N42: 45820 | O42: Healthpro Chiropractic PC | P42: 1730320276 | Q42: Map | R42: Record
A43: Heartlight Chiropractic, PA. | B43: Chiropractic | D43: Chiropractic | E43: 2960 Judicial Rd | F43: Ste 210 | G43: Burnsville | H43: Dakota | I43: Twin Cities Metro | J43: 55337 | K43: (952) 890-5694 | L43: 1 | M43: No | N43: 46022 | O43: Heartlight Chiropractic, PA. | P43: 1912184573 | Q43: Map | R43: Record
A44: Heartlight Chiropractic, PA. | B44: Chiropractic | D44: Chiropractic | E44: 13955 W Preserve Blvd | F44: Ste 200 | G44: Burnsville | H44: Dakota | I44: Twin Cities Metro | J44: 55337 | K44: (952) 890-5694 | L44: 9 | M44: No | N44: 46022 | O44: Heartlight Chiropractic, PA. | P44: 1912184573 | Q44: Map | R44: Record
A45: Institute For Orthopedics & Chiropractic, PLLC | B45: Chiropractic | C45: Physical Therapy | D45: Chiropractic, Physical Therapy | E45: 14300 Buck Hill Rd | F45: Ste E | G45: Burnsville | H45: Dakota | I45: Twin Cities Metro | J45: 55306 | K45: (952) 941-3311 | L45: 4 | M45: No | N45: 46161 | O45: Institute For Orthopedics & Chiropractic, PLLC | P45: 1710216858 | Q45: Map | R45: Record
A46: Integrate Chiropractic PLLC | B46: Chiropractic | D46: Chiropractic | E46: 1103 W Burnsville Pkwy | F46: Ste 120 | G46: Burnsville | H46: Dakota | I46: Twin Cities Metro | J46: 55337 | K46: (952) 300-1461 | L46: 1 | M46: No | N46: 45706 | O46: Integrate Chiropractic PLLC | P46: 1295366888 | Q46: Map | R46: Record
A47: Integrative Orthopedic Clinics, PLLC | B47: Physical Therapy | C47: Chiropractic | D47: Chiropractic, Physical Therapy | E47: 14300 Buck Hill Rd | F47: Ste E | G47: Burnsville | H47: Dakota | I47: Twin Cities Metro | J47: 55306 | K47: (952) 941-3311 | L47: 4 | M47: No | N47: 46148 | O47: Integrative Orthopedic Clinics, PLLC | P47: 1558208033 | Q47: Map | R47: Record
A48: Limitless, PLLC | B48: Chiropractic | D48: Chiropractic | E48: 14612 Burnell Park Dr | G48: Burnsville | H48: Dakota | I48: Twin Cities Metro | J48: 55306 | K48: (952) 314-8449 | L48: 0 | M48: No | N48: 45813 | O48: Limitless, PLLC | P48: 1750871372 | Q48: Map | R48: Record
A49: Nova Chiropractic and Wellness | B49: Chiropractic | D49: Chiropractic | E49: 2424 E 117th St | G49: Burnsville | H49: Dakota | I49: Twin Cities Metro | J49: 55337 | K49: (952) 894-5108 | L49: 8 | M49: No | N49: 44796 | O49: Nova Chiropractic and Wellness | P49: 1871212951 | Q49: Map | R49: Record
A50: Pdr Burnsville, INC | B50: Injury Physicians | C50: Chiropractic, Physical Therapy | D50: Physical Medicine & Rehabilitation, Chiropractic, Physical Therapy | E50: 14050 Nicollet Ave | F50: #114 | G50: Burnsville | H50: Dakota | I50: Twin Cities Metro | J50: 55337 | K50: (952) 908-2710 | L50: 1 | M50: No | N50: 45911 | O50: Pdr Burnsville, INC | P50: 1952414971 | Q50: Map | R50: Record
A51: Peak Performance Chiropractic Center | B51: Chiropractic | D51: Chiropractic | E51: 12750 Nicollet Ave | F51: Ste 303 | G51: Burnsville | H51: Dakota | I51: Twin Cities Metro | J51: 55337 | K51: (507) 476-7345 | L51: 1 | M51: No | N51: 45754 | O51: Peak Performance Chiropractic Center | P51: 1144031675 | Q51: Map | R51: Record
A52: Resurgence Chiropractic Clinic LLC | B52: Chiropractic | D52: Chiropractic | E52: 1602 Cliff Rd E | G52: Burnsville | H52: Dakota | I52: Twin Cities Metro | J52: 55337 | K52: (612) 710-7756 | L52: 1 | M52: No | N52: 45848 | O52: Resurgence Chiropractic Clinic LLC | P52: 1124919071 | Q52: Map | R52: Record
A53: Revibe Chiropractic and Rehabilitation | B53: Chiropractic | D53: Chiropractic | E53: 14300 Buck Hill Rd | F53: Ste E | G53: Burnsville | H53: Dakota | I53: Twin Cities Metro | J53: 55306 | K53: (952) 866-9010 | L53: 3 | M53: No | N53: 46251 | O53: Wyn Chiropractic & Rehabilitation PLLC | P53: 1053253781 | Q53: Map | R53: Record
A54: Thrive Chiropractic & Health LLC | B54: Chiropractic | D54: Chiropractic | E54: 511 County Road 42 E | G54: Burnsville | H54: Dakota | I54: Twin Cities Metro | J54: 55306 | K54: (612) 720-7436 | L54: 2 | M54: No | N54: 44726 | O54: Thrive Chiropractic & Health LLC | P54: 1457081275 | Q54: Map | R54: Record
A55: Vector Sport and Spine : Chiro & Rehab PLLC | B55: Chiropractic | D55: Chiropractic | E55: 12919 Oliver Ave S | G55: Burnsville | H55: Dakota | I55: Twin Cities Metro | J55: 55337 | K55: (952) 222-5770 | L55: 1 | M55: No | N55: 44578 | O55: Vector Sport and Spine : Chiro & Rehab PLLC | P55: 1447901996 | Q55: Map | R55: Record
A56: A.m. Family Chiropractic and Nutrition PLLC. | B56: Chiropractic | D56: Chiropractic | E56: 1121 Town Centre Dr | F56: Ste 105 | G56: Eagan | H56: Dakota | I56: Twin Cities Metro | J56: 55123 | K56: (651) 500-8897 | L56: 1 | M56: No | N56: 46191 | O56: A.m. Family Chiropractic and Nutrition PLLC. | P56: 1912833070 | Q56: Map | R56: Record
A57: Chris Johnson DC | B57: Chiropractic | D57: Chiropractic | E57: 2119 Cliff Rd | G57: Eagan | H57: Dakota | I57: Twin Cities Metro | J57: 55122 | K57: (612) 251-8173 | L57: 2 | M57: No | N57: 45719 | O57: Chris Johnson DC LLC | P57: 1962215087 | Q57: Map | R57: Record
A58: Cornerstone Family Chiropractic, PLLC | B58: Chiropractic | D58: Chiropractic | E58: 1590 Thomas Center Dr | F58: Ste 110 | G58: Eagan | H58: Dakota | I58: Twin Cities Metro | J58: 55122 | K58: (651) 209-9710 | L58: 3 | M58: No | N58: 45105 | O58: Cornerstone Family Chiropractic, PLLC | P58: 1487848719 | Q58: Map | R58: Record
A59: Genesis Chiropractic Health Center | B59: Chiropractic | D59: Chiropractic | E59: 4678 Slater Rd | G59: Eagan | H59: Dakota | I59: Twin Cities Metro | J59: 55122 | K59: (651) 905-0330 | L59: 1 | M59: No | N59: 45000 | O59: Genesis Chiropractic Health Center | P59: 1831411727 | Q59: Map | R59: Record
A60: Synapse | B60: Chiropractic | D60: Chiropractic | E60: 4490 Erin Dr | G60: Eagan | H60: Dakota | I60: Twin Cities Metro | J60: 55122 | K60: (651) 209-9906 | L60: 3 | M60: No | N60: 45412 | O60: Center For Health & Healing INC | P60: 1285761825 | Q60: Map | R60: Record
A61: Healthpro Chiropractic PC | B61: Chiropractic | D61: Chiropractic | E61: 19685 Pilot Knob Rd | F61: Ste 260 | G61: Farmington | H61: Dakota | I61: Twin Cities Metro | J61: 55024 | K61: (651) 463-8222 | L61: 4 | M61: No | N61: 45820 | O61: Healthpro Chiropractic PC | P61: 1730320276 | Q61: Map | R61: Record
A62: Hastings Sport and Spine LLC | B62: Chiropractic | D62: Chiropractic | E62: 1806 Vermillion St | F62: Ste A | G62: Hastings | H62: Dakota | I62: Twin Cities Metro | J62: 55033 | K62: (563) 449-6651 | L62: 1 | M62: No | N62: 45691 | O62: Hastings Sport and Spine LLC | P62: 1336505551 | Q62: Map | R62: Record
A63: Optimal Health Chiropractic | B63: Chiropractic | D63: Chiropractic | E63: 1260 S Frontage Rd. | F63: Ste B | G63: Hastings | H63: Dakota | I63: Twin Cities Metro | J63: 55033 | K63: (651) 243-0633 | L63: 1 | M63: No | N63: 44796 | O63: Optimal Health Chiropractic, PC. | P63: 1194453365 | Q63: Map | R63: Record
A64: Power Within Chiropractic PA | B64: Chiropractic | D64: Chiropractic | E64: 925 Highway 55 | F64: Ste 103 | G64: Hastings | H64: Dakota | I64: Twin Cities Metro | J64: 55033 | K64: (651) 437-6778 | L64: 1 | M64: No | N64: 45924 | O64: Power Within Chiropractic PA | P64: 1467517953 | Q64: Map | R64: Record
A65: Inver Grove Chiropractic P A | B65: Chiropractic | C65: Physical Therapy | D65: Chiropractic, Physical Therapy | E65: 2940 65th St E | G65: Inver Grove Heights | H65: Dakota | I65: Twin Cities Metro | J65: 55076 | K65: (651) 451-1012 | L65: 3 | M65: No | N65: 45622 | O65: Inver Grove Chiropractic P A | P65: 1194904417 | Q65: Map | R65: Record
A66: Limitless Chiropractic LLC | B66: Chiropractic | D66: Chiropractic | E66: 9086 Buchanan Trl | G66: Inver Grove Heights | H66: Dakota | I66: Twin Cities Metro | J66: 55076 | K66: (651) 300-4500 | L66: 0 | M66: No | N66: 45572 | O66: Limitless Chiropractic LLC | P66: 1679392781 | Q66: Map | R66: Record
A67: Optimum Health | B67: Chiropractic | D67: Chiropractic | E67: 7781 Amana Trl | F67: Ste 300 | G67: Inver Grove Heights | H67: Dakota | I67: Twin Cities Metro | J67: 55077 | K67: (651) 237-3799 | L67: 2 | M67: No | N67: 45692 | O67: Optimum Health PLLC | P67: 1578375630 | Q67: Map | R67: Record
A68: Oyespa LLC | B68: Chiropractic | D68: Chiropractic | E68: 7741 Amana Trl | G68: Inver Grove Heights | H68: Dakota | I68: Twin Cities Metro | J68: 55077 | K68: (651) 371-9100 | L68: 1 | M68: No | N68: 45415 | O68: Starnovus LLC | P68: 1639926942 | Q68: Map | R68: Record
A69: Twin Cities Movement Chiropractic and Rehabilitation PLLC | B69: Chiropractic | D69: Chiropractic | E69: 5844 Blaine Ave | G69: Inver Grove Heights | H69: Dakota | I69: Twin Cities Metro | J69: 55076 | K69: (651) 867-2937 | L69: 0 | M69: No | N69: 46133 | O69: Twin Cities Movement Chiropractic and Rehabilitation PLLC | P69: 1881534220 | Q69: Map | R69: Record
A70: Zero Distance Acupuncture LLC | B70: Chiropractic | D70: Chiropractic | E70: 5810 Blackshire Path | G70: Inver Grove Heights | H70: Dakota | I70: Twin Cities Metro | J70: 55076 | K70: (612) 261-7300 | L70: 1 | M70: No | N70: 46053 | O70: Zero Distance Acupuncture LLC | P70: 1194496471 | Q70: Map | R70: Record
A71: Align Chiropractic PA | B71: Chiropractic | D71: Chiropractic | E71: 16301 Kenrick Ave | G71: Lakeville | H71: Dakota | I71: Twin Cities Metro | J71: 55044 | K71: (952) 594-3137 | L71: 3 | M71: No | N71: 44763 | O71: Align Chiropractic PA | P71: 1679098172 | Q71: Map | R71: Record
A72: Alpha Spine Health & Injury Center | B72: Chiropractic | D72: Chiropractic | E72: 7644 160th St. West | G72: Lakeville | H72: Dakota | I72: Twin Cities Metro | J72: 55044 | K72: (952) 985-5444 | L72: 2 | M72: No | N72: 44699 | O72: Betzina Clinics , LLC | P72: 1205083540 | Q72: Map | R72: Record
A73: Lakeville Integrated Health Clinic INC. | B73: Chiropractic | D73: Chiropractic | E73: 16283 Ipava Ave | G73: Lakeville | H73: Dakota | I73: Twin Cities Metro | J73: 55044 | K73: (952) 898-2287 | L73: 8 | M73: No | N73: 45257 | O73: Lakeville Integrated Health Clinic INC. | P73: 1639710957 | Q73: Map | R73: Record
A74: Lakeville Spine & Health | B74: Chiropractic | D74: Chiropractic | E74: 20176 Heritage Dr | G74: Lakeville | H74: Dakota | I74: Twin Cities Metro | J74: 55044 | K74: (952) 985-8808 | L74: 5 | M74: No | N74: 44719 | O74: Carder Chiropractic and Health PLLC | P74: 1043873821 | Q74: Map | R74: Record
A75: Midwest Integrated Health Clinic | B75: Chiropractic | D75: Chiropractic | E75: 16283 Ipava Ave | G75: Lakeville | H75: Dakota | I75: Twin Cities Metro | J75: 55044 | K75: (952) 898-2287 | L75: 8 | M75: No | N75: 45905 | O75: The Chiropractic Clinic PLLC | P75: 1669281341 | Q75: Map | R75: Record
A76: New Life Chiropractic | B76: Chiropractic | D76: Chiropractic | E76: 17595 Kenwood Trl | F76: Ste 120 | G76: Lakeville | H76: Dakota | I76: Twin Cities Metro | J76: 55044 | K76: (651) 401-6494 | L76: 3 | M76: No | N76: 45280 | O76: New Life Chiropractic LLC | P76: 1306555719 | Q76: Map | R76: Record
A77: Rozmarin Family Chiropractic, P. A. | B77: Chiropractic | D77: Chiropractic | E77: 18476 Kenrick Ave | F77: Ste 201 | G77: Lakeville | H77: Dakota | I77: Twin Cities Metro | J77: 55044 | K77: (952) 220-9554 | L77: 4 | M77: No | N77: 44635 | O77: Rozmarin Family Chiropractic, P. A. | P77: 1215197397 | Q77: Map | R77: Record
A78: Turning Leaf Chiropractic, PA. | B78: Chiropractic | D78: Chiropractic | E78: 10438 185th St W | F78: Ste 200 | G78: Lakeville | H78: Dakota | I78: Twin Cities Metro | J78: 55044 | K78: (952) 898-0525 | L78: 5 | M78: No | N78: 45602 | O78: Turning Leaf Chiropractic, PA. | P78: 1528110376 | Q78: Map | R78: Record
A79: Inspire Life Chiropractic Center, PLLC | B79: Chiropractic | D79: Chiropractic | E79: 750 Main St | F79: Ste 108 | G79: Mendota Heights | H79: Dakota | I79: Twin Cities Metro | J79: 55118 | K79: (651) 756-1218 | L79: 1 | M79: No | N79: 44763 | O79: Inspire Life Chiropractic Center, PLLC | P79: 1598293201 | Q79: Map | R79: Record
A80: Lifestyle Chiropractic and Wellness, PA | B80: Chiropractic | D80: Chiropractic | E80: 750 S Plaza Dr | F80: Ste 104 | G80: Mendota Heights | H80: Dakota | I80: Twin Cities Metro | J80: 55120 | K80: (612) 710-8798 | L80: 3 | M80: No | N80: 45986 | O80: Lifestyle Chiropractic and Wellness, PA | P80: 1376104901 | Q80: Map | R80: Record
A81: Healthpro Chiropractic PC | B81: Chiropractic | D81: Chiropractic | E81: 2930 146th St W | F81: Ste 110 | G81: Rosemount | H81: Dakota | I81: Twin Cities Metro | J81: 55068 | K81: (651) 463-8222 | L81: 4 | M81: No | N81: 45820 | O81: Healthpro Chiropractic PC | P81: 1730320276 | Q81: Map | R81: Record
A82: Nielson Family Chiropractic PLLC | B82: Chiropractic | C82: Physical Therapy | D82: Chiropractic, Physical Therapy | E82: 14450 S Robert Trl | F82: Ste 208 | G82: Rosemount | H82: Dakota | I82: Twin Cities Metro | J82: 55068 | K82: (651) 423-2251 | L82: 5 | M82: No | N82: 46198 | O82: Nielson Family Chiropractic PLLC | P82: 1467736231 | Q82: Map | R82: Record
A83: Restore-U Chiropractic | B83: Chiropractic | D83: Chiropractic | E83: 200 Thompson Ave E | G83: West St Paul | H83: Dakota | I83: Twin Cities Metro | J83: 55118 | K83: (651) 451-6839 | L83: 1 | M83: No | N83: 45140 | O83: Allen Rydberg PA. | P83: 1164724332 | Q83: Map | R83: Record
A84: Bloomington Wellness Center, PA | B84: Chiropractic | D84: Chiropractic | E84: 5143 W 98th St | G84: Bloomington | H84: Hennepin | I84: Twin Cities Metro | J84: 55437 | K84: (952) 881-2800 | L84: 10 | M84: No | N84: 46000 | O84: Bloomington Wellness Center, PA | P84: 1225175755 | Q84: Map | R84: Record
A85: Cdm, PLLC | B85: Chiropractic | D85: Chiropractic | E85: 8120 Penn Ave S | F85: Ste 580A | G85: Bloomington | H85: Hennepin | I85: Twin Cities Metro | J85: 55431 | K85: (952) 213-4008 | L85: 5 | M85: No | N85: 46106 | O85: Cdm, PLLC | P85: 1871432906 | Q85: Map | R85: Record
A86: Dr. Cassie Mcguire, Holistic Chiropractic & Wellness | B86: Chiropractic | D86: Chiropractic | E86: 8120 Penn Ave S | F86: Ste 580A | G86: Bloomington | H86: Hennepin | I86: Twin Cities Metro | J86: 55431 | K86: (952) 213-4008 | L86: 5 | M86: No | N86: 46181 | O86: Cdm, PLLC | P86: 1669333902 | Q86: Map | R86: Record
A87: Elysium Chiropractic PLLC | B87: Chiropractic | D87: Chiropractic | E87: 10800 Lyndale Ave S | F87: Ste 151 | G87: Bloomington | H87: Hennepin | I87: Twin Cities Metro | J87: 55420 | K87: (715) 212-7148 | L87: 0 | M87: No | N87: 46133 | O87: Elysium Chiropractic PLLC | P87: 1003751603 | Q87: Map | R87: Record
A88: Freitag Family Chiropractic | B88: Chiropractic | D88: Chiropractic | E88: 140 W 98th St | F88: Ste 111 | G88: Bloomington | H88: Hennepin | I88: Twin Cities Metro | J88: 55420 | K88: (952) 818-2485 | L88: 0 | M88: No | N88: 44851 | O88: Freitag Family Chiropractic LLC | P88: 1427633080 | Q88: Map | R88: Record
A89: Good Bones Chiropractic | B89: Chiropractic | D89: Chiropractic | E89: 8500 Normandale, | F89: Ste 350, Ste 350 | G89: Bloomington | H89: Hennepin | I89: Twin Cities Metro | J89: 55429 | K89: (818) 510-5150 | L89: 0 | M89: No | N89: 45587 | O89: Good Bones Chiropractic | P89: 1144041294 | Q89: Map | R89: Record
A90: Jbc Services PLLC | B90: Chiropractic | D90: Chiropractic | E90: 1700 Haeg Dr | G90: Bloomington | H90: Hennepin | I90: Twin Cities Metro | J90: 55431 | K90: (712) 298-0776 | L90: 0 | M90: No | N90: 46188 | O90: Jbc Services PLLC | P90: 1093640906 | Q90: Map | R90: Record
A91: Planet Gratitude Chiropractic | B91: Chiropractic | D91: Chiropractic | E91: 220 W 98th St | F91: Ste 7 | G91: Bloomington | H91: Hennepin | I91: Twin Cities Metro | J91: 55420 | K91: (952) 922-1478 | L91: 1 | M91: No | N91: 45574 | O91: Golden Sun Chiropractic Wellness Center, PLLC | P91: 1982744140 | Q91: Map | R91: Record
A92: Resonance Chiropractic and Hoistic Health PLLC | B92: Chiropractic | D92: Chiropractic | E92: 215 E 78th St | F92: Ste 300 | G92: Bloomington | H92: Hennepin | I92: Twin Cities Metro | J92: 55420 | K92: (763) 614-0953 | L92: 0 | M92: No | N92: 45573 | O92: Resonance Chiropractic and Hoistic Health PLLC | P92: 1952120800 | Q92: Map | R92: Record
A93: Wellness Centers, PLLC | B93: Chiropractic | D93: Chiropractic | E93: 11133 France Ave S | G93: Bloomington | H93: Hennepin | I93: Twin Cities Metro | J93: 55431 | K93: (612) 545-7099 | L93: 1 | M93: No | N93: 44763 | O93: Wellness Centers, PLLC | P93: 1902327547 | Q93: Map | R93: Record
A94: Dettling Chiropractic Rehab and Performance PLLC | B94: Chiropractic | D94: Chiropractic | E94: 615 66th Ave N | G94: Brooklyn Center | H94: Hennepin | I94: Twin Cities Metro | J94: 55430 | K94: (763) 560-8980 | L94: 1 | M94: No | N94: 45831 | O94: Dettling Chiropractic Rehab and Performance PLLC | P94: 1083081418 | Q94: Map | R94: Record
A95: Family Chiropractic Health Service | B95: Chiropractic | D95: Chiropractic | E95: 8465 W Broadway Ave | G95: Brooklyn Park | H95: Hennepin | I95: Twin Cities Metro | J95: 55445 | K95: (763) 424-7750 | L95: 2 | M95: No | N95: 44573 | O95: Jo G Theisen DC, PA | P95: 1952484602 | Q95: Map | R95: Record
A96: Park East Chiropractic, PC | B96: Chiropractic | D96: Chiropractic | E96: 4632 85th Ave N | G96: Brooklyn Park | H96: Hennepin | I96: Twin Cities Metro | J96: 55443 | K96: (763) 494-4900 | L96: 2 | M96: No | N96: 44763 | O96: Park East Chiropractic, PC | P96: 1285154542 | Q96: Map | R96: Record
A97: Rooted Wellness Chiropractic, PLLC | B97: Chiropractic | D97: Chiropractic | E97: 8465 W Broadway Ave | G97: Brooklyn Park | H97: Hennepin | I97: Twin Cities Metro | J97: 55445 | K97: (763) 424-7750 | L97: 2 | M97: No | N97: 45848 | O97: Rooted Wellness Chiropractic, PLLC | P97: 1588555494 | Q97: Map | R97: Record
A98: Tozer Chiropractic PA | B98: Chiropractic | D98: Chiropractic | E98: 8500 Edinbrook Pkwy | F98: Ste F | G98: Brooklyn Park | H98: Hennepin | I98: Twin Cities Metro | J98: 55443 | K98: (763) 493-8449 | L98: 1 | M98: No | N98: 45883 | O98: Tozer Chiropractic PA | P98: 1912147281 | Q98: Map | R98: Record
A99: Exceptional Chiropractic P A | B99: Chiropractic | D99: Chiropractic | E99: 11660 Theatre Dr N | F99: Ste 115 | G99: Champlin | H99: Hennepin | I99: Twin Cities Metro | J99: 55316 | K99: (763) 208-5382 | L99: 0 | M99: No | N99: 45352 | O99: Exceptional Chiropractic P A | P99: 1881795961 | Q99: Map | R99: Record
A100: Summit Chiropractic, INC | B100: Chiropractic | D100: Chiropractic | E100: 11030 Douglas Dr N | G100: Champlin | H100: Hennepin | I100: Twin Cities Metro | J100: 55316 | K100: (763) 571-2115 | L100: 2 | M100: No | N100: 45573 | O100: Summit Chiropractic, INC | P100: 1326273798 | Q100: Map | R100: Record
...

Sheet Physical Therapy
A1: Clinic Name | B1: Specialty Group | C1: Also In | D1: Specialties | E1: Street | F1: Suite | G1: City | H1: County | I1: Region | J1: ZIP | K1: Phone | L1: Providers at Address | M1: On Xpert Connect | N1: Registry Updated | O1: Legal Name | P1: NPI | Q1: Map | R1: NPPES Record
A2: Moore Therapies, PLLC | B2: Physical Therapy | D2: Physical Therapy | E2: 16817 Zion St NW | G2: Andover | H2: Anoka | I2: Twin Cities Metro | J2: 55304 | K2: (651) 955-3327 | L2: 0 | M2: No | N2: 45408 | O2: Moore Therapies, PLLC | P2: 1225884661 | Q2: Map | R2: Record
A3: Club West Chiropractic PA | B3: Chiropractic | C3: Physical Therapy | D3: Chiropractic, Physical Therapy | E3: 10950 Club West Pkwy | F3: Ste 190 | G3: Blaine | H3: Anoka | I3: Twin Cities Metro | J3: 55449 | K3: (763) 400-4940 | L3: 3 | M3: No | N3: 45348 | O3: Club West Chiropractic PA | P3: 1427447432 | Q3: Map | R3: Record
A4: Concentra Medical Center | B4: Physical Therapy | D4: Physical Therapy | E4: 10190 Baltimore St NE | F4: Ste 100 | G4: Blaine | H4: Anoka | I4: Twin Cities Metro | J4: 55449 | K4: (763) 780-8264 | L4: 0 | M4: No | N4: 45827 | O4: Occupational Health Centers of Minnesota PC | P4: 1508347964 | Q4: Map | R4: Record
A5: Novacare Rehabilitation | B5: Physical Therapy | D5: Physical Therapy | E5: 11855 Ulysses St NE | F5: Ste 20 | G5: Blaine | H5: Anoka | I5: Twin Cities Metro | J5: 55434 | K5: (763) 767-3140 | L5: 10 | M5: No | N5: 45589 | O5: Novacare Outpatient Rehabilitation East, INC. | P5: 1235950957 | Q5: Map | R5: Record
A6: Concentra Medical Center | B6: Physical Therapy | D6: Physical Therapy | E6: 600 Coon Rapids Blvd NW | F6: Ste 2 | G6: Coon Rapids | H6: Anoka | I6: Twin Cities Metro | J6: 55433 | K6: (651) 968-5273 | L6: 1 | M6: No | N6: 46211 | O6: Occupational Health Centers of Minnesota PC | P6: 1326966300 | Q6: Map | R6: Record
A7: Mary T Outpatient | B7: Physical Therapy | D7: Physical Therapy | E7: 11800 Xeon Blvd NW | G7: Coon Rapids | H7: Anoka | I7: Twin Cities Metro | J7: 55448 | K7: (763) 489-3638 | L7: 4 | M7: No | N7: 44736 | O7: Mary T Outpatient | P7: 1396475927 | Q7: Map | R7: Record
A8: Novacare Rehabilitation | B8: Physical Therapy | D8: Physical Therapy | E8: 2104 Northdale Blvd NW | F8: Ste 100 | G8: Coon Rapids | H8: Anoka | I8: Twin Cities Metro | J8: 55433 | K8: (763) 755-5495 | L8: 18 | M8: No | N8: 45593 | O8: Novacare Outpatient Rehabilitation East, INC. | P8: 1386466886 | Q8: Map | R8: Record
A9: Novacare Rehabilitation | B9: Physical Therapy | D9: Physical Therapy | E9: 10091 Dogwood St NW | G9: Coon Rapids | H9: Anoka | I9: Twin Cities Metro | J9: 55448 | K9: (763) 450-0298 | L9: 4 | M9: No | N9: 45926 | O9: Novacare Outpatient Rehabilitation East, INC. | P9: 1982246013 | Q9: Map | R9: Record
A10: Pdr Coon Rapids, INC | B10: Injury Physicians | C10: Chiropractic, Physical Therapy | D10: Physical Medicine & Rehabilitation, Chiropractic, Physical Therapy | E10: 320 Coon Rapids Blvd NW | F10: #100 | G10: Coon Rapids | H10: Anoka | I10: Twin Cities Metro | J10: 55433 | K10: (952) 908-2580 | L10: 5 | M10: No | N10: 45911 | O10: Pdr Coon Rapids, INC | P10: 1477666428 | Q10: Map | R10: Record
A11: Summit Orthopedics, LTD. | B11: Physical Therapy | D11: Physical Therapy | E11: 600 Coon Rapids Blvd NW | F11: Ste 150 | G11: Coon Rapids | H11: Anoka | I11: Twin Cities Metro | J11: 55433 | K11: (651) 968-5201 | L11: 1 | M11: No | N11: 45391 | O11: Summit Orthopedics, LTD. | P11: 1770207193 | Q11: Map | R11: Record
A12: Therapy Partners INC | B12: Physical Therapy | D12: Physical Therapy | E12: 11800 Xeon Blvd NW | G12: Coon Rapids | H12: Anoka | I12: Twin Cities Metro | J12: 55448 | K12: (763) 489-3638 | L12: 4 | M12: No | N12: 45370 | O12: Therapy Partners INC | P12: 1306606397 | Q12: Map | R12: Record
A13: Therapy Partners, INC. | B13: Physical Therapy | D13: Physical Therapy | E13: 8770 Springbrook Dr NW | F13: Ste 100 | G13: Coon Rapids | H13: Anoka | I13: Twin Cities Metro | J13: 55433 | K13: (763) 231-1824 | L13: 6 | M13: No | N13: 46275 | O13: Therapy Partners, INC. | P13: 1407809494 | Q13: Map | R13: Record
A14: Novacare Rehabilitation | B14: Physical Therapy | D14: Physical Therapy | E14: 480 Osborne Road | F14: Number 280 | G14: Fridley | H14: Anoka | I14: Twin Cities Metro | J14: 55432 | K14: (763) 784-3155 | L14: 0 | M14: No | N14: 45951 | O14: Novacare Outpatient Rehabilitation East INC | P14: 1558610519 | Q14: Map | R14: Record
A15: Novacare Rehabilitation | B15: Physical Therapy | D15: Physical Therapy | E15: 480 Osborne Rd NE | F15: Ste 280 | G15: Fridley | H15: Anoka | I15: Twin Cities Metro | J15: 55432 | K15: (763) 784-3155 | L15: 3 | M15: No | N15: 45589 | O15: Novacare Outpatient Rehabilitation East, INC. | P15: 1356162051 | Q15: Map | R15: Record
A16: Hands Hooves and Hearts Therapeutic Services LLC | B16: Physical Therapy | D16: Physical Therapy | E16: 9457 Highway 10 NW | G16: Ramsey | H16: Anoka | I16: Twin Cities Metro | J16: 55303 | K16: (612) 230-0308 | L16: 0 | M16: No | N16: 46107 | O16: Hands Hooves and Hearts Therapeutic Services LLC | P16: 1891332599 | Q16: Map | R16: Record
A17: Kandor Physical Therapy & Pelvic Health LLC | B17: Physical Therapy | D17: Physical Therapy | E17: 8951 Crossroads Blvd | F17: Ste 213 | G17: Chanhassen | H17: Carver | I17: Twin Cities Metro | J17: 55317 | K17: (952) 395-7461 | L17: 0 | M17: No | N17: 46037 | O17: Kandor Physical Therapy & Pelvic Health LLC | P17: 1114885357 | Q17: Map | R17: Record
A18: Therapy Partners, INC. | B18: Physical Therapy | D18: Physical Therapy | E18: 600 Market St | F18: Ste 150 | G18: Chanhassen | H18: Carver | I18: Twin Cities Metro | J18: 55317 | K18: (952) 491-4700 | L18: 8 | M18: No | N18: 46275 | O18: Therapy Partners, INC. | P18: 1407809494 | Q18: Map | R18: Record
A19: Concentra Medical Center | B19: Physical Therapy | D19: Physical Therapy | E19: 1580 White Oak Dr | F19: Ste 100 | G19: Chaska | H19: Carver | I19: Twin Cities Metro | J19: 55318 | K19: (952) 544-8800 | L19: 2 | M19: No | N19: 45827 | O19: Occupational Health Centers of Minnesota PC | P19: 1790266153 | Q19: Map | R19: Record
A20: Inmind Health, LLC | B20: Physical Therapy | D20: Physical Therapy | E20: 1107 Hazeltine Blvd | F20: Ste 496, MD 45 | G20: Chaska | H20: Carver | I20: Twin Cities Metro | J20: 55318 | K20: (952) 240-3344 | L20: 0 | M20: No | N20: 46177 | O20: Inmind Health, LLC | P20: 1912782749 | Q20: Map | R20: Record
A21: Sunnydays Therapy INC | B21: Physical Therapy | D21: Physical Therapy | E21: 9346 Oak Ave | G21: Waconia | H21: Carver | I21: Twin Cities Metro | J21: 55387 | K21: (952) 223-2506 | L21: 3 | M21: No | N21: 45379 | O21: Sunnydays Therapy INC | P21: 1891914412 | Q21: Map | R21: Record
A22: Children's Therapy Center, INC | B22: Physical Therapy | D22: Physical Therapy | E22: 14635 Pennock Ave | F22: Ste 300 | G22: Apple Valley | H22: Dakota | I22: Twin Cities Metro | J22: 55124 | K22: (651) 994-9644 | L22: 8 | M22: No | N22: 46141 | O22: Children's Therapy Center, INC | P22: 1295809366 | Q22: Map | R22: Record
A23: Liberty Physical Therapy LLC | B23: Physical Therapy | D23: Physical Therapy | E23: 272 Cimarron Rd | G23: Apple Valley | H23: Dakota | I23: Twin Cities Metro | J23: 55124 | K23: (715) 495-6918 | L23: 0 | M23: No | N23: 44797 | O23: Liberty Physical Therapy LLC | P23: 1497474274 | Q23: Map | R23: Record
A24: Niko Physical Therapy LLC | B24: Physical Therapy | D24: Physical Therapy | E24: 7300 147th St W | F24: Ste 403 | G24: Apple Valley | H24: Dakota | I24: Twin Cities Metro | J24: 55124 | K24: (952) 214-8724 | L24: 1 | M24: No | N24: 46031 | O24: Niko Physical Therapy LLC | P24: 1770440810 | Q24: Map | R24: Record
A25: North Star Balance LLC | B25: Physical Therapy | D25: Physical Therapy | E25: 15083 Flagstaff Ave | F25: Ste A | G25: Apple Valley | H25: Dakota | I25: Twin Cities Metro | J25: 55124 | K25: (612) 246-6900 | L25: 0 | M25: No | N25: 46114 | O25: North Star Balance LLC | P25: 1023959228 | Q25: Map | R25: Record
A26: Novacare Rehabilitation | B26: Physical Therapy | D26: Physical Therapy | E26: 15290 Pennock Ln | F26: Ste 120 | G26: Apple Valley | H26: Dakota | I26: Twin Cities Metro | J26: 55124 | K26: (952) 953-3711 | L26: 2 | M26: No | N26: 45951 | O26: Novacare Outpatient Rehabilitation East INC | P26: 1669668026 | Q26: Map | R26: Record
A27: Spinefocus Physical Therapy LLC | B27: Physical Therapy | D27: Physical Therapy | E27: 7300 147th St W | F27: Ste 403 | G27: Apple Valley | H27: Dakota | I27: Twin Cities Metro | J27: 55124 | K27: (651) 363-1449 | L27: 1 | M27: No | N27: 46119 | O27: Spinefocus Physical Therapy LLC | P27: 1013859305 | Q27: Map | R27: Record
A28: Therapy Partners, INC. | B28: Physical Therapy | D28: Physical Therapy | E28: 15160 Foliage Ave | F28: Ste 170 | G28: Apple Valley | H28: Dakota | I28: Twin Cities Metro | J28: 55124 | K28: (952) 683-1745 | L28: 5 | M28: No | N28: 46275 | O28: Therapy Partners, INC. | P28: 1407809494 | Q28: Map | R28: Record
A29: Therapy Partners, INC. | B29: Physical Therapy | D29: Physical Therapy | E29: 14665 Galaxie Ave | F29: Ste 320 | G29: Apple Valley | H29: Dakota | I29: Twin Cities Metro | J29: 55124 | K29: (952) 892-6777 | L29: 2 | M29: No | N29: 46275 | O29: Therapy Partners, INC. | P29: 1407809494 | Q29: Map | R29: Record
A30: Institute For Orthopedics & Chiropractic, PLLC | B30: Chiropractic | C30: Physical Therapy | D30: Chiropractic, Physical Therapy | E30: 14300 Buck Hill Rd | F30: Ste E | G30: Burnsville | H30: Dakota | I30: Twin Cities Metro | J30: 55306 | K30: (952) 941-3311 | L30: 4 | M30: No | N30: 46161 | O30: Institute For Orthopedics & Chiropractic, PLLC | P30: 1710216858 | Q30: Map | R30: Record
A31: Integrative Orthopedic Clinics, PLLC | B31: Physical Therapy | C31: Chiropractic | D31: Chiropractic, Physical Therapy | E31: 14300 Buck Hill Rd | F31: Ste E | G31: Burnsville | H31: Dakota | I31: Twin Cities Metro | J31: 55306 | K31: (952) 941-3311 | L31: 4 | M31: No | N31: 46148 | O31: Integrative Orthopedic Clinics, PLLC | P31: 1558208033 | Q31: Map | R31: Record
A32: Mprove Physical Therapy, LLC | B32: Physical Therapy | D32: Physical Therapy | E32: 1103 W Burnsville Pkwy | F32: Ste 120 | G32: Burnsville | H32: Dakota | I32: Twin Cities Metro | J32: 55337 | K32: (952) 300-1461 | L32: 1 | M32: No | N32: 45169 | O32: Mprove Physical Therapy, LLC | P32: 1538842711 | Q32: Map | R32: Record
A33: Pdr Burnsville, INC | B33: Injury Physicians | C33: Chiropractic, Physical Therapy | D33: Physical Medicine & Rehabilitation, Chiropractic, Physical Therapy | E33: 14050 Nicollet Ave | F33: #114 | G33: Burnsville | H33: Dakota | I33: Twin Cities Metro | J33: 55337 | K33: (952) 908-2710 | L33: 1 | M33: No | N33: 45911 | O33: Pdr Burnsville, INC | P33: 1952414971 | Q33: Map | R33: Record
A34: Therapy Partners, INC. | B34: Physical Therapy | D34: Physical Therapy | E34: 1351 Larc Industrial Blvd | G34: Burnsville | H34: Dakota | I34: Twin Cities Metro | J34: 55337 | K34: (952) 683-1745 | L34: 1 | M34: No | N34: 46275 | O34: Therapy Partners, INC. | P34: 1407809494 | Q34: Map | R34: Record
A35: Children's Therapy Center, INC | B35: Physical Therapy | D35: Physical Therapy | E35: 2795 Pilot Knob Rd | F35: Ste 100 | G35: Eagan | H35: Dakota | I35: Twin Cities Metro | J35: 55121 | K35: (651) 994-9644 | L35: 7 | M35: No | N35: 46141 | O35: Children's Therapy Center, INC | P35: 1295809366 | Q35: Map | R35: Record
A36: Concentra Medical Center | B36: Physical Therapy | D36: Physical Therapy | E36: 1400 Corporate Center Curv | F36: Ste 200 | G36: Eagan | H36: Dakota | I36: Twin Cities Metro | J36: 55121 | K36: (651) 968-5732 | L36: 0 | M36: No | N36: 46211 | O36: Occupational Health Centers of Minnesota PC | P36: 1174441083 | Q36: Map | R36: Record
A37: M Health Fairview Rehabilitation | B37: Physical Therapy | D37: Physical Therapy | E37: 3305 Central Park Village Drive | F37: Ste 130 | G37: Eagan | H37: Dakota | I37: Twin Cities Metro | J37: 55121 | K37: (651) 406-8868 | L37: 12 | M37: No | N37: 45950 | O37: Fairview Express Care | P37: 1881141349 | Q37: Map | R37: Record
A38: Medlinq Clinics | B38: Physical Therapy | D38: Physical Therapy | E38: 860 Blue Gentian Rd | F38: Ste 200 | G38: Eagan | H38: Dakota | I38: Twin Cities Metro | J38: 55121 | K38: (888) 447-8248 | L38: 0 | M38: No | N38: 45674 | O38: Medlinq | P38: 1689150120 | Q38: Map | R38: Record
A39: Summit Orthopedics, LTD | B39: Injury Physicians | C39: Physical Therapy | D39: Orthopedics, Physical Therapy | E39: 2620 Eagan Woods Dr | G39: Eagan | H39: Dakota | I39: Twin Cities Metro | J39: 55121 | K39: (651) 968-5200 | L39: 23 | M39: Yes | N39: 45867 | O39: Summit Orthopedics, LTD | P39: 1063563518 | Q39: Map | R39: Record
A40: Therapy Partners, INC. | B40: Physical Therapy | D40: Physical Therapy | E40: 2119 Cliff Rd | G40: Eagan | H40: Dakota | I40: Twin Cities Metro | J40: 55122 | K40: (651) 688-7500 | L40: 7 | M40: No | N40: 46275 | O40: Therapy Partners, INC. | P40: 1407809494 | Q40: Map | R40: Record
A41: The Next Level Physio, LLC | B41: Physical Therapy | D41: Physical Therapy | E41: 21210 Eaton Ave | G41: Farmington | H41: Dakota | I41: Twin Cities Metro | J41: 55024 | K41: (612) 226-7885 | L41: 1 | M41: No | N41: 45295 | O41: The Next Level Physio, LLC | P41: 1760263461 | Q41: Map | R41: Record
A42: Therapy Ops, LLC | B42: Physical Therapy | D42: Physical Therapy | E42: 1312 S Frontage Rd | G42: Hastings | H42: Dakota | I42: Twin Cities Metro | J42: 55033 | K42: (651) 455-0561 | L42: 0 | M42: No | N42: 45012 | O42: Therapy Ops, LLC | P42: 1013323559 | Q42: Map | R42: Record
A43: Compcare Occupational Medicine & Urgent Care | B43: Physical Therapy | D43: Physical Therapy | E43: 7635 Addisen Path | G43: Inver Grove Heights | H43: Dakota | I43: Twin Cities Metro | J43: 55077 | K43: (805) 698-8480 | L43: 0 | M43: No | N43: 45205 | O43: Presence Telehealth PLLC | P43: 1780162552 | Q43: Map | R43: Record
A44: Inver Grove Chiropractic P A | B44: Chiropractic | C44: Physical Therapy | D44: Chiropractic, Physical Therapy | E44: 2940 65th St E | G44: Inver Grove Heights | H44: Dakota | I44: Twin Cities Metro | J44: 55076 | K44: (651) 451-1012 | L44: 3 | M44: No | N44: 45622 | O44: Inver Grove Chiropractic P A | P44: 1194904417 | Q44: Map | R44: Record
A45: Therapy Ops, LLC | B45: Physical Therapy | D45: Physical Therapy | E45: 2925 Buckley Way | G45: Inver Grove Heights | H45: Dakota | I45: Twin Cities Metro | J45: 55076 | K45: (612) 360-4289 | L45: 6 | M45: No | N45: 45012 | O45: Therapy Ops, LLC | P45: 1013323559 | Q45: Map | R45: Record
A46: Fyzical Therapy & Balance | B46: Physical Therapy | D46: Physical Therapy | E46: 17761 Kenwood Trl | G46: Lakeville | H46: Dakota | I46: Twin Cities Metro | J46: 55044 | K46: (612) 203-9115 | L46: 0 | M46: No | N46: 44995 | O46: Pink Skies Corporation | P46: 1871294538 | Q46: Map | R46: Record
A47: Novacare Rehabilitation | B47: Physical Therapy | D47: Physical Therapy | E47: 17305 Cedar Ave S | F47: Ste 110 | G47: Lakeville | H47: Dakota | I47: Twin Cities Metro | J47: 55044 | K47: (952) 953-3711 | L47: 5 | M47: No | N47: 45588 | O47: Novacare Outpatient Rehabilitation East, INC. | P47: 1356162143 | Q47: Map | R47: Record
A48: Concentra Medical Center | B48: Physical Therapy | D48: Physical Therapy | E48: 2520 Pilot Knob Rd | F48: Ste 250 | G48: Mendota Heights | H48: Dakota | I48: Twin Cities Metro | J48: 55120 | K48: (651) 224-8264 | L48: 3 | M48: No | N48: 45827 | O48: Occupational Health Centers of Minnesota PC | P48: 1407337868 | Q48: Map | R48: Record
A49: Heights PT PLLC | B49: Physical Therapy | D49: Physical Therapy | E49: 665 Woodridge Dr | G49: Mendota Heights | H49: Dakota | I49: Twin Cities Metro | J49: 55118 | K49: (612) 237-1072 | L49: 0 | M49: No | N49: 45936 | O49: Heights PT PLLC | P49: 1407727191 | Q49: Map | R49: Record
A50: Mendota Physical Therapy LLC | B50: Physical Therapy | D50: Physical Therapy | E50: 1270 Northland Dr | F50: Ste 175 | G50: Mendota Heights | H50: Dakota | I50: Twin Cities Metro | J50: 55120 | K50: (651) 905-9000 | L50: 5 | M50: No | N50: 44860 | O50: Mendota Physical Therapy LLC | P50: 1487064507 | Q50: Map | R50: Record
A51: Therapy Partners, INC. | B51: Physical Therapy | D51: Physical Therapy | E51: 1270 Northland Dr | F51: Ste 175 | G51: Mendota Heights | H51: Dakota | I51: Twin Cities Metro | J51: 55120 | K51: (651) 905-9000 | L51: 5 | M51: No | N51: 46275 | O51: Therapy Partners, INC. | P51: 1407809494 | Q51: Map | R51: Record
A52: Nielson Family Chiropractic PLLC | B52: Chiropractic | C52: Physical Therapy | D52: Chiropractic, Physical Therapy | E52: 14450 S Robert Trl | F52: Ste 208 | G52: Rosemount | H52: Dakota | I52: Twin Cities Metro | J52: 55068 | K52: (651) 423-2251 | L52: 5 | M52: No | N52: 46198 | O52: Nielson Family Chiropractic PLLC | P52: 1467736231 | Q52: Map | R52: Record
A53: Novacare Rehabilitation | B53: Physical Therapy | D53: Physical Therapy | E53: 60 Marie Ave E | F53: Ste 105, 2ND Floor | G53: West St Paul | H53: Dakota | I53: Twin Cities Metro | J53: 55118 | K53: (651) 451-6156 | L53: 8 | M53: No | N53: 45951 | O53: Select Physical Therapy Holdings INC | P53: 1689634131 | Q53: Map | R53: Record
A54: Infinite Health Collaborative, PA | B54: Injury Physicians | C54: Physical Therapy, Imaging | D54: Orthopedics, Physical Therapy, Radiology | E54: 3500 American Blvd W | F54: Ste 300 | G54: Bloomington | H54: Hennepin | I54: Twin Cities Metro | J54: 55431 | K54: (952) 512-5600 | L54: 0 | M54: Yes | N54: 46177 | O54: Infinite Health Collaborative, PA | P54: 1265675870 | Q54: Map | R54: Record
A55: National Dizzy & Balance Center,ltd. | B55: Injury Physicians | C55: Physical Therapy | D55: Physical Medicine & Rehabilitation, Physical Therapy | E55: 4801 W 81st St | F55: Ste 112 | G55: Bloomington | H55: Hennepin | I55: Twin Cities Metro | J55: 55437 | K55: (952) 345-3000 | L55: 19 | M55: No | N55: 44901 | O55: National Dizzy & Balance Center,ltd. | P55: 1023021938 | Q55: Map | R55: Record
A56: Saunders Therapy Centers INC | B56: Physical Therapy | D56: Physical Therapy | E56: 4801 W 81st St | F56: Ste 103 | G56: Bloomington | H56: Hennepin | I56: Twin Cities Metro | J56: 55437 | K56: (952) 924-0199 | L56: 17 | M56: No | N56: 45609 | O56: Saunders Therapy Centers INC | P56: 1952554495 | Q56: Map | R56: Record
A57: Shooting Star Pediatric Physical Therapy LLC | B57: Physical Therapy | D57: Physical Therapy | E57: 8120 Penn Ave S | F57: Ste 500C | G57: Bloomington | H57: Hennepin | I57: Twin Cities Metro | J57: 55431 | K57: (952) 373-1180 | L57: 6 | M57: No | N57: 45055 | O57: Shooting Star Pediatric Physical Therapy LLC | P57: 1952091464 | Q57: Map | R57: Record
A58: Tria Orthopaedic Center LLC | B58: Injury Physicians | C58: Physical Therapy | D58: Orthopedics, Pain Management, Physical Therapy | E58: 8100 Northland Dr | G58: Bloomington | H58: Hennepin | I58: Twin Cities Metro | J58: 55431 | K58: (952) 831-8742 | L58: 78 | M58: Yes | N58: 46237 | O58: Tria Orthopaedic Center LLC | P58: 1346624384 | Q58: Map | R58: Record
A59: Tria Orthopaedic Clinic | B59: Injury Physicians | C59: Physical Therapy | D59: Orthopedics, Pain Management, Physical Therapy | E59: 8100 Northland Dr | G59: Bloomington | H59: Hennepin | I59: Twin Cities Metro | J59: 55431 | K59: (952) 831-8742 | L59: 78 | M59: Yes | N59: 46237 | O59: Tria Orthopaedic Center LLC | P59: 1518273085 | Q59: Map | R59: Record
A60: Viverant PT LLC | B60: Physical Therapy | D60: Physical Therapy | E60: 5107 W 98th St | G60: Bloomington | H60: Hennepin | I60: Twin Cities Metro | J60: 55437 | K60: (952) 835-4512 | L60: 2 | M60: No | N60: 44687 | O60: Viverant PT LLC | P60: 1346553179 | Q60: Map | R60: Record
A61: Drift North Therapy Co. PLLC | B61: Physical Therapy | D61: Physical Therapy | E61: 5320 95th Ln N | G61: Brooklyn Park | H61: Hennepin | I61: Twin Cities Metro | J61: 55443 | K61: (763) 258-9803 | L61: 1 | M61: No | N61: 46097 | O61: Drift North Therapy Co. PLLC | P61: 1497602551 | Q61: Map | R61: Record
A62: Sunnydays Therapy INC | B62: Physical Therapy | D62: Physical Therapy | E62: 18872 Lake Dr E | G62: Chanhassen | H62: Hennepin | I62: Twin Cities Metro | J62: 55317 | K62: (952) 223-2506 | L62: 0 | M62: No | N62: 45379 | O62: Sunnydays Therapy INC | P62: 1891914412 | Q62: Map | R62: Record
A63: Novacare Rehabilitation | B63: Physical Therapy | D63: Physical Therapy | E63: 5700 Bottineau Blvd | F63: Ste 200 | G63: Crystal | H63: Hennepin | I63: Twin Cities Metro | J63: 55429 | K63: (763) 535-7607 | L63: 3 | M63: No | N63: 46106 | O63: Novacare Outpatient Rehabilitation East INC | P63: 1518963909 | Q63: Map | R63: Record
A64: Active Therapy MN | B64: Physical Therapy | D64: Physical Therapy | E64: 10300 Hennepin Town Rd | G64: Eden Prairie | H64: Hennepin | I64: Twin Cities Metro | J64: 55347 | K64: (612) 562-8204 | L64: 3 | M64: No | N64: 44642 | O64: Active Therapy MN | P64: 1730835257 | Q64: Map | R64: Record
A65: Atrium Physical Therapy | B65: Physical Therapy | D65: Physical Therapy | E65: 6400 Flying Cloud Dr | F65: Ste 213 | G65: Eden Prairie | H65: Hennepin | I65: Twin Cities Metro | J65: 55344 | K65: (952) 457-2811 | L65: 0 | M65: No | N65: 46156 | O65: Mobilerehabmn | P65: 1306496278 | Q65: Map | R65: Record
A66: Flying Cloud Spine & Sport, PA. | B66: Physical Therapy | C66: Chiropractic | D66: Chiropractic, Physical Therapy | E66: 7707 Flying Cloud Dr | G66: Eden Prairie | H66: Hennepin | I66: Twin Cities Metro | J66: 55344 | K66: (952) 829-7814 | L66: 1 | M66: No | N66: 45911 | O66: Flying Cloud Spine & Sport, PA. | P66: 1861405128 | Q66: Map | R66: Record
A67: Institute For Orthopedics & Chiropractic, PLLC | B67: Chiropractic | C67: Physical Therapy | D67: Chiropractic, Physical Therapy | E67: 6545 Flying Cloud Dr | F67: Ste 100 | G67: Eden Prairie | H67: Hennepin | I67: Twin Cities Metro | J67: 55344 | K67: (952) 941-3311 | L67: 23 | M67: No | N67: 46161 | O67: Institute For Orthopedics & Chiropractic, PLLC | P67: 1710216858 | Q67: Map | R67: Record
A68: Integrative Orthopedic Clinics, PLLC | B68: Physical Therapy | C68: Chiropractic | D68: Chiropractic, Physical Therapy | E68: 6545 Flying Cloud Dr | F68: Ste 100 | G68: Eden Prairie | H68: Hennepin | I68: Twin Cities Metro | J68: 55344 | K68: (952) 941-3311 | L68: 23 | M68: No | N68: 46148 | O68: Integrative Orthopedic Clinics, PLLC | P68: 1558208033 | Q68: Map | R68: Record
A69: Orthology | B69: Physical Therapy | D69: Physical Therapy | E69: 11995 Singletree Lane | F69: Ste 120 | G69: Eden Prairie | H69: Hennepin | I69: Twin Cities Metro | J69: 55344 | K69: (952) 491-4442 | L69: 10 | M69: No | N69: 44784 | O69: Perham Physical Therapy LTD. | P69: 1437451853 | Q69: Map | R69: Record
A70: Sartorial Physical Therapy and Wellness | B70: Physical Therapy | D70: Physical Therapy | E70: 9642 Jonathan Ln | G70: Eden Prairie | H70: Hennepin | I70: Twin Cities Metro | J70: 55347 | K70: (217) 313-9833 | L70: 0 | M70: No | N70: 44634 | O70: Sartorial Physical Therapy and Wellness | P70: 1104574763 | Q70: Map | R70: Record
A71: Sturm Physical Therapy & Lymphatic Health LLC | B71: Physical Therapy | D71: Physical Therapy | E71: 8901 Aztec Dr | F71: Ste B | G71: Eden Prairie | H71: Hennepin | I71: Twin Cities Metro | J71: 55347 | K71: (612) 234-1181 | L71: 1 | M71: No | N71: 46126 | O71: Sturm Physical Therapy & Lymphatic Health LLC | P71: 1447190202 | Q71: Map | R71: Record
A72: Therapy Partners, INC. | B72: Physical Therapy | D72: Physical Therapy | E72: 11995 Singletree Ln | F72: Ste 120 | G72: Eden Prairie | H72: Hennepin | I72: Twin Cities Metro | J72: 55344 | K72: (952) 373-5720 | L72: 10 | M72: No | N72: 46275 | O72: Therapy Partners, INC. | P72: 1407809494 | Q72: Map | R72: Record
A73: Active Life Physical Therapy and Wellness LLC | B73: Physical Therapy | D73: Physical Therapy | E73: 5200 Willson Rd | F73: Ste 150 | G73: Edina | H73: Hennepin | I73: Twin Cities Metro | J73: 55424 | K73: (952) 232-5020 | L73: 0 | M73: No | N73: 45366 | O73: Active Life Physical Therapy and Wellness LLC | P73: 1205694742 | Q73: Map | R73: Record
A74: Bethany Hansen, LLC | B74: Physical Therapy | D74: Physical Therapy | E74: 7250 Metro Blvd | F74: Ste 100 | G74: Edina | H74: Hennepin | I74: Twin Cities Metro | J74: 55439 | K74: (612) 778-6240 | L74: 1 | M74: No | N74: 46174 | O74: Bethany Hansen, LLC | P74: 1811661747 | Q74: Map | R74: Record
A75: Center For Pediatric Movement LLC | B75: Physical Therapy | D75: Physical Therapy | E75: 6600 France Ave S | F75: Ste 164 | G75: Edina | H75: Hennepin | I75: Twin Cities Metro | J75: 55435 | K75: (612) 889-0973 | L75: 8 | M75: No | N75: 46059 | O75: Center For Pediatric Movement LLC | P75: 1881307932 | Q75: Map | R75: Record
A76: Fyzical Therapy and Balance Centers Edina | B76: Physical Therapy | D76: Physical Therapy | E76: 5227 W 73rd St | G76: Edina | H76: Hennepin | I76: Twin Cities Metro | J76: 55439 | K76: (952) 207-2997 | L76: 0 | M76: No | N76: 45778 | O76: Therex Rehab Specialists, LLC | P76: 1629004692 | Q76: Map | R76: Record
A77: Healthpro Heritage Rehab & Fitness, LLC | B77: Physical Therapy | D77: Physical Therapy | E77: 7128 France Ave S | G77: Edina | H77: Hennepin | I77: Twin Cities Metro | J77: 55435 | K77: (651) 422-8987 | L77: 0 | M77: No | N77: 45643 | O77: Healthpro Heritage Rehab & Fitness, LLC | P77: 1841063872 | Q77: Map | R77: Record
A78: Institute For Orthopedics & Chiropractic, PLLC | B78: Chiropractic | C78: Physical Therapy | D78: Chiropractic, Physical Therapy | E78: 6550 York Ave S | F78: Ste 600 | G78: Edina | H78: Hennepin | I78: Twin Cities Metro | J78: 55435 | K78: (952) 941-3311 | L78: 27 | M78: No | N78: 46161 | O78: Institute For Orthopedics & Chiropractic, PLLC | P78: 1710216858 | Q78: Map | R78: Record
A79: Novacare Rehabilitation | B79: Physical Therapy | D79: Physical Therapy | E79: 6515 Barrie Rd | F79: Ste 100 | G79: Edina | H79: Hennepin | I79: Twin Cities Metro | J79: 55435 | K79: (952) 922-5019 | L79: 8 | M79: No | N79: 45951 | O79: Novacare Outpatient Rehabilitation East INC | P79: 1518963909 | Q79: Map | R79: Record
A80: Pdr Southdale, INC | B80: Injury Physicians | C80: Chiropractic, Physical Therapy | D80: Physical Medicine & Rehabilitation, Chiropractic, Physical Therapy | E80: 3400 W 66th St | F80: Ste 450 | G80: Edina | H80: Hennepin | I80: Twin Cities Metro | J80: 55435 | K80: (952) 908-2700 | L80: 41 | M80: No | N80: 45911 | O80: Pdr Southdale, INC | P80: 1073626008 | Q80: Map | R80: Record
A81: Romanie Health Services, PA | B81: Chiropractic | C81: Physical Therapy | D81: Chiropractic, Physical Therapy | E81: 5325 W 74th St | F81: Ste 9 | G81: Edina | H81: Hennepin | I81: Twin Cities Metro | J81: 55439 | K81: (952) 835-6653 | L81: 0 | M81: No | N81: 44865 | O81: Romanie Health Services, PA | P81: 1912551185 | Q81: Map | R81: Record
A82: Romanie Health Services, PA | B82: Physical Therapy | D82: Physical Therapy | E82: 4510 77th St W | F82: Ste 120 | G82: Edina | H82: Hennepin | I82: Twin Cities Metro | J82: 55435 | K82: (952) 835-6653 | L82: 0 | M82: No | N82: 45460 | O82: Romanie Health Services, PA | P82: 1316780349 | Q82: Map | R82: Record
A83: Therapy Partners, INC. | B83: Physical Therapy | D83: Physical Therapy | E83: 6529 Cecilia Cir | G83: Edina | H83: Hennepin | I83: Twin Cities Metro | J83: 55439 | K83: (651) 348-7428 | L83: 4 | M83: No | N83: 46275 | O83: Therapy Partners, INC. | P83: 1407809494 | Q83: Map | R83: Record
A84: Therapy Partners, INC. | B84: Physical Therapy | D84: Physical Therapy | E84: 4956 Lincoln Dr | G84: Edina | H84: Hennepin | I84: Twin Cities Metro | J84: 55436 | K84: (952) 936-9600 | L84: 4 | M84: No | N84: 46275 | O84: Therapy Partners, INC. | P84: 1407809494 | Q84: Map | R84: Record
A85: Intrinsic Physical Therapy & Wellness | B85: Physical Therapy | D85: Physical Therapy | E85: 4250 Dahlberg Dr | G85: Golden Valley | H85: Hennepin | I85: Twin Cities Metro | J85: 55422 | K85: (612) 440-8455 | L85: 1 | M85: No | N85: 46028 | O85: Intrinsic Physical Therapy, LLC | P85: 1770264426 | Q85: Map | R85: Record
A86: Dmr Methods | B86: Chiropractic | C86: Physical Therapy | D86: Chiropractic, Physical Therapy | E86: 15 8th Ave N | F86: Ste 2 | G86: Hopkins | H86: Hennepin | I86: Twin Cities Metro | J86: 55343 | K86: (952) 207-2768 | L86: 18 | M86: No | N86: 45908 | O86: Dmr Methods | P86: 1720969785 | Q86: Map | R86: Record
A87: Fix It Physical Therapy, LLC | B87: Physical Therapy | D87: Physical Therapy | E87: 11102 91st Ave N | F87: Ste 100 | G87: Maple Grove | H87: Hennepin | I87: Twin Cities Metro | J87: 55369 | K87: (612) 222-3029 | L87: 1 | M87: No | N87: 46196 | O87: Fix It Physical Therapy, LLC | P87: 1356277511 | Q87: Map | R87: Record
A88: Interventional Spine and Pain Physicians, PA | B88: Injury Physicians | C88: Physical Therapy | D88: Pain Management, Physical Medicine & Rehabilitation, Physical Therapy | E88: 9645 Grove Cir N | F88: Ste 200 | G88: Maple Grove | H88: Hennepin | I88: Twin Cities Metro | J88: 55369 | K88: (763) 201-8191 | L88: 7 | M88: No | N88: 46287 | O88: Interventional Spine and Pain Physicians, PA | P88: 1326398561 | Q88: Map | R88: Record
A89: Movement Lab Physical Therapy LLC | B89: Physical Therapy | D89: Physical Therapy | E89: 6274 Fountain Ln N | G89: Maple Grove | H89: Hennepin | I89: Twin Cities Metro | J89: 55311 | K89: (612) 703-4888 | L89: 0 | M89: No | N89: 46269 | O89: Movement Lab Physical Therapy LLC | P89: 1184543001 | Q89: Map | R89: Record
A90: Novacare Rehabilitation | B90: Physical Therapy | D90: Physical Therapy | E90: 16366 County Road 30 | G90: Maple Grove | H90: Hennepin | I90: Twin Cities Metro | J90: 55311 | K90: (763) 559-0356 | L90: 2 | M90: No | N90: 45926 | O90: Novacare Outpatient Rehabilitation East, INC. | P90: 1366084402 | Q90: Map | R90: Record
A91: Saunders Therapy Centers INC | B91: Physical Therapy | D91: Physical Therapy | E91: 10900 73rd Ave N | F91: Ste 140 | G91: Maple Grove | H91: Hennepin | I91: Twin Cities Metro | J91: 55369 | K91: (763) 315-1296 | L91: 10 | M91: No | N91: 45609 | O91: Saunders Therapy Centers INC | P91: 1952554495 | Q91: Map | R91: Record
A92: Sunnydays Therapy INC | B92: Physical Therapy | D92: Physical Therapy | E92: 6433 Sycamore Ct N | G92: Maple Grove | H92: Hennepin | I92: Twin Cities Metro | J92: 55369 | K92: (952) 223-2506 | L92: 0 | M92: No | N92: 45379 | O92: Sunnydays Therapy INC | P92: 1891914412 | Q92: Map | R92: Record
A93: Therapy Partners, INC. | B93: Physical Therapy | D93: Physical Therapy | E93: 9325 Upland Ln N | F93: Ste 230 | G93: Maple Grove | H93: Hennepin | I93: Twin Cities Metro | J93: 55369 | K93: (763) 315-0466 | L93: 7 | M93: No | N93: 46275 | O93: Therapy Partners, INC. | P93: 1407809494 | Q93: Map | R93: Record
A94: Arlo Physical Therapy & Wellness | B94: Physical Therapy | D94: Physical Therapy | E94: 575 9th St SE | F94: Ste 52 | G94: Minneapolis | H94: Hennepin | I94: Twin Cities Metro | J94: 55414 | K94: (612) 300-2232 | L94: 0 | M94: No | N94: 46027 | O94: Arlo Physical Therapy LLC | P94: 1831948199 | Q94: Map | R94: Record
A95: Atrium Physical Therapy | B95: Physical Therapy | D95: Physical Therapy | E95: 5646 Interlachen Cir | G95: Minneapolis | H95: Hennepin | I95: Twin Cities Metro | J95: 55436 | K95: (952) 457-2811 | L95: 1 | M95: No | N95: 46156 | O95: Mobilerehabmn | P95: 1306496278 | Q95: Map | R95: Record
A96: Concentra Medical Center | B96: Physical Therapy | D96: Physical Therapy | E96: 7550 34th Ave S | G96: Minneapolis | H96: Hennepin | I96: Twin Cities Metro | J96: 55450 | K96: (612) 727-1167 | L96: 3 | M96: No | N96: 45827 | O96: Occupational Health Centers of Minnesota PC | P96: 1427539881 | Q96: Map | R96: Record
A97: Fairview Specialty Services | B97: Physical Therapy | D97: Physical Therapy | E97: 2450 Riverside Ave | G97: Minneapolis | H97: Hennepin | I97: Twin Cities Metro | J97: 55454 | K97: (855) 324-7843 | L97: 130 | M97: Yes | N97: 45898 | O97: Fairview Specialty Services | P97: 1043199334 | Q97: Map | R97: Record
A98: Minnesota Orthopedic Performance and Prevention LLC | B98: Physical Therapy | D98: Physical Therapy | E98: 2721 E Franklin Ave | G98: Minneapolis | H98: Hennepin | I98: Twin Cities Metro | J98: 55406 | K98: (651) 412-3072 | L98: 0 | M98: No | N98: 44606 | O98: Minnesota Orthopedic Performance and Prevention LLC | P98: 1770238396 | Q98: Map | R98: Record
A99: Motion Forward Physical Therapy and Wellness LLC | B99: Physical Therapy | D99: Physical Therapy | E99: 305 1st Ave NE | G99: Minneapolis | H99: Hennepin | I99: Twin Cities Metro | J99: 55413 | K99: (612) 482-1086 | L99: 1 | M99: No | N99: 46021 | O99: Motion Forward Physical Therapy and Wellness LLC | P99: 1073361283 | Q99: Map | R99: Record
A100: Prescott Therapies LLC | B100: Physical Therapy | D100: Physical Therapy | E100: 825 Nicollet Mall | F100: Ste 1947 | G100: Minneapolis | H100: Hennepin | I100: Twin Cities Metro | J100: 55402 | K100: (952) 200-0215 | L100: 7 | M100: No | N100: 45616 | O100: Prescott Therapies LLC | P100: 1487240693 | Q100: Map | R100: Record
...

Sheet Imaging
A1: Clinic Name | B1: Specialty Group | C1: Also In | D1: Specialties | E1: Street | F1: Suite | G1: City | H1: County | I1: Region | J1: ZIP | K1: Phone | L1: Providers at Address | M1: On Xpert Connect | N1: Registry Updated | O1: Legal Name | P1: NPI | Q1: Map | R1: NPPES Record
A2: Ridgeview Medical Center | B2: Imaging | D2: Radiology | E2: 500 S Maple St | G2: Waconia | H2: Carver | I2: Twin Cities Metro | J2: 55387 | K2: (952) 442-2191 | L2: 3 | M2: Yes | N2: 45268 | O2: Ridgeview Medical Center | P2: 1811174923 | Q2: Map | R2: Record
A3: Summit Orthopedics, LTD | B3: Injury Physicians | C3: Imaging | D3: Orthopedics, MRI | E3: 17210 Kenyon Ave | G3: Lakeville | H3: Dakota | I3: Twin Cities Metro | J3: 55044 | K3: (651) 968-5201 | L3: 0 | M3: No | N3: 45818 | O3: Summit Orthopedics, LTD | P3: 1629740949 | Q3: Map | R3: Record
A4: Infinite Health Collaborative, PA | B4: Injury Physicians | C4: Physical Therapy, Imaging | D4: Orthopedics, Physical Therapy, Radiology | E4: 3500 American Blvd W | F4: Ste 300 | G4: Bloomington | H4: Hennepin | I4: Twin Cities Metro | J4: 55431 | K4: (952) 512-5600 | L4: 0 | M4: Yes | N4: 46177 | O4: Infinite Health Collaborative, PA | P4: 1265675870 | Q4: Map | R4: Record
A5: Icare Diagnostic Imaging | B5: Imaging | D5: MRI | E5: 2781 Freeway Blvd | F5: Ste 160 | G5: Brooklyn Center | H5: Hennepin | I5: Twin Cities Metro | J5: 55430 | K5: (763) 244-8020 | L5: 0 | M5: No | N5: 46198 | O5: Icare Diagnostic Imaging | P5: 1336580018 | Q5: Map | R5: Record
A6: Rayus Radiology | B6: Imaging | D6: Radiology | E6: 775 Prairie Center Dr | F6: Ste 260 | G6: Eden Prairie | H6: Hennepin | I6: Twin Cities Metro | J6: 55344 | K6: (952) 345-3805 | L6: 0 | M6: No | N6: 45931 | O6: Medical Scanning Consultants PA | P6: 1699706176 | Q6: Map | R6: Record
A7: Diagnostic Imaging, INC | B7: Imaging | D7: MRI | E7: 6500 Barrie Rd | G7: Edina | H7: Hennepin | I7: Twin Cities Metro | J7: 55435 | K7: (952) 920-6500 | L7: 0 | M7: No | N7: 44763 | O7: Diagnostic Imaging, INC | P7: 1558406074 | Q7: Map | R7: Record
A8: Summit Orthopedics LTD | B8: Imaging | D8: MRI | E8: 6050 Sycamore Lane N. | G8: Plymouth | H8: Hennepin | I8: Twin Cities Metro | J8: 55442 | K8: (651) 968-5200 | L8: 0 | M8: Yes | N8: 45743 | O8: Summit Orthopedics LTD | P8: 1952103905 | Q8: Map | R8: Record
A9: Center For Diagnostic Imaging | B9: Imaging | D9: Radiology | E9: 5775 Wayzata Blvd | F9: Ste 400 | G9: St. Louis Park | H9: Hennepin | I9: Twin Cities Metro | J9: 55416 | K9: (952) 525-6338 | L9: 27 | M9: No | N9: 44763 | O9: Rai Keystone Imaging Services, LLC | P9: 1609392349 | Q9: Map | R9: Record
A10: Rayus Radiology | B10: Imaging | D10: Radiology | E10: 5775 Wayzata Blvd | F10: Ste 190 | G10: St. Louis Park | H10: Hennepin | I10: Twin Cities Metro | J10: 55416 | K10: (952) 541-1840 | L10: 27 | M10: No | N10: 46289 | O10: Medical Scanning Consultants PA | P10: 1659348092 | Q10: Map | R10: Record
A11: Maplewood Imaging Center LLC | B11: Imaging | D11: Radiology | E11: 2945 Hazelwood St | F11: Ste 110 | G11: Maplewood | H11: Ramsey | I11: Twin Cities Metro | J11: 55109 | K11: (651) 292-2000 | L11: 0 | M11: No | N11: 44594 | O11: Maplewood Imaging Center LLC | P11: 1164604146 | Q11: Map | R11: Record
A12: Elite Radiology PA. | B12: Imaging | D12: Radiology, MRI | E12: 441 University Ave W | F12: Ste 102 | G12: St. Paul | H12: Ramsey | I12: Twin Cities Metro | J12: 55103 | K12: (651) 330-9270 | L12: 0 | M12: No | N12: 46251 | O12: Elite Radiology PA. | P12: 1316852908 | Q12: Map | R12: Record
A13: Summit Orthopedics, LTD | B13: Physical Therapy | C13: Imaging | D13: Physical Therapy, MRI | E13: 1661 Saint Anthony Ave | G13: St. Paul | H13: Ramsey | I13: Twin Cities Metro | J13: 55104 | K13: (651) 968-5335 | L13: 10 | M13: No | N13: 45818 | O13: Summit Orthopedics, LTD | P13: 1477604320 | Q13: Map | R13: Record
A14: Voyageur Imaging,llc | B14: Imaging | D14: Radiology | E14: 393 Dunlap St N | F14: Ste Ll40 | G14: St. Paul | H14: Ramsey | I14: Twin Cities Metro | J14: 55104 | K14: (651) 647-0000 | L14: 0 | M14: No | N14: 45315 | O14: Voyageur Imaging,llc | P14: 1043643059 | Q14: Map | R14: Record
A15: Medical X-Ray Consultants, LTD | B15: Imaging | D15: Radiology | E15: 111 17th Ave E | G15: Alexandria | H15: Douglas | I15: West Central Minnesota | J15: 56308 | K15: (715) 295-9431 | L15: 2 | M15: No | N15: 46106 | O15: Medical X-Ray Consultants, LTD | P15: 1386601383 | Q15: Map | R15: Record
A16: Mankato Clinic LTD | B16: Injury Physicians | C16: Imaging | D16: Neurology, Radiology | E16: 1230 E Main St | G16: Mankato | H16: Blue Earth | I16: South Central Minnesota | J16: 56001 | K16: (800) 657-6944 | L16: 5 | M16: No | N16: 46038 | O16: Mankato Clinic LTD | P16: 1629044029 | Q16: Map | R16: Record
A17: Sanford Luverne Clinic | B17: Injury Physicians | C17: Imaging | D17: Orthopedics, Radiology | E17: 1601 Sioux Valley Dr | G17: Luverne | H17: Rock | I17: Southwest Minnesota | J17: 56156 | K17: (507) 283-2321 | L17: 0 | M17: No | N17: 45230 | O17: Sanford Health Network | P17: 1033495379 | Q17: Map | R17: Record

Sheet TMJ Specialists
A1: Clinic Name | B1: Specialty Group | C1: Also In | D1: Specialties | E1: TMJ Specialists Here | F1: Street | G1: Suite | H1: City | I1: County | J1: Region | K1: ZIP | L1: Phone | M1: Website | N1: Web Check | O1: Providers at Address | P1: On Xpert Connect | Q1: Registry Updated | R1: Legal Name | S1: NPI | T1: Map | U1: NPPES Record
A2: The Facial Pain Center | B2: TMJ Specialists | D2: TMJ Treatment | E2: Patricia Fernandes Boettner, DDS, MS | F2: 4190 108th Ave NE | G2: Ste 130 | H2: Blaine | I2: Anoka | J2: Twin Cities Metro | K2: 55449 | L2: (651) 636-2016 | M2: thefacialpaincenter.com | N2: Confirmed | O2: 0 | P2: No | Q2: 46245 | R2: Facial Pain Center PLLC | S2: 1407325830 | T2: Map | U2: Record
A3: Minnesota Head and Neck Pain Clinic, PA | B3: TMJ Specialists | D3: TMJ Clinic | E3: James Fricton, DDS; Pathamas Mittman, DDS, MS; Saranya Varun, BDS, MDS; Thiago Nascimento, DDS | F3: 675 E Nicollet Blvd | G3: Ste 255 | H3: Burnsville | I3: Dakota | J3: Twin Cities Metro | K3: 55337 | L3: (952) 892-6222 | M3: mhnpc.com | N3: Confirmed | O3: 4 | P3: No | Q3: 45490 | R3: Minnesota Head and Neck Pain Clinic, PA | S3: 1255715181 | T3: Map | U3: Record
A4: The Facial Pain Center | B4: TMJ Specialists | D4: TMJ Clinic | E4: Davina Kumar, DMD, MS | F4: 40 W Nicollet Blvd | H4: Burnsville | I4: Dakota | J4: Twin Cities Metro | K4: 55337 | L4: (952) 926-3858 | M4: thefacialpaincenter.com | N4: Confirmed | O4: 1 | P4: No | Q4: 44132 | R4: Pdg, PA. | S4: 1821473927 | T4: Map | U4: Record
A5: The Facial Pain Center | B5: TMJ Specialists | D5: Orofacial Pain | E5: Davina Kumar, DMD, MS | F5: 4200 W Old Shakopee Rd | G5: Ste 100 | H5: Bloomington | I5: Hennepin | J5: Twin Cities Metro | K5: 55437 | L5: (952) 926-3858 | M5: thefacialpaincenter.com | N5: Confirmed | O5: 1 | P5: No | Q5: 45545 | R5: Davina Kumar, DMD | S5: 1043839574 | T5: Map | U5: Record
A6: Gallagher Dentistry & Facial Pain Center | B6: TMJ Specialists | D6: TMJ Treatment | E6: Michael Gallagher, DDS | F6: 11800 Singletree Ln | G6: Ste 208 | H6: Eden Prairie | I6: Hennepin | J6: Twin Cities Metro | K6: 55344 | L6: (952) 942-9600 | M6: gallaghercosmeticdentistry.com | N6: Confirmed | O6: 0 | P6: No | Q6: 44065 | R6: Gallagher Cosmetic &family Dentistry, PA | S6: 1841353992 | T6: Map | U6: Record
A7: Twin Cities TMJ & Facial Pain Clinic | B7: TMJ Specialists | D7: TMJ Clinic | E7: Shanti Kaimal, BDS, MS; David Streif, DDS | F7: 4956 Lincoln Dr | H7: Edina | I7: Hennepin | J7: Twin Cities Metro | K7: 55436 | L7: (952) 931-9961 | M7: twincitiestmj.com | N7: New address | O7: 0 | P7: No | Q7: 39548 | R7: Twin Cities TMJ & Facial Pain Clinic, LTD. | S7: 1225201213 | T7: Map | U7: Record
A8: Zoya's Orofacial Pain and Dental Sleep Remedies PLLC | B8: TMJ Specialists | C8: Oral Surgery | D8: Orofacial Pain, TMJ Clinic, TMJ Treatment, Oral & Maxillofacial Surgery | E8: Mariam Siddiqui, BDS, MS | F8: 1405 Lilac Lane Drive North | G8: Ste 150 K | H8: Golden Valley | I8: Hennepin | J8: Twin Cities Metro | K8: 55422 | L8: (763) 762-6549 | M8: zoyaorofacialpaindentalsleep.org | N8: Confirmed | O8: 1 | P8: No | Q8: 44721 | R8: Zoya's Orofacial Pain and Dental Sleep Remedies PLLC | S8: 1306513023 | T8: Map | U8: Record
A9: Bloomington Sleep and TMD Care PLLC | B9: TMJ Specialists | D9: TMJ Clinic, TMJ Treatment | F9: 9820 Nicollet Ave S | H9: Minneapolis | I9: Hennepin | J9: Twin Cities Metro | K9: 55420 | L9: (952) 856-0058 | N9: Unverified | O9: 0 | P9: No | Q9: 46106 | R9: Bloomington Sleep and TMD Care PLLC | S9: 1922947142 | T9: Map | U9: Record
A10: Hennepin Healthcare Dental & Oral Surgery | B10: TMJ Specialists | D10: Orofacial Pain | E10: Dennis Haley, DDS; Maram Taema, BDS, MS | F10: 715 S 8th St | H10: Minneapolis | I10: Hennepin | J10: Twin Cities Metro | K10: 55404 | L10: (612) 873-6963 | M10: hennepinhealthcare.org | N10: Confirmed | O10: 2 | P10: No | Q10: 45639 | R10: Dennis Haley, DDS | S10: 1902850738 | T10: Map | U10: Record
A11: M Health Fairview Neurosurgery Clinic Minneapolis | B11: TMJ Specialists | D11: TMJ Treatment | E11: Donald Nixdorf, DDS, MS | F11: 909 Fulton St SE | G11: Floor 3 | H11: Minneapolis | I11: Hennepin | J11: Twin Cities Metro | K11: 55455 | L11: (651) 232-3900 | M11: providers.mhealthfairview.org | N11: Confirmed | O11: 0 | P11: No | R11: M Health Fairview Neurosurgery Clinic Minneapolis | T11: Map | U11: Web
A12: The Facial Pain Center | B12: TMJ Specialists | D12: Orofacial Pain, TMJ Clinic | E12: Davina Kumar, DMD, MS | F12: 5000 W 36th St | G12: Ste 250 | H12: Minneapolis | I12: Hennepin | J12: Twin Cities Metro | K12: 55416 | L12: (952) 926-3858 | M12: thefacialpaincenter.com | N12: Confirmed | O12: 1 | P12: No | Q12: 45545 | R12: Davina Kumar, DMD | S12: 1043839574 | T12: Map | U12: Record
A13: University of Minnesota TMD, Orofacial Pain & Dental Sleep Medicine Clinic | B13: TMJ Specialists | D13: Orofacial Pain, TMJ Clinic | E13: Alexander Crain, DDS; Benjaporn Krubsack, DDS, MS; Emilija Bezhoska; Jack Botros, DDS, MS; Julianne Yuziuk, DMD; Richard Van Gurp, DMD; Saranya Varun, BDS, MDS | F13: 515 Delaware St SE | G13: 7-530 Moos Tower | H13: Minneapolis | I13: Hennepin | J13: Twin Cities Metro | K13: 55455 | L13: (612) 626-0140 | M13: dentalclinics.umn.edu | N13: Confirmed | O13: 9 | P13: No | Q13: 45467 | R13: Regents of the University of Minnesota | S13: 1457448615 | T13: Map | U13: Record
A14: The Facial Pain Center | B14: TMJ Specialists | D14: TMJ Treatment | E14: Patricia Fernandes Boettner, DDS, MS | F14: 13059 Ridgedale Dr | H14: Minnetonka | I14: Hennepin | J14: Twin Cities Metro | K14: 55305 | L14: (952) 926-3858 | M14: thefacialpaincenter.com | N14: Confirmed | O14: 0 | P14: No | Q14: 46245 | R14: Facial Pain Center PLLC | S14: 1407325830 | T14: Map | U14: Record
A15: Minnesota Head and Neck Pain Clinic, PA | B15: TMJ Specialists | D15: TMJ Clinic | E15: Cory Herman, DDS, MS; James Fricton, DDS, MS; Pathamas Mittman, DDS, MS; Preetanjali Thakur, BDS, MS | F15: 3475 Plymouth Blvd | G15: Ste 200 | H15: Plymouth | I15: Hennepin | J15: Twin Cities Metro | K15: 55447 | L15: (763) 577-2484 | M15: mhnpc.com | N15: Confirmed | O15: 3 | P15: No | Q15: 45490 | R15: Minnesota Head and Neck Pain Clinic, PA | S15: 1871975607 | T15: Map | U15: Record
A16: The Facial Pain Center | B16: TMJ Specialists | D16: Orofacial Pain, TMJ Clinic, TMJ Treatment | E16: Patricia Boettner, DDS, MS | F16: 1835 County Road C W | G16: Ste 200 | H16: Roseville | I16: Ramsey | J16: Twin Cities Metro | K16: 55113 | L16: (651) 636-2016 | M16: thefacialpaincenter.com | N16: Confirmed | O16: 1 | P16: No | Q16: 46245 | R16: Facial Pain Center PLLC | S16: 1407325830 | T16: Map | U16: Record
A17: HealthPartners St. Paul (Wabasha) Dental Clinic | B17: TMJ Specialists | C17: Oral Surgery | D17: Orofacial Pain, Oral & Maxillofacial Surgery | F17: 205 Wabasha St S | H17: St. Paul | I17: Ramsey | J17: Twin Cities Metro | K17: 55107 | L17: (651) 254-7373 | M17: healthpartners.com | N17: Confirmed | O17: 0 | P17: No | Q17: 46248 | R17: Group Health, INC. | S17: 1952042053 | T17: Map | U17: Record
A18: Minnesota Craniofacial Center for TMJ & Sleep Treatment | B18: TMJ Specialists | D18: TMJ Clinic | E18: Roy Hakala, DDS; Kim Ledermann | F18: 2550 University Ave W | G18: Ste 143N | H18: St. Paul | I18: Ramsey | J18: Twin Cities Metro | K18: 55114 | L18: (651) 642-1013 | M18: mncranio.com | N18: Confirmed | O18: 4 | P18: No | Q18: 41543 | R18: Minnesota Craniofacial Center Midway, PA. | S18: 1285757864 | T18: Map | U18: Record
A19: Minnesota Head and Neck Pain Clinic, PA | B19: TMJ Specialists | D19: TMJ Clinic | E19: James Fricton, DDS; Pathamas Mittman, DDS, MS; Preetanjali Thakur, BDS | F19: 2550 University Ave W | G19: Ste 189S | H19: St. Paul | I19: Ramsey | J19: Twin Cities Metro | K19: 55114 | L19: (651) 332-7474 | M19: mhnpc.com | N19: Confirmed | O19: 4 | P19: No | Q19: 45490 | R19: Minnesota Head and Neck Pain Clinic, PA | S19: 1104850155 | T19: Map | U19: Record
A20: TMJ & Sleep Therapy Centre of St. Paul (at Smiles of Distinction Dentistry) | B20: TMJ Specialists | D20: TMJ Treatment | E20: Bart Schultz, DDS | F20: 4300 Egan Dr | H20: Savage | I20: Scott | J20: Twin Cities Metro | K20: 55378 | L20: (952) 894-2545 | M20: tmjandsleeptherapycentreofminnesota.com | N20: Confirmed | O20: 0 | P20: No | R20: TMJ & Sleep Therapy Centre of St. Paul (at Smiles of Distinction Dentistry) | T20: Map | U20: Web
A21: The Facial Pain Center | B21: TMJ Specialists | D21: Orofacial Pain | E21: Davina Kumar, DMD, MS | F21: 4155 Dean Lakes Blvd | H21: Shakopee | I21: Scott | J21: Twin Cities Metro | K21: 55379 | L21: (952) 926-3858 | M21: thefacialpaincenter.com | N21: Confirmed | O21: 1 | P21: No | Q21: 45545 | R21: Davina Kumar, DMD | S21: 1043839574 | T21: Map | U21: Record
A22: Ross Orthodontics (Dr. Gregory Ross) | B22: TMJ Specialists | D22: TMJ Treatment | F22: 368 Lake St S | G22: Ste 101 | H22: Forest Lake | I22: Washington | J22: Twin Cities Metro | K22: 55025 | L22: (651) 464-6988 | M22: my.officite.com | N22: Confirmed | O22: 0 | P22: No | Q22: 45295 | R22: Rossodontics Dental Sleep Medicine | S22: 1588094171 | T22: Map | U22: Record
A23: HealthPartners TMD Lake Elmo | B23: TMJ Specialists | D23: Orofacial Pain, TMJ Clinic | E23: Darrell Boychuk, DDS, MS | F23: 8515 Eagle Point Blvd | G23: Ste 200 | H23: Lake Elmo | I23: Washington | J23: Twin Cities Metro | K23: 55042 | L23: (651) 523-9951 | M23: healthpartners.com | N23: Confirmed | O23: 0 | P23: No | Q23: 46240 | R23: Group Health, INC. | S23: 1811288269 | T23: Map | U23: Record
A24: Carlson Dental Group | B24: TMJ Specialists | D24: TMJ Treatment | E24: Sarah Carlson, DDS | F24: 1701 Curve Crest Blvd W | G24: Ste 100 | H24: Stillwater | I24: Washington | J24: Twin Cities Metro | K24: 55082 | L24: (651) 439-8840 | M24: stillwaterbeautifulsmiles.com | N24: Confirmed | O24: 0 | P24: No | Q24: 44992 | R24: Carlson Distinctive Dentistry, PLLC | S24: 1598243990 | T24: Map | U24: Record
A25: Minnesota Head and Neck Pain Clinic, PA | B25: TMJ Specialists | D25: Orofacial Pain, TMJ Clinic | F25: 9950 Valley Creek Rd | G25: Ste 100 | H25: Woodbury | I25: Washington | J25: Twin Cities Metro | K25: 55125 | L25: (651) 332-7474 | M25: mhnpc.com | N25: Confirmed | O25: 0 | P25: No | Q25: 46252 | R25: Minnesota Head and Neck Pain Clinic, PA | S25: 1710854369 | T25: Map | U25: Record
A26: The Facial Pain Center | B26: TMJ Specialists | D26: TMJ Treatment | E26: Patricia Fernandes Boettner, DDS, MS | F26: 241 Radio Dr | H26: Woodbury | I26: Washington | J26: Twin Cities Metro | K26: 55125 | L26: (651) 636-2016 | M26: thefacialpaincenter.com | N26: Confirmed | O26: 0 | P26: No | Q26: 46245 | R26: Facial Pain Center PLLC | S26: 1407325830 | T26: Map | U26: Record
A27: Hanson Dental | B27: TMJ Specialists | D27: TMJ Treatment | F27: 1100 Highway 25 North | G27: Ste 1 | H27: Buffalo | I27: Wright | J27: Twin Cities Metro | K27: 55313 | L27: (763) 682-9796 | M27: hansondental.com | N27: Confirmed | O27: 0 | P27: No | Q27: 39729 | R27: Thomas M Hanson Dds PA | S27: 1871663831 | T27: Map | U27: Record
A28: MN Center for Dental Care | B28: TMJ Specialists | D28: TMJ Treatment | E28: Paul Sheils, DDS | F28: 9075 Quaday Ave NE | G28: Ste 102 | H28: Otsego | I28: Wright | J28: Twin Cities Metro | K28: 55330 | L28: (763) 972-0440 | M28: mncenterfordentalcare.com | N28: Confirmed | O28: 0 | P28: No | Q28: 45483 | R28: Minnesota Dental Implants | S28: 1386312411 | T28: Map | U28: Record
A29: Minnesota Head & Neck Pain Clinic | B29: TMJ Specialists | D29: Orofacial Pain, TMJ Clinic | E29: Pathamas Mittman, DDS, MS | F29: 622 Roosevelt Rd | H29: St. Cloud | I29: Stearns | J29: Central Minnesota | K29: 56301 | L29: (763) 233-7252 | M29: mhnpc.com | N29: Confirmed | O29: 1 | P29: No | Q29: 45490 | R29: Minnesota Head and Neck Pain Clinic, PA | S29: 1003316852 | T29: Map | U29: Record
A30: Riverfront Dental | B30: TMJ Specialists | D30: TMJ Treatment | E30: Grant Colling, DDS | F30: 124 E Lincoln Ave | H30: Fergus Falls | I30: Otter Tail | J30: West Central Minnesota | K30: 56537 | L30: (218) 736-5627 | N30: New address | O30: 0 | P30: No | Q30: 45257 | R30: Scott Wagnild Dds,llc | S30: 1033723309 | T30: Map | U30: Record
A31: Hyland Dental | B31: TMJ Specialists | D31: TMJ Treatment | E31: Amanda Hyland, DDS | F31: 810 Independence Dr | H31: Mankato | I31: Blue Earth | J31: South Central Minnesota | K31: 56001 | L31: (507) 387-3249 | M31: hylanddental.net | N31: Confirmed | O31: 0 | P31: No | Q31: 44916 | R31: Amanda L. Hyland D.d.s. PA | S31: 1780108209 | T31: Map | U31: Record
A32: Honor Dental | B32: TMJ Specialists | D32: TMJ Treatment | E32: Andrew Greenslade, DMD | F32: 2112 Viking Dr NW | H32: Rochester | I32: Olmsted | J32: Southeast Minnesota | K32: 55901 | L32: (507) 288-1101 | M32: honordentalrochester.com | N32: Confirmed | O32: 0 | P32: No | Q32: 45821 | R32: Honor Dental PLLC | S32: 1003702408 | T32: Map | U32: Record
A33: Mayo Clinic – Orofacial Pain (Dental Specialties) | B33: TMJ Specialists | D33: Orofacial Pain | E33: Subha Giri, BDS, MS | F33: 200 1st St SW | H33: Rochester | I33: Olmsted | J33: Southeast Minnesota | K33: 55905 | L33: (507) 284-2511 | M33: mayoclinic.org | N33: Confirmed | O33: 1 | P33: Yes | Q33: 45383 | R33: Imran Patel | S33: 1780066282 | T33: Map | U33: Record
A34: Respira | B34: TMJ Specialists | D34: TMJ Treatment | E34: Ryan Henrichsen, DDS, MAGD | F34: 1309 Salem Rd SW | H34: Rochester | I34: Olmsted | J34: Southeast Minnesota | K34: 55902 | L34: (507) 701-1127 | M34: respirawell.com | N34: Confirmed | O34: 0 | P34: No | Q34: 45965 | R34: Respira, LTD | S34: 1255928917 | T34: Map | U34: Record

Sheet Oral Surgery
A1: Clinic Name | B1: Specialty Group | C1: Also In | D1: Specialties | E1: Oral Surgeons Here | F1: Street | G1: Suite | H1: City | I1: County | J1: Region | K1: ZIP | L1: Phone | M1: Website | N1: Web Check | O1: Treats TMJ | P1: Providers at Address | Q1: On Xpert Connect | R1: Registry Updated | S1: Legal Name | T1: NPI | U1: Map | V1: NPPES Record
A2: Metro Dentalcare Blaine 10 | B2: Oral Surgery | D2: Oral & Maxillofacial Surgery | F2: 261 County Road 10 NE | G2: Ste 10 | H2: Blaine | I2: Anoka | J2: Twin Cities Metro | K2: 55434 | L2: (763) 786-9644 | N2: Confirmed | P2: 0 | Q2: No | R2: 44642 | S2: Family Oral Surgery Specialists, PLC | T2: 1730838186 | U2: Map | V2: Record
A3: OMS Specialists | B3: Oral Surgery | D3: Oral & Maxillofacial Surgery | F3: 11855 Ulysses Street NE | G3: 130 | H3: Blaine | I3: Anoka | J3: Twin Cities Metro | K3: 55434 | L3: (763) 757-2220 | M3: omsspecialists.com | N3: New address | O3: Yes | P3: 0 | Q3: No | R3: 41849 | S3: Oral & Maxillofacial Surgery Specialists, PA | T3: 1467563510 | U3: Map | V3: Record
A4: Associated Oral & Maxillofacial Surgeons (Associated OMS) | B4: Oral Surgery | D4: Oral & Maxillofacial Surgery | F4: 3833 Coon Rapids Blvd NW | H4: Coon Rapids | I4: Anoka | J4: Twin Cities Metro | K4: 55433 | L4: (763) 421-6271 | M4: associatedoms.com | N4: Confirmed | O4: Yes | P4: 1 | Q4: No | R4: 45441 | S4: MN Dental Service Providers LLC | T4: 1649043662 | U4: Map | V4: Record
A5: Northside Minnesota Oral and Maxillofacial Surgeons, PLLC | B5: Oral Surgery | D5: Oral & Maxillofacial Surgery | F5: 11441 Osage St NW | H5: Coon Rapids | I5: Anoka | J5: Twin Cities Metro | K5: 55433 | L5: (763) 862-6442 | M5: northsideoms.com | N5: Confirmed | P5: 1 | Q5: No | R5: 44369 | S5: Northside Minnesota Oral and Maxillofacial Surgeons, PLLC | T5: 1245809458 | U5: Map | V5: Record
A6: The Dental Specialists - Coon Rapids / Riverdale | B6: Oral Surgery | D6: Oral & Maxillofacial Surgery | F6: 3360 Northdale Blvd. | H6: Coon Rapids | I6: Anoka | J6: Twin Cities Metro | K6: 55448 | L6: (763) 233-3390 | M6: thedentalspecialists.com | N6: Confirmed | O6: No | P6: 0 | Q6: No | R6: 44763 | S6: Dental Specialists of Minnesota, PLLC | T6: 1396095048 | U6: Map | V6: Record
A7: The Dental Specialists - Coon Rapids Riverdale | B7: Oral Surgery | D7: Oral & Maxillofacial Surgery | F7: 3360 Northdale Blvd NW | H7: Coon Rapids | I7: Anoka | J7: Twin Cities Metro | K7: 55448 | L7: (763) 201-6962 | M7: thedentalspecialists.com | N7: New address | O7: No | P7: 0 | Q7: No | R7: 44132 | S7: Dental Specialists of Minnesota, PLLC | T7: 1518200286 | U7: Map | V7: Record
A8: OMS Specialists | B8: Oral Surgery | D8: Oral & Maxillofacial Surgery | F8: 490 S Maple St | G8: Ste 102 | H8: Waconia | I8: Carver | J8: Twin Cities Metro | K8: 55387 | L8: (952) 442-5448 | M8: omsspecialists.com | N8: Confirmed | O8: Yes | P8: 1 | Q8: No | R8: 41849 | S8: Oral & Maxillofacial Surgery Specialists, PA | T8: 1770694812 | U8: Map | V8: Record
A9: Twin Cities Oral & Maxillofacial Surgery | B9: Oral Surgery | D9: Oral & Maxillofacial Surgery | F9: 14635 Pennock Ave | G9: #250 | H9: Apple Valley | I9: Dakota | J9: Twin Cities Metro | K9: 55124 | L9: (952) 432-1514 | M9: tcoralsurgery.com | N9: Confirmed | P9: 0 | Q9: No | R9: 44065 | S9: Twin Cities Oral & Maxillofacial Surgery PA | T9: 1821299041 | U9: Map | V9: Record
A10: Metro Dentalcare Specialty Center Burnsville - Oral Surgery | B10: Oral Surgery | D10: Oral & Maxillofacial Surgery | F10: 14344 Burnhaven Dr | H10: Burnsville | I10: Dakota | J10: Twin Cities Metro | K10: 55306 | L10: (612) 638-1238 | M10: mdscburnsvilleoralsurgery.com | N10: Confirmed | O10: No | P10: 1 | Q10: No | R10: 44642 | S10: Family Oral Surgery Specialists, PLC | T10: 1407505829 | U10: Map | V10: Record
A11: South Suburban Oral & Maxillofacial Surgeons LTD | B11: Oral Surgery | D11: Oral & Maxillofacial Surgery | F11: 625 East Nicollet Boulevard | G11: Ste 205 | H11: Burnsville | I11: Dakota | J11: Twin Cities Metro | K11: 55337 | L11: (952) 435-0310 | N11: Confirmed | P11: 0 | Q11: No | R11: 44065 | S11: South Suburban Oral & Maxillofacial Surgeons LTD | T11: 1134103674 | U11: Map | V11: Record
A12: The Dental Specialists | B12: Oral Surgery | D12: Oral & Maxillofacial Surgery | F12: 40 W Nicollet Blvd | H12: Burnsville | I12: Dakota | J12: Twin Cities Metro | K12: 55337 | L12: (952) 241-5901 | M12: thedentalspecialists.com | N12: Confirmed | O12: No | P12: 0 | Q12: No | R12: 44132 | S12: Dental Specialists of Minnesota, PLLC | T12: 1508932344 | U12: Map | V12: Record
A13: Twin Cities Oral & Maxillofacial Surgery PA. | B13: Oral Surgery | D13: Oral & Maxillofacial Surgery | F13: 925 Highway 55 | G13: 202 | H13: Hastings | I13: Dakota | J13: Twin Cities Metro | K13: 55033 | L13: (651) 437-3262 | M13: tcoralsurgery.com | N13: Confirmed | O13: Yes | P13: 0 | Q13: No | R13: 39771 | S13: Twin Cities Oral & Maxillofacial Surgery PA. | T13: 1083792279 | U13: Map | V13: Record
A14: Advanced Oral Surgery & Periodontics | B14: Oral Surgery | D14: Oral & Maxillofacial Surgery | F14: 19925 Idealic Ave | H14: Lakeville | I14: Dakota | J14: Twin Cities Metro | K14: 55044 | L14: (952) 683-9884 | M14: advancedoralsurgerymn.com | N14: Confirmed | O14: No | P14: 0 | Q14: No | R14: 43356 | S14: Advanced Oral Surgery | T14: 1295218303 | U14: Map | V14: Record
A15: Dakota Valley Oral and Maxillofacial Surgery, PLLC | B15: Oral Surgery | D15: Oral & Maxillofacial Surgery | E15: Cassandra Stacy, DMD | F15: 2130 Cliff Rd | G15: Ste 100 | H15: St. Paul | I15: Dakota | J15: Twin Cities Metro | K15: 55122 | L15: (651) 452-6933 | M15: dakotavalley-oms.com | N15: Confirmed | O15: No | P15: 3 | Q15: No | R15: 44018 | S15: Dakota Valley Oral and Maxillofacial Surgery, PLLC | T15: 1366568206 | U15: Map | V15: Record
A16: Oral and Maxillofacial Surgical Consultants PA | B16: Oral Surgery | D16: Oral & Maxillofacial Surgery | F16: 7770 Dell Road | G16: Ste 100 | H16: Chanhassen | I16: Hennepin | J16: Twin Cities Metro | K16: 55317 | L16: (952) 975-0605 | M16: omscmn.com | N16: Confirmed | O16: Yes | P16: 0 | Q16: No | R16: 42180 | S16: Oral and Maxillofacial Surgical Consultants PA | T16: 1720206428 | U16: Map | V16: Record
A17: EOS Expert Oral Surgery | B17: Oral Surgery | D17: Oral & Maxillofacial Surgery | F17: 11800 Singletree Ln | G17: Ste 404 | H17: Eden Prairie | I17: Hennepin | J17: Twin Cities Metro | K17: 55344 | L17: (952) 452-9151 | M17: eosoralsurgery.com | N17: Confirmed | O17: Yes | P17: 0 | Q17: No | R17: 44896 | S17: Midwest Oral & Facial Surgery PLLC | T17: 1063122976 | U17: Map | V17: Record
A18: HealthPartners Dental Clinic Eden Prairie | B18: Oral Surgery | D18: Oral & Maxillofacial Surgery | F18: 8455 Flying Cloud Dr | H18: Eden Prairie | I18: Hennepin | J18: Twin Cities Metro | K18: 55344 | L18: (952) 883-9040 | M18: healthpartners.com | N18: Confirmed | O18: No | P18: 0 | Q18: No | R18: 46248 | S18: Group Health, INC. | T18: 1164959938 | U18: Map | V18: Record
A19: Oral and Maxillofacial Surgical Consultants PA | B19: Oral Surgery | D19: Oral & Maxillofacial Surgery | E19: James Omlie, DDS | F19: 7373 France Ave S | G19: Ste 602 | H19: Edina | I19: Hennepin | J19: Twin Cities Metro | K19: 55435 | L19: (952) 835-5003 | M19: omscmn.com | N19: Confirmed | O19: Yes | P19: 9 | Q19: No | R19: 42180 | S19: Oral and Maxillofacial Surgical Consultants PA | T19: 1619049921 | U19: Map | V19: Record
A20: The Dental Specialists | B20: Oral Surgery | D20: Oral & Maxillofacial Surgery | F20: 6545 France Ave S | G20: Ste 366 | H20: Edina | I20: Hennepin | J20: Twin Cities Metro | K20: 55435 | L20: (952) 241-5863 | M20: thedentalspecialists.com | N20: Confirmed | O20: No | P20: 1 | Q20: No | R20: 44132 | S20: Dental Specialists of Minnesota, PLLC | T20: 1376619114 | U20: Map | V20: Record
A21: Zoya's Orofacial Pain and Dental Sleep Remedies PLLC | B21: TMJ Specialists | C21: Oral Surgery | D21: Orofacial Pain, TMJ Clinic, TMJ Treatment, Oral & Maxillofacial Surgery | E21: Mariam Siddiqui, BDS, MS | F21: 1405 Lilac Lane Drive North | G21: Ste 150 K | H21: Golden Valley | I21: Hennepin | J21: Twin Cities Metro | K21: 55422 | L21: (763) 762-6549 | M21: zoyaorofacialpaindentalsleep.org | N21: Confirmed | O21: Yes | P21: 1 | Q21: No | R21: 44721 | S21: Zoya's Orofacial Pain and Dental Sleep Remedies PLLC | T21: 1306513023 | U21: Map | V21: Record
A22: Associated Oral & Maxillofacial Surgeons | B22: Oral Surgery | D22: Oral & Maxillofacial Surgery | F22: 12000 Elm Creek Blvd N | H22: Maple Grove | I22: Hennepin | J22: Twin Cities Metro | K22: 55369 | L22: (763) 416-9990 | M22: associatedoms.com | N22: Confirmed | O22: Yes | P22: 1 | Q22: No | R22: 45231 | S22: MN Dental Service Providers LLC | T22: 1649043662 | U22: Map | V22: Record
A23: OMS Specialists | B23: Oral Surgery | D23: Oral & Maxillofacial Surgery | F23: 13950 Grove Dr | G23: #100 | H23: Maple Grove | I23: Hennepin | J23: Twin Cities Metro | K23: 55311 | L23: (763) 494-8825 | M23: omsspecialists.com | N23: New address | O23: Yes | P23: 0 | Q23: No | R23: 41849 | S23: Oral & Maxillofacial Surgery Specialists, PA | T23: 1902917057 | U23: Map | V23: Record
A24: The Dental Specialists - Maple Grove | B24: Oral Surgery | D24: Oral & Maxillofacial Surgery | F24: 15701 Grove Circle N | H24: Maple Grove | I24: Hennepin | J24: Twin Cities Metro | K24: 55369 | L24: (763) 233-3321 | M24: thedentalspecialists.com | N24: New address | O24: No | P24: 0 | Q24: No | R24: 44132 | S24: Dental Specialists of Minnesota, PLLC | T24: 1912143843 | U24: Map | V24: Record
A25: University of Minnesota Dental Clinics – Oral & Maxillofacial Surgery | B25: Oral Surgery | D25: Oral & Maxillofacial Surgery | F25: 515 Delaware St SE | G25: 7TH Floor Moos Tower | H25: Minneapolis | I25: Hennepin | J25: Twin Cities Metro | K25: 55455 | L25: (612) 626-6529 | N25: Confirmed | P25: 24 | Q25: No | R25: 42725 | S25: Regents of the University of Minnesota | T25: 1164763629 | U25: Map | V25: Record
A26: Facial Designs, P.A. | B26: Oral Surgery | D26: Oral & Maxillofacial Surgery | F26: 11601 Minnetonka Mills Rd | H26: Minnetonka | I26: Hennepin | J26: Twin Cities Metro | K26: 55305 | L26: (952) 935-8420 | M26: facial-designs.com | N26: Confirmed | O26: Yes | P26: 3 | Q26: No | R26: 45547 | S26: Affiliated Oral and Maxillofacial Surgeons PA. | T26: 1679620801 | U26: Map | V26: Record
A27: Wise Decision Wisdom Teeth Specialists | B27: Oral Surgery | D27: Oral & Maxillofacial Surgery | F27: 10653 Wayzata Blvd | G27: Ste 200 | H27: Minnetonka | I27: Hennepin | J27: Twin Cities Metro | K27: 55305 | L27: (952) 952-1100 | M27: wisedecision.com | N27: Confirmed | O27: No | P27: 0 | Q27: No | R27: 45357 | S27: Wise Option Dental PLLC | T27: 1407613375 | U27: Map | V27: Record
A28: Minnesota Maxillofacial and Oral Consultants | B28: Oral Surgery | D28: Oral & Maxillofacial Surgery | F28: 15600 36th Ave N | G28: Ste 100 | H28: Plymouth | I28: Hennepin | J28: Twin Cities Metro | K28: 55446 | L28: (763) 559-7688 | M28: mnmax.com | N28: Confirmed | O28: Yes | P28: 0 | Q28: No | R28: 44065 | S28: Minnesota Maxillofacial and Oral Consultants | T28: 1417034661 | U28: Map | V28: Record
A29: HealthPartners Dental Clinic St. Louis Park | B29: Oral Surgery | D29: Oral & Maxillofacial Surgery | F29: 5500 Excelsior Blvd | H29: St. Louis Park | I29: Hennepin | J29: Twin Cities Metro | K29: 55416 | L29: (952) 853-9120 | M29: healthpartners.com | N29: Confirmed | O29: Yes | P29: 0 | Q29: No | R29: 46248 | S29: Group Health, INC. | T29: 1699272427 | U29: Map | V29: Record
A30: Northern Star Oral and Maxillofacial Surgery PLLC | B30: Oral Surgery | D30: Oral & Maxillofacial Surgery | F30: 1660 Highway 100 S | G30: Ste 145 | H30: St. Louis Park | I30: Hennepin | J30: Twin Cities Metro | K30: 55416 | L30: (952) 465-0105 | M30: northernstaroms.com | N30: New address | O30: No | P30: 0 | Q30: No | R30: 41813 | S30: Northern Star Oral and Maxillofacial Surgery PLLC | T30: 1699901140 | U30: Map | V30: Record
A31: Oral and Maxillofacial Surgical Consultants PA | B31: Oral Surgery | D31: Oral & Maxillofacial Surgery | F31: 250 Central Ave N | G31: Suite126 | H31: Wayzata | I31: Hennepin | J31: Twin Cities Metro | K31: 55391 | L31: (952) 475-2266 | M31: omscmn.com | N31: Confirmed | O31: Yes | P31: 0 | Q31: No | R31: 42180 | S31: Oral and Maxillofacial Surgical Consultants PA | T31: 1265650956 | U31: Map | V31: Record
A32: The Dental Specialists - Deephaven | B32: Oral Surgery | D32: Oral & Maxillofacial Surgery | F32: 18258 Minnetonka Blvd | G32: Ste 100 | H32: Wayzata | I32: Hennepin | J32: Twin Cities Metro | K32: 55391 | L32: (952) 241-5815 | M32: thedentalspecialists.com | N32: Confirmed | O32: No | P32: 0 | Q32: No | R32: 44041 | S32: Dental Specialist of Minnesota, PLLC | T32: 1568071199 | U32: Map | V32: Record
A33: OMS Specialists | B33: Oral Surgery | D33: Oral & Maxillofacial Surgery | F33: 1595 2nd Ave NE | G33: Ste 120 | H33: Cambridge | I33: Isanti | J33: Twin Cities Metro | K33: 55008 | L33: (763) 691-8827 | M33: omsspecialists.com | N33: Confirmed | O33: Yes | P33: 1 | Q33: No | R33: 41849 | S33: Oral & Maxillofacial Surgery Specialists, PA | T33: 1508160060 | U33: Map | V33: Record
A34: ClearChoice Dental Implant Center - Roseville | B34: Oral Surgery | D34: Oral & Maxillofacial Surgery | F34: 3130 Cleveland Ave N | H34: Arden Hills | I34: Ramsey | J34: Twin Cities Metro | K34: 55112 | L34: (651) 605-6944 | M34: clearchoice.com | N34: Confirmed | O34: No | P34: 0 | Q34: No | R34: 45748 | S34: Clearchoice Dental Implant Center | T34: 1538963590 | U34: Map | V34: Record
A35: Twin Cities Oral & Maxillofacial Surgery, PA | B35: Oral Surgery | D35: Oral & Maxillofacial Surgery | F35: 1655 Beam Ave | G35: Ste 208 | H35: Maplewood | I35: Ramsey | J35: Twin Cities Metro | K35: 55109 | L35: (651) 770-7703 | M35: tcoralsurgery.com | N35: Confirmed | O35: No | P35: 0 | Q35: No | R35: 44065 | S35: Twin Cities Oral & Maxillofacial Surgery, PA | T35: 1356542575 | U35: Map | V35: Record
A36: OMS Specialists | B36: Oral Surgery | D36: Oral & Maxillofacial Surgery | F36: 550 County Road D | G36: Ste 12 | H36: New Brighton | I36: Ramsey | J36: Twin Cities Metro | K36: 55421 | L36: (612) 788-9246 | M36: omsspecialists.com | N36: Confirmed | O36: Yes | P36: 0 | Q36: No | R36: 41849 | S36: Oral & Maxillofacial Surgery Specialists, PA | T36: 1982634010 | U36: Map | V36: Record
A37: Momenta Oral & Maxillofacial Surgery | B37: Oral Surgery | D37: Oral & Maxillofacial Surgery | E37: Emad Abdou, DDS | F37: 700 Village Center Dr | G37: Ste 170 | H37: North Oaks | I37: Ramsey | J37: Twin Cities Metro | K37: 55127 | L37: (651) 482-0065 | M37: momentaoms.com | N37: Confirmed | O37: Yes | P37: 2 | Q37: No | R37: 43628 | S37: Momenta, PC | T37: 1497814032 | U37: Map | V37: Record
A38: The Dental Specialists - Roseville | B38: Oral Surgery | D38: Oral & Maxillofacial Surgery | F38: 1835 County Road C-West | G38: Ste 200 | H38: Roseville | I38: Ramsey | J38: Twin Cities Metro | K38: 55113 | L38: (651) 760-3610 | M38: thedentalspecialists.com | N38: Confirmed | O38: No | P38: 0 | Q38: No | R38: 44132 | S38: Dental Specialists of Minnesota, PLLC | T38: 1780750539 | U38: Map | V38: Record
A39: Twin Cities Oral & Maxillofacial Surgery | B39: Oral Surgery | D39: Oral & Maxillofacial Surgery | F39: 1790 Lexington Ave N | H39: Roseville | I39: Ramsey | J39: Twin Cities Metro | K39: 55113 | L39: (651) 488-9884 | M39: tcoralsurgery.com | N39: Confirmed | O39: No | P39: 0 | Q39: No | R39: 44065 | S39: Twin Cities Oral & Maxillofaical Surgery PA | T39: 1154522373 | U39: Map | V39: Record
A40: HealthPartners Dental Specialty Center (Como) | B40: Oral Surgery | D40: Oral & Maxillofacial Surgery | F40: 2500 Como Ave | H40: St. Paul | I40: Ramsey | J40: Twin Cities Metro | K40: 55108 | L40: (651) 647-2500 | N40: Confirmed | O40: No | P40: 5 | Q40: No | R40: 46248 | S40: Group Health, INC. | T40: 1780739417 | U40: Map | V40: Record
A41: HealthPartners St. Paul (Wabasha) Dental Clinic | B41: TMJ Specialists | C41: Oral Surgery | D41: Orofacial Pain, Oral & Maxillofacial Surgery | F41: 205 Wabasha St S | H41: St. Paul | I41: Ramsey | J41: Twin Cities Metro | K41: 55107 | L41: (651) 254-7373 | M41: healthpartners.com | N41: Confirmed | O41: Yes | P41: 0 | Q41: No | R41: 46248 | S41: Group Health, INC. | T41: 1952042053 | U41: Map | V41: Record
A42: St. Paul Oral Surgery | B42: Oral Surgery | D42: Oral & Maxillofacial Surgery | F42: 2550 University Ave W | G42: Ste 115N | H42: St. Paul | I42: Ramsey | J42: Twin Cities Metro | K42: 55114 | L42: (651) 645-6429 | M42: stpauloralsurgery.com | N42: Confirmed | O42: Yes | P42: 3 | Q42: No | R42: 44683 | S42: St Paul Oral Surgery and Dental Implants LLC | T42: 1043870645 | U42: Map | V42: Record
A43: EOS Oral Surgery | B43: Oral Surgery | D43: Oral & Maxillofacial Surgery | E43: Jee Hyun Lyu, DDS | F43: 13875 Hwy 13 Frontage Rd | G43: Ste 50 | H43: Savage | I43: Scott | J43: Twin Cities Metro | K43: 55378 | L43: (952) 452-9151 | M43: eosoralsurgery.com | N43: Confirmed | O43: Yes | P43: 2 | Q43: No | R43: 44896 | S43: Midwest Oral & Facial Surgery PLLC | T43: 1063122976 | U43: Map | V43: Record
A44: EOS: Expert Oral Surgery | B44: Oral Surgery | D44: Oral & Maxillofacial Surgery | F44: 403 East First Avenue | H44: Shakopee | I44: Scott | J44: Twin Cities Metro | K44: 55379 | L44: (952) 452-9151 | M44: eosoralsurgery.com | N44: New address | O44: Yes | P44: 0 | Q44: No | R44: 44896 | S44: Midwest Oral & Facial Surgery PLLC | T44: 1063122976 | U44: Map | V44: Record
A45: Associated Oral & Maxillofacial Surgeons (Elk River) | B45: Oral Surgery | D45: Oral & Maxillofacial Surgery | F45: 501 Main St NW | H45: Elk River | I45: Sherburne | J45: Twin Cities Metro | K45: 55330 | L45: (763) 274-1092 | M45: associatedoms.com | N45: Confirmed | O45: Yes | P45: 1 | Q45: No | R45: 45231 | S45: MN Dental Service Providers LLC | T45: 1649043662 | U45: Map | V45: Record
A46: HealthPartners Dental Specialty Center Woodbury - Lake Elmo | B46: Oral Surgery | D46: Oral & Maxillofacial Surgery | E46: Krista Primley; Louis Christensen, DDS | F46: 8515 Eagle Point Blvd | H46: Lake Elmo | I46: Washington | J46: Twin Cities Metro | K46: 55042 | L46: (651) 523-9950 | N46: Confirmed | O46: No | P46: 2 | Q46: No | R46: 46248 | S46: Group Health, INC. | T46: 1093261190 | U46: Map | V46: Record
A47: Saint Croix Oral Surgery | B47: Oral Surgery | D47: Oral & Maxillofacial Surgery | E47: Martin Tahara, DMD, MD; Steven Johnson, DDS | F47: 1701 Curve Crest Blvd W | G47: Ste 108 | H47: Stillwater | I47: Washington | J47: Twin Cities Metro | K47: 55082 | L47: (651) 439-8030 | N47: Confirmed | P47: 2 | Q47: No | R47: 44065 | S47: St Croix Oral, Maxillofacial & Implant Surgery, PA. | T47: 1427129717 | U47: Map | V47: Record
A48: The Oral Surgery Center | B48: Oral Surgery | D48: Oral & Maxillofacial Surgery | F48: 2850 Curve Crest Blvd | G48: Ste 130 | H48: Stillwater | I48: Washington | J48: Twin Cities Metro | K48: 55082 | L48: (651) 233-2141 | M48: theoralsurgerycenter.com | N48: Confirmed | O48: Yes | P48: 0 | Q48: No | R48: 40471 | S48: Great Lakes Oral & Maxillofacial Surgery, PA. | T48: 1508058322 | U48: Map | V48: Record
A49: The Dental Specialists - Woodbury | B49: Oral Surgery | D49: Oral & Maxillofacial Surgery | F49: 241 Radio Drive | G49: A | H49: Woodbury | I49: Washington | J49: Twin Cities Metro | K49: 55125 | L49: (651) 760-3661 | M49: thedentalspecialists.com | N49: New address | O49: No | P49: 0 | Q49: No | R49: 43858 | S49: Dental Specialists of Minnesota, PLLC | T49: 1346316189 | U49: Map | V49: Record
A50: The Oral Surgery Center | B50: Oral Surgery | D50: Oral & Maxillofacial Surgery | E50: Emily Snodgrass, DDS | F50: 748 Bielenberg Drive | G50: Ste 160 | H50: Woodbury | I50: Washington | J50: Twin Cities Metro | K50: 55125 | L50: (651) 233-2140 | M50: theoralsurgerycenter.com | N50: Confirmed | O50: Yes | P50: 2 | Q50: No | R50: 44827 | S50: The Oral Surgery Center | T50: 1104864529 | U50: Map | V50: Record
A51: True North Oral Surgery & Implants | B51: Oral Surgery | D51: Oral & Maxillofacial Surgery | E51: Marshall Wade, DDS; Paul Vollmer, DDS | F51: 9950 Valley Creek Rd | G51: Ste 100 | H51: Woodbury | I51: Washington | J51: Twin Cities Metro | K51: 55125 | L51: (651) 578-7000 | M51: truenorthoralsurgery.com | N51: Confirmed | O51: No | P51: 4 | Q51: No | R51: 42837 | S51: Maplewood Oral and Maxillofacial Surgery, PA. | T51: 1003993304 | U51: Map | V51: Record
A52: Associated Oral & Maxillofacial Surgeons | B52: Oral Surgery | D52: Oral & Maxillofacial Surgery | F52: 215 Highway 55 E | H52: Buffalo | I52: Wright | J52: Twin Cities Metro | K52: 55313 | L52: (763) 682-3410 | M52: associatedoms.com | N52: Confirmed | O52: Yes | P52: 1 | Q52: No | R52: 45231 | S52: MN Dental Service Providers LLC | T52: 1649043662 | U52: Map | V52: Record
A53: Associated Oral & Maxillofacial Surgeons (Associated OMS) | B53: Oral Surgery | D53: Oral & Maxillofacial Surgery | F53: 114 W 3rd St | H53: Monticello | I53: Wright | J53: Twin Cities Metro | K53: 55362 | L53: (763) 271-6770 | M53: associatedoms.com | N53: Confirmed | O53: Yes | P53: 1 | Q53: No | R53: 45231 | S53: MN Dental Service Providers LLC | T53: 1649043662 | U53: Map | V53: Record
A54: Minnesota Oral & Facial Surgery | B54: Oral Surgery | D54: Oral & Maxillofacial Surgery | F54: 2380 Troop Drive | G54: Ste 202 | H54: Sartell | I54: Stearns | J54: Central Minnesota | K54: 56377 | L54: (320) 257-9555 | M54: mnofs.com | N54: Confirmed | O54: Yes | P54: 1 | Q54: No | R54: 44065 | S54: Central Lakes Oral & Facial Surgery | T54: 1386723575 | U54: Map | V54: Record
A55: Centrasota Oral Surgeons | B55: Oral Surgery | D55: Oral & Maxillofacial Surgery | E55: Donald Primley, DDS, MS; Eric Stine, DDS, MS; Griffin Sonstegard, DDS; Harold Machesky, DDS, MS; Nicholas Kenning, DDS, MD; Sean Welander, DDS | F55: 3950 Veterans Dr | G55: Ste 100 | H55: St. Cloud | I55: Stearns | J55: Central Minnesota | K55: 56303 | L55: (320) 252-3611 | M55: centrasotaoms.com | N55: Confirmed | O55: Yes | P55: 11 | Q55: No | R55: 44065 | S55: Centrasota Oral & Maxillofacial Surgeons, PA. | T55: 1598710477 | U55: Map | V55: Record
A56: Oral and Maxillofacial Surgery Associates, LTD | B56: Oral Surgery | D56: Oral & Maxillofacial Surgery | F56: 1903 S 6th St | G56: Ste 4 | H56: Brainerd | I56: Crow Wing | J56: Northeast Minnesota | K56: 56401 | L56: (218) 829-1728 | M56: omsabrainerd.com | N56: Confirmed | O56: Yes | P56: 4 | Q56: No | R56: 39455 | S56: Oral and Maxillofacial Surgery Associates, LTD | T56: 1942382379 | U56: Map | V56: Record
A57: Blue Water Oral and Facial Surgery | B57: Oral Surgery | D57: Oral & Maxillofacial Surgery | F57: 303 SE 1st St | H57: Grand Rapids | I57: Itasca | J57: Northeast Minnesota | K57: 55744 | L57: (218) 326-0349 | M57: bluewateroral.surgery | N57: Confirmed | O57: Yes | P57: 0 | Q57: No | R57: 45694 | S57: Oral and Maxillofacial Surgical Associates PA | T57: 1679668529 | U57: Map | V57: Record
A58: Blue Water Oral and Facial Surgery | B58: Oral Surgery | D58: Oral & Maxillofacial Surgery | E58: Eric Scotland, DDS; Scott Varland, DDS | F58: 1000 E 1st St | G58: Ste 108 | H58: Duluth | I58: St. Louis | J58: Northeast Minnesota | K58: 55805 | L58: (218) 722-1854 | M58: bluewateroral.surgery | N58: Confirmed | O58: Yes | P58: 6 | Q58: No | R58: 45694 | S58: Oral and Maxillofacial Surgical Associates PA | T58: 1104911056 | U58: Map | V58: Record
A59: Northern Oral Surgery & Implant Center | B59: Oral Surgery | D59: Oral & Maxillofacial Surgery | E59: Mark Ash, DDS | F59: 3617 W Arrowhead Rd | H59: Duluth | I59: St. Louis | J59: Northeast Minnesota | K59: 55811 | L59: (218) 722-8377 | M59: northernoralsurgeons.com | N59: Confirmed | O59: Yes | P59: 6 | Q59: No | R59: 39512 | S59: Northern Oral & Maxillofacial Surgeons, PA | T59: 1457401820 | U59: Map | V59: Record
A60: Northern Oral & Maxillofacial Surgeons, PA | B60: Oral Surgery | D60: Oral & Maxillofacial Surgery | F60: 3899 Highway 73 | G60: Ste 5-6 | H60: Hibbing | I60: St. Louis | J60: Northeast Minnesota | K60: 55746 | L60: (218) 293-0691 | N60: New address | P60: 1 | Q60: No | R60: 39512 | S60: Northern Oral & Maxillofacial Surgeons, PA | T60: 1588715163 | U60: Map | V60: Record
A61: Blue Water Oral and Facial Surgery | B61: Oral Surgery | D61: Oral & Maxillofacial Surgery | F61: 505 S 12th Ave W | G61: Ste 2 | H61: Virginia | I61: St. Louis | J61: Northeast Minnesota | K61: 55792 | L61: (218) 741-0894 | M61: bluewateroral.surgery | N61: Confirmed | O61: Yes | P61: 0 | Q61: No | R61: 45694 | S61: Oral and Maxillofacial Surgical Associates PA | T61: 1417042367 | U61: Map | V61: Record
A62: Soderholm Oral Surgery and Implants | B62: Oral Surgery | D62: Oral & Maxillofacial Surgery | E62: Andrew Soderholm, DDS | F62: 120 12th Ave E | H62: Alexandria | I62: Douglas | J62: West Central Minnesota | K62: 56308 | L62: (320) 298-1000 | M62: soderholmoralsurgery.com | N62: Confirmed | O62: No | P62: 1 | Q62: No | R62: 44998 | S62: Soderholm Oral Surgery and Implants | T62: 1841991262 | U62: Map | V62: Record
A63: Soderholm Oral Surgery and Implants | B63: Oral Surgery | D63: Oral & Maxillofacial Surgery | F63: 215 N Tower Rd | H63: Fergus Falls | I63: Otter Tail | J63: West Central Minnesota | K63: 56537 | L63: (320) 298-1000 | M63: soderholmoralsurgery.com | N63: Confirmed | O63: No | P63: 0 | Q63: No | R63: 44998 | S63: Soderholm Oral Surgery and Implants | T63: 1841991262 | U63: Map | V63: Record
A64: Soderholm Oral Surgery and Implants | B64: Oral Surgery | D64: Oral & Maxillofacial Surgery | F64: 940 Market St | H64: Perham | I64: Otter Tail | J64: West Central Minnesota | K64: 56573 | L64: (320) 298-1000 | M64: soderholmoralsurgery.com | N64: Confirmed | O64: No | P64: 0 | Q64: No | R64: 44998 | S64: Soderholm Oral Surgery and Implants | T64: 1841991262 | U64: Map | V64: Record
A65: Southeastern Minnesota Oral & Maxillofacial Surgery Associates, PLLC | B65: Oral Surgery | D65: Oral & Maxillofacial Surgery | E65: Courtney Anderson, DDS | F65: 1410 Madison Ave | H65: Mankato | I65: Blue Earth | J65: South Central Minnesota | K65: 56001 | L65: (507) 344-8698 | M65: semoms.com | N65: Confirmed | O65: Yes | P65: 1 | Q65: No | R65: 46295 | S65: Southeastern Minnesota Oral & Maxillofacial Surgery Associates, PLLC | T65: 1659492312 | U65: Map | V65: Record
A66: Psimos Oral Surgery | B66: Oral Surgery | D66: Oral & Maxillofacial Surgery | F66: 1101 N Broadway | H66: Rochester | I66: Olmsted | J66: Southeast Minnesota | K66: 55906 | L66: (507) 288-0126 | M66: psimosoralsurgery.com | N66: Confirmed | O66: No | P66: 1 | Q66: No | R66: 40680 | S66: Nicholas H. Psimos, Dds, PLC | T66: 1770533531 | U66: Map | V66: Record
A67: Southeastern Minnesota Oral & Maxillofacial Surgery Associates, PLLC | B67: Oral Surgery | D67: Oral & Maxillofacial Surgery | E67: Dietrich Lawrenz, MD DDS | F67: 2519 Commerce Dr NW | G67: Ste 110 | H67: Rochester | I67: Olmsted | J67: Southeast Minnesota | K67: 55901 | L67: (507) 281-5000 | M67: semoms.com | N67: Confirmed | O67: Yes | P67: 1 | Q67: No | R67: 46295 | S67: Southeastern Minnesota Oral & Maxillofacial Surgery Associates, PLLC | T67: 1659492312 | U67: Map | V67: Record
A68: Oral and Maxillofacial Surgery of Minnesota PLLC | B68: Oral Surgery | D68: Oral & Maxillofacial Surgery | F68: 1029 19th Ave SW | H68: Willmar | I68: Kandiyohi | J68: Southwest Minnesota | K68: 56201 | L68: (320) 235-1803 | N68: Unverified | P68: 2 | Q68: No | R68: 45224 | S68: Oral and Maxillofacial Surgery of Minnesota PLLC | T68: 1942072871 | U68: Map | V68: Record

Sheet Older Entries
A1: Clinic Name | B1: Specialty Group | C1: Also In | D1: Specialties | E1: Street | F1: Suite | G1: City | H1: County | I1: Region | J1: ZIP | K1: Phone | L1: Providers at Address | M1: On Xpert Connect | N1: Registry Updated | O1: Legal Name | P1: NPI | Q1: Map | R1: NPPES Record
A2: Abeler Chiropractic of Andover, PA. | B2: Chiropractic | D2: Chiropractic | E2: 2705 Bunker Lake Blvd NW | F2: Ste 112 | G2: Andover | H2: Anoka | I2: Twin Cities Metro | J2: 55304 | K2: (763) 754-2500 | L2: 1 | M2: No | N2: 42181 | O2: Abeler Chiropractic of Andover, PA. | P2: 1396864732 | Q2: Map | R2: Record
A3: Andover Family Chiropractic PA | B3: Chiropractic | D3: Chiropractic | E3: 1573 154th Ave NW | G3: Andover | H3: Anoka | I3: Twin Cities Metro | J3: 55304 | K3: (763) 413-0032 | L3: 0 | M3: No | N3: 40717 | O3: Andover Family Chiropractic PA | P3: 1043506454 | Q3: Map | R3: Record
A4: Andrews Chiropractic, PA. | B4: Chiropractic | D4: Chiropractic | E4: 3368 Bunker Lake Blvd NW | G4: Andover | H4: Anoka | I4: Twin Cities Metro | J4: 55304 | K4: (763) 427-0820 | L4: 2 | M4: No | N4: 40969 | O4: Andrews Chiropractic, PA. | P4: 1992924526 | Q4: Map | R4: Record
A5: Essentials of Life Chiropractic | B5: Chiropractic | D5: Chiropractic | E5: 15190 Bluebird St NW | F5: Ste 104 | G5: Andover | H5: Anoka | I5: Twin Cities Metro | J5: 55304 | K5: (763) 413-6934 | L5: 1 | M5: No | N5: 42062 | O5: Essentials of Life Chiropractic | P5: 1437541430 | Q5: Map | R5: Record
A6: Sora Pediatric Therapy | B6: Physical Therapy | D6: Physical Therapy | E6: 1891 Station Pkwy NW | G6: Andover | H6: Anoka | I6: Twin Cities Metro | J6: 55304 | K6: (763) 755-4275 | L6: 9 | M6: No | N6: 43472 | O6: Family Speech & Therapy Services, LLC | P6: 1235285966 | Q6: Map | R6: Record
A7: Abeler Chiropractic Clinic, PA | B7: Chiropractic | D7: Chiropractic | E7: 600 E Main St | G7: Anoka | H7: Anoka | I7: Twin Cities Metro | J7: 55303 | K7: (763) 421-3722 | L7: 3 | M7: No | N7: 39883 | O7: Abeler Chiropractic Clinic, PA | P7: 1225251770 | Q7: Map | R7: Record
A8: Anoka Chiropractic, PA. | B8: Chiropractic | D8: Chiropractic | E8: 646 E River Rd | F8: Ste 2 | G8: Anoka | H8: Anoka | I8: Twin Cities Metro | J8: 55303 | K8: (763) 421-1410 | L8: 3 | M8: No | N8: 44065 | O8: Anoka Chiropractic, PA. | P8: 1912055435 | Q8: Map | R8: Record
A9: Anoka Family Wellness | B9: Chiropractic | D9: Chiropractic | E9: 3507 Round Lake Blvd NW | F9: Ste 300 | G9: Anoka | H9: Anoka | I9: Twin Cities Metro | J9: 55303 | K9: (763) 427-2400 | L9: 3 | M9: No | N9: 44291 | O9: Ak Chiropractic | P9: 1770162174 | Q9: Map | R9: Record
A10: Anoka-Andover Chiropractic, PA | B10: Chiropractic | D10: Chiropractic | E10: 3722 7th Ave | G10: Anoka | H10: Anoka | I10: Twin Cities Metro | J10: 55303 | K10: (763) 427-7122 | L10: 2 | M10: No | N10: 39778 | O10: Anoka-Andover Chiropractic, PA | P10: 1184766842 | Q10: Map | R10: Record
A11: Heil Chiropractic Center PA | B11: Chiropractic | D11: Chiropractic | E11: 3507 Round Lake Blvd NW | F11: 300 | G11: Anoka | H11: Anoka | I11: Twin Cities Metro | J11: 55303 | K11: (763) 323-4855 | L11: 3 | M11: No | N11: 43623 | O11: Heil Chiropractic Center PA | P11: 1326246810 | Q11: Map | R11: Record
A12: Manuel Chiropractic Center | B12: Chiropractic | D12: Chiropractic | E12: 2321 7th Ave | G12: Anoka | H12: Anoka | I12: Twin Cities Metro | J12: 55303 | K12: (517) 256-1824 | L12: 0 | M12: No | N12: 39538 | O12: Manuel Chiropractic Center | P12: 1811169832 | Q12: Map | R12: Record
A13: North Country Chiropractic | B13: Chiropractic | D13: Chiropractic | E13: 2321 7th Ave N | G13: Anoka | H13: Anoka | I13: Twin Cities Metro | J13: 55303 | K13: (763) 439-4634 | L13: 1 | M13: No | N13: 40394 | O13: Chad R. Young, DC. PLLC | P13: 1407160294 | Q13: Map | R13: Record
A14: Wellspring Spinal Care, PC | B14: Chiropractic | D14: Chiropractic | E14: 540 Greenhaven Rd | F14: Ste 204 | G14: Anoka | H14: Anoka | I14: Twin Cities Metro | J14: 55303 | K14: (952) 303-9124 | L14: 0 | M14: No | N14: 42313 | O14: Wellspring Spinal Care, PC | P14: 1336512920 | Q14: Map | R14: Record
A15: Blaine Health and Wellness | B15: Chiropractic | D15: Chiropractic | E15: 1360 101st Ave NE | F15: Ste 140 | G15: Blaine | H15: Anoka | I15: Twin Cities Metro | J15: 55449 | K15: (763) 703-3509 | L15: 0 | M15: No | N15: 42304 | O15: Lund Health Professional Corporation | P15: 1194197368 | Q15: Map | R15: Record
A16: Build and Balance Chiropractic Center | B16: Chiropractic | D16: Chiropractic | E16: 12203 Aberdeen St NE | F16: Ste 140 | G16: Blaine | H16: Anoka | I16: Twin Cities Metro | J16: 55449 | K16: (763) 785-4120 | L16: 3 | M16: No | N16: 44065 | O16: Dr. Rebecca R. Jackson LLC | P16: 1821211210 | Q16: Map | R16: Record
A17: Club West Chiropractic | B17: Chiropractic | D17: Chiropractic | E17: 10995 Club West Pkwy | F17: Ste 400 | G17: Blaine | H17: Anoka | I17: Twin Cities Metro | J17: 55449 | K17: (763) 400-4940 | L17: 1 | M17: No | N17: 42171 | O17: Lindstrom Chiropractic Center, PA | P17: 1023499928 | Q17: Map | R17: Record
A18: Community Accident & Injury Center | B18: Chiropractic | D18: Chiropractic | E18: 13060 Central Ave NE | F18: #100 | G18: Blaine | H18: Anoka | I18: Twin Cities Metro | J18: 55434 | K18: (763) 566-8023 | L18: 1 | M18: No | N18: 42234 | O18: Doc Djr PC | P18: 1336515550 | Q18: Map | R18: Record
A19: Community Chiropractic Center | B19: Chiropractic | D19: Chiropractic | E19: 13060 Central Ave NE | F19: Ste 100 | G19: Blaine | H19: Anoka | I19: Twin Cities Metro | J19: 55434 | K19: (763) 566-8023 | L19: 1 | M19: No | N19: 42186 | O19: Verdan PA | P19: 1316127384 | Q19: Map | R19: Record
A20: Coon Rapids Chiropractic Health Services LTD | B20: Chiropractic | D20: Chiropractic | E20: 9140 Baltimore St NE | G20: Blaine | H20: Anoka | I20: Twin Cities Metro | J20: 55449 | K20: (763) 757-7220 | L20: 0 | M20: No | N20: 44065 | O20: Coon Rapids Chiropractic Health Services LTD | P20: 1679614010 | Q20: Map | R20: Record
A21: Corrective Care Chiropractic PC | B21: Chiropractic | D21: Chiropractic | E21: 922 125th Ln NE | G21: Blaine | H21: Anoka | I21: Twin Cities Metro | J21: 55434 | K21: (763) 754-6303 | L21: 1 | M21: No | N21: 44065 | O21: Corrective Care Chiropractic PC | P21: 1417024050 | Q21: Map | R21: Record
A22: Dr. Andrew Brown Chiropracitc PC | B22: Chiropractic | D22: Chiropractic | E22: 12203 Aberdeen St NE | F22: # 140 | G22: Blaine | H22: Anoka | I22: Twin Cities Metro | J22: 55449 | K22: (763) 785-4120 | L22: 3 | M22: No | N22: 39891 | O22: Dr. Andrew Brown Chiropracitc PC | P22: 1568507705 | Q22: Map | R22: Record
A23: Elevated Health Center | B23: Chiropractic | D23: Chiropractic | E23: 10705 Town Square Dr NE | F23: Ste 220 | G23: Blaine | H23: Anoka | I23: Twin Cities Metro | J23: 55449 | K23: (651) 216-1997 | L23: 2 | M23: No | N23: 41836 | O23: Elevated Health Center | P23: 1033526538 | Q23: Map | R23: Record
A24: Empowered Health Chiropractic & Wellness, LLC | B24: Chiropractic | D24: Chiropractic | E24: 12157 Dunkirk St NE | F24: Ste 402 | G24: Blaine | H24: Anoka | I24: Twin Cities Metro | J24: 55449 | K24: (763) 267-1731 | L24: 1 | M24: No | N24: 42215 | O24: Empowered Health Chiropractic & Wellness, LLC | P24: 1780072082 | Q24: Map | R24: Record
